Workbook

Sheet Inputs
A1: OTC Collateral & Margin Call Tracker
A2: Synthetic portfolio for demonstration. Blue cells are inputs; black cells are formulas.
A4: Overnight market moves
A5: Rates move (bp) | B5: 0 | C5: Parallel move in rates, basis points
A6: USD vs basket (%) | B6: 0 | C6: Percent move
A7: Equities (%) | B7: 0 | C7: Percent move
A8: Commodities (%) | B8: 0 | C8: Percent move
A9: Dispute tolerance (% of exposure) | B9: 0.05 | C9: A dispute is raised when our call and the counterparty's differ by more than this, or $500k
A10: Minimum dispute amount ($) | B10: 500000 | C10: Floor for the dispute tolerance
A13: How to use: change the market moves or tolerance; the Margin calls and Collateral sheets update.

Sheet Margin calls
A1: Margin calls by counterparty
A2: Exposure = base MTM + sensitivities × moves. Positive exposure: the counterparty owes us. Deliveries round up, returns round down.
A4: Counterparty | B4: Type | C4: Product | D4: Base exposure ($) | E4: Rates sens. ($/bp) | F4: FX sens. ($/%) | G4: Equity sens. ($/%) | H4: Commodity sens. ($/%) | I4: Threshold ($) | J4: MTA ($) | K4: Rounding ($) | L4: Collateral balance ($) | M4: Their MTM difference ($) | N4: Exposure ($) | O4: Required balance ($) | P4: Movement ($) | Q4: Direction | R4: Call amount ($) | S4: Their movement ($) | T4: Status | U4: Undisputed amount ($)
A5: Aldridge Capital | B5: Hedge fund | C5: Rates swaps | D5: 184000000 | E5: -450000 | F5: 0 | G5: 0 | H5: 0 | I5: 0 | J5: 500000 | K5: 100000 | L5: 150000000 | M5: 1000000 | N5: =D5+E5*Inputs!$B$5+F5*Inputs!$B$6+G5*Inputs!$B$7+H5*Inputs!$B$8 -> 184000000 | O5: =IF(N5>0,MAX(0,N5-I5),-MAX(0,-N5-I5)) -> 184000000 | P5: =O5-L5 -> 34000000 | Q5: =IF(ABS(P5)<J5,IF(ABS(O5)<1,"Under threshold","Below MTA"),IF(P5>0,IF(L5<0,"Recall from counterparty","We call"),IF(L5>0,"Return to counterparty","Counterparty calls us"))) -> We call | R5: =IF(OR(Q5="Under threshold",Q5="Below MTA"),0,IF(OR(Q5="We call",Q5="Counterparty calls us"),ROUNDUP(ROUND(ABS(P5)/K5,6),0),ROUNDDOWN(ROUND(ABS(P5)/K5,6),0))*K5) -> 34000000 | S5: =IF(N5+M5>0,MAX(0,N5+M5-I5),-MAX(0,-(N5+M5)-I5))-L5 -> 35000000 | T5: =IF(R5=0,Q5,IF(ABS(P5-S5)>MAX(Inputs!$B$9*ABS(N5),Inputs!$B$10),"Disputed","Agreed")) -> Agreed | U5: =IF(T5="Disputed",MIN(ABS(P5),ABS(S5)),R5) -> 34000000
A6: Northbay Pension Fund | B6: Pension | C6: Rates swaps | D6: -220000000 | E6: 600000 | F6: 0 | G6: 0 | H6: 0 | I6: 0 | J6: 500000 | K6: 100000 | L6: -195000000 | M6: -500000 | N6: =D6+E6*Inputs!$B$5+F6*Inputs!$B$6+G6*Inputs!$B$7+H6*Inputs!$B$8 -> -220000000 | O6: =IF(N6>0,MAX(0,N6-I6),-MAX(0,-N6-I6)) -> -220000000 | P6: =O6-L6 -> -25000000 | Q6: =IF(ABS(P6)<J6,IF(ABS(O6)<1,"Under threshold","Below MTA"),IF(P6>0,IF(L6<0,"Recall from counterparty","We call"),IF(L6>0,"Return to counterparty","Counterparty calls us"))) -> Counterparty calls us | R6: =IF(OR(Q6="Under threshold",Q6="Below MTA"),0,IF(OR(Q6="We call",Q6="Counterparty calls us"),ROUNDUP(ROUND(ABS(P6)/K6,6),0),ROUNDDOWN(ROUND(ABS(P6)/K6,6),0))*K6) -> 25000000 | S6: =IF(N6+M6>0,MAX(0,N6+M6-I6),-MAX(0,-(N6+M6)-I6))-L6 -> -25500000 | T6: =IF(R6=0,Q6,IF(ABS(P6-S6)>MAX(Inputs!$B$9*ABS(N6),Inputs!$B$10),"Disputed","Agreed")) -> Agreed | U6: =IF(T6="Disputed",MIN(ABS(P6),ABS(S6)),R6) -> 25000000
A7: Kestrel Macro Fund | B7: Hedge fund | C7: FX forwards | D7: 63000000 | E7: 0 | F7: 1800000 | G7: 0 | H7: 0 | I7: 10000000 | J7: 500000 | K7: 100000 | L7: 52700000 | M7: 0 | N7: =D7+E7*Inputs!$B$5+F7*Inputs!$B$6+G7*Inputs!$B$7+H7*Inputs!$B$8 -> 63000000 | O7: =IF(N7>0,MAX(0,N7-I7),-MAX(0,-N7-I7)) -> 53000000 | P7: =O7-L7 -> 300000 | Q7: =IF(ABS(P7)<J7,IF(ABS(O7)<1,"Under threshold","Below MTA"),IF(P7>0,IF(L7<0,"Recall from counterparty","We call"),IF(L7>0,"Return to counterparty","Counterparty calls us"))) -> Below MTA | R7: =IF(OR(Q7="Under threshold",Q7="Below MTA"),0,IF(OR(Q7="We call",Q7="Counterparty calls us"),ROUNDUP(ROUND(ABS(P7)/K7,6),0),ROUNDDOWN(ROUND(ABS(P7)/K7,6),0))*K7) -> 0 | S7: =IF(N7+M7>0,MAX(0,N7+M7-I7),-MAX(0,-(N7+M7)-I7))-L7 -> 300000 | T7: =IF(R7=0,Q7,IF(ABS(P7-S7)>MAX(Inputs!$B$9*ABS(N7),Inputs!$B$10),"Disputed","Agreed")) -> Below MTA | U7: =IF(T7="Disputed",MIN(ABS(P7),ABS(S7)),R7) -> 0
A8: Harbour Insurance | B8: Insurer | C8: Equity options | D8: 112000000 | E8: 0 | F8: 0 | G8: 3200000 | H8: 0 | I8: 20000000 | J8: 1000000 | K8: 100000 | L8: 60000000 | M8: -19000000 | N8: =D8+E8*Inputs!$B$5+F8*Inputs!$B$6+G8*Inputs!$B$7+H8*Inputs!$B$8 -> 112000000 | O8: =IF(N8>0,MAX(0,N8-I8),-MAX(0,-N8-I8)) -> 92000000 | P8: =O8-L8 -> 32000000 | Q8: =IF(ABS(P8)<J8,IF(ABS(O8)<1,"Under threshold","Below MTA"),IF(P8>0,IF(L8<0,"Recall from counterparty","We call"),IF(L8>0,"Return to counterparty","Counterparty calls us"))) -> We call | R8: =IF(OR(Q8="Under threshold",Q8="Below MTA"),0,IF(OR(Q8="We call",Q8="Counterparty calls us"),ROUNDUP(ROUND(ABS(P8)/K8,6),0),ROUNDDOWN(ROUND(ABS(P8)/K8,6),0))*K8) -> 32000000 | S8: =IF(N8+M8>0,MAX(0,N8+M8-I8),-MAX(0,-(N8+M8)-I8))-L8 -> 13000000 | T8: =IF(R8=0,Q8,IF(ABS(P8-S8)>MAX(Inputs!$B$9*ABS(N8),Inputs!$B$10),"Disputed","Agreed")) -> Disputed | U8: =IF(T8="Disputed",MIN(ABS(P8),ABS(S8)),R8) -> 13000000
A9: Solent Asset Management | B9: Asset manager | C9: Repo | D9: -48000000 | E9: 50000 | F9: 0 | G9: 0 | H9: 0 | I9: 0 | J9: 250000 | K9: 100000 | L9: -56000000 | M9: 0 | N9: =D9+E9*Inputs!$B$5+F9*Inputs!$B$6+G9*Inputs!$B$7+H9*Inputs!$B$8 -> -48000000 | O9: =IF(N9>0,MAX(0,N9-I9),-MAX(0,-N9-I9)) -> -48000000 | P9: =O9-L9 -> 8000000 | Q9: =IF(ABS(P9)<J9,IF(ABS(O9)<1,"Under threshold","Below MTA"),IF(P9>0,IF(L9<0,"Recall from counterparty","We call"),IF(L9>0,"Return to counterparty","Counterparty calls us"))) -> Recall from counterparty | R9: =IF(OR(Q9="Under threshold",Q9="Below MTA"),0,IF(OR(Q9="We call",Q9="Counterparty calls us"),ROUNDUP(ROUND(ABS(P9)/K9,6),0),ROUNDDOWN(ROUND(ABS(P9)/K9,6),0))*K9) -> 8000000 | S9: =IF(N9+M9>0,MAX(0,N9+M9-I9),-MAX(0,-(N9+M9)-I9))-L9 -> 8000000 | T9: =IF(R9=0,Q9,IF(ABS(P9-S9)>MAX(Inputs!$B$9*ABS(N9),Inputs!$B$10),"Disputed","Agreed")) -> Agreed | U9: =IF(T9="Disputed",MIN(ABS(P9),ABS(S9)),R9) -> 8000000
A10: Meridian Bank | B10: Bank | C10: Rates and FX | D10: 21000000 | E10: -200000 | F10: 500000 | G10: 0 | H10: 0 | I10: 100000000 | J10: 1000000 | K10: 100000 | L10: 0 | M10: 0 | N10: =D10+E10*Inputs!$B$5+F10*Inputs!$B$6+G10*Inputs!$B$7+H10*Inputs!$B$8 -> 21000000 | O10: =IF(N10>0,MAX(0,N10-I10),-MAX(0,-N10-I10)) -> 0 | P10: =O10-L10 -> 0 | Q10: =IF(ABS(P10)<J10,IF(ABS(O10)<1,"Under threshold","Below MTA"),IF(P10>0,IF(L10<0,"Recall from counterparty","We call"),IF(L10>0,"Return to counterparty","Counterparty calls us"))) -> Under threshold | R10: =IF(OR(Q10="Under threshold",Q10="Below MTA"),0,IF(OR(Q10="We call",Q10="Counterparty calls us"),ROUNDUP(ROUND(ABS(P10)/K10,6),0),ROUNDDOWN(ROUND(ABS(P10)/K10,6),0))*K10) -> 0 | S10: =IF(N10+M10>0,MAX(0,N10+M10-I10),-MAX(0,-(N10+M10)-I10))-L10 -> 0 | T10: =IF(R10=0,Q10,IF(ABS(P10-S10)>MAX(Inputs!$B$9*ABS(N10),Inputs!$B$10),"Disputed","Agreed")) -> Under threshold | U10: =IF(T10="Disputed",MIN(ABS(P10),ABS(S10)),R10) -> 0
A11: Tarn Energy Trading | B11: Commodity trader | C11: Commodity swaps | D11: 145000000 | E11: 0 | F11: 0 | G11: 0 | H11: 4000000 | I11: 30000000 | J11: 500000 | K11: 100000 | L11: 90000000 | M11: 1500000 | N11: =D11+E11*Inputs!$B$5+F11*Inputs!$B$6+G11*Inputs!$B$7+H11*Inputs!$B$8 -> 145000000 | O11: =IF(N11>0,MAX(0,N11-I11),-MAX(0,-N11-I11)) -> 115000000 | P11: =O11-L11 -> 25000000 | Q11: =IF(ABS(P11)<J11,IF(ABS(O11)<1,"Under threshold","Below MTA"),IF(P11>0,IF(L11<0,"Recall from counterparty","We call"),IF(L11>0,"Return to counterparty","Counterparty calls us"))) -> We call | R11: =IF(OR(Q11="Under threshold",Q11="Below MTA"),0,IF(OR(Q11="We call",Q11="Counterparty calls us"),ROUNDUP(ROUND(ABS(P11)/K11,6),0),ROUNDDOWN(ROUND(ABS(P11)/K11,6),0))*K11) -> 25000000 | S11: =IF(N11+M11>0,MAX(0,N11+M11-I11),-MAX(0,-(N11+M11)-I11))-L11 -> 26500000 | T11: =IF(R11=0,Q11,IF(ABS(P11-S11)>MAX(Inputs!$B$9*ABS(N11),Inputs!$B$10),"Disputed","Agreed")) -> Agreed | U11: =IF(T11="Disputed",MIN(ABS(P11),ABS(S11)),R11) -> 25000000
A12: Vale Corporate Treasury | B12: Corporate | C12: FX forwards | D12: -32000000 | E12: 0 | F12: -1500000 | G12: 0 | H12: 0 | I12: 20000000 | J12: 1000000 | K12: 100000 | L12: 0 | M12: 0 | N12: =D12+E12*Inputs!$B$5+F12*Inputs!$B$6+G12*Inputs!$B$7+H12*Inputs!$B$8 -> -32000000 | O12: =IF(N12>0,MAX(0,N12-I12),-MAX(0,-N12-I12)) -> -12000000 | P12: =O12-L12 -> -12000000 | Q12: =IF(ABS(P12)<J12,IF(ABS(O12)<1,"Under threshold","Below MTA"),IF(P12>0,IF(L12<0,"Recall from counterparty","We call"),IF(L12>0,"Return to counterparty","Counterparty calls us"))) -> Counterparty calls us | R12: =IF(OR(Q12="Under threshold",Q12="Below MTA"),0,IF(OR(Q12="We call",Q12="Counterparty calls us"),ROUNDUP(ROUND(ABS(P12)/K12,6),0),ROUNDDOWN(ROUND(ABS(P12)/K12,6),0))*K12) -> 12000000 | S12: =IF(N12+M12>0,MAX(0,N12+M12-I12),-MAX(0,-(N12+M12)-I12))-L12 -> -12000000 | T12: =IF(R12=0,Q12,IF(ABS(P12-S12)>MAX(Inputs!$B$9*ABS(N12),Inputs!$B$10),"Disputed","Agreed")) -> Agreed | U12: =IF(T12="Disputed",MIN(ABS(P12),ABS(S12)),R12) -> 12000000
A14: Summary
A15: Calls today | B15: =COUNTIF(R5:R12,">0") -> 6
A16: Collateral due in ($) | B16: =SUMIFS(R5:R12,Q5:Q12,"We call")+SUMIFS(R5:R12,Q5:Q12,"Recall from counterparty") -> 99000000
A17: Collateral due out ($) | B17: =SUMIFS(R5:R12,Q5:Q12,"Counterparty calls us")+SUMIFS(R5:R12,Q5:Q12,"Return to counterparty") -> 37000000
A18: Disputes | B18: =COUNTIF(T5:T12,"Disputed") -> 1
A19: Amount in dispute ($) | B19: =SUMPRODUCT((T5:T12="Disputed")*(R5:R12-U5:U12)) -> 19000000
A21: Sensitivities: rates in $ per basis point, others in $ per 1% move. Their MTM difference = counterparty's valuation minus ours.

Sheet Collateral
A1: Collateral we post: cheapest to deliver
A2: For each call we must meet, pick the eligible asset with the lowest cost per unit of collateral value after haircut. Inventory assumed sufficient.
A4: Asset | B4: Haircut | C4: Cost (bp a year) | D4: Cost per unit of value (bp)
A5: Cash (USD) | B5: 0 | C5: 45 | D5: =C5/(1-B5) -> 45
A6: US Treasuries | B6: 0.01 | C6: 12 | D6: =C6/(1-B6) -> 12.121212
A7: German Bunds | B7: 0.02 | C7: 15 | D7: =C7/(1-B7) -> 15.306122
A8: IG corporate bonds | B8: 0.08 | C8: 30 | D8: =C8/(1-B8) -> 32.608696
A9: Main-index equities | B9: 0.15 | C9: 60 | D9: =C9/(1-B9) -> 70.588235
A11: Eligibility by counterparty (from each CSA): Y = eligible
A12: Counterparty | B12: Cash (USD) | C12: US Treasuries | D12: German Bunds | E12: IG corporate bonds | F12: Main-index equities | G12: Call to meet ($) | H12: Cheapest eligible asset | I12: Market value to deliver ($) | J12: Annual cost ($) | K12: Cost if all cash ($)
A13: Aldridge Capital | B13: Y | C13: Y | D13: Y | E13: N | F13: N | G13: =IF('Margin calls'!Q5="Counterparty calls us",'Margin calls'!R5,0) -> 0 | H13: =IF(G13=0,"-",INDEX($A$5:$A$9,MATCH(MIN(IF(B13="Y",$D$5,1000000000),IF(C13="Y",$D$6,1000000000),IF(D13="Y",$D$7,1000000000),IF(E13="Y",$D$8,1000000000),IF(F13="Y",$D$9,1000000000)),CHOOSE({1,2,3,4,5},IF(B13="Y",$D$5,1000000000),IF(C13="Y",$D$6,1000000000),IF(D13="Y",$D$7,1000000000),IF(E13="Y",$D$8,1000000000),IF(F13="Y",$D$9,1000000000)),0))) -> - | I13: =IF(G13=0,0,G13/(1-INDEX($B$5:$B$9,MATCH(H13,$A$5:$A$9,0)))) -> 0 | J13: =IF(G13=0,0,I13*INDEX($C$5:$C$9,MATCH(H13,$A$5:$A$9,0))/10000) -> 0 | K13: =G13*$C$5/10000 -> 0
A14: Northbay Pension Fund | B14: Y | C14: Y | D14: Y | E14: N | F14: N | G14: =IF('Margin calls'!Q6="Counterparty calls us",'Margin calls'!R6,0) -> 25000000 | H14: =IF(G14=0,"-",INDEX($A$5:$A$9,MATCH(MIN(IF(B14="Y",$D$5,1000000000),IF(C14="Y",$D$6,1000000000),IF(D14="Y",$D$7,1000000000),IF(E14="Y",$D$8,1000000000),IF(F14="Y",$D$9,1000000000)),CHOOSE({1,2,3,4,5},IF(B14="Y",$D$5,1000000000),IF(C14="Y",$D$6,1000000000),IF(D14="Y",$D$7,1000000000),IF(E14="Y",$D$8,1000000000),IF(F14="Y",$D$9,1000000000)),0))) -> US Treasuries | I14: =IF(G14=0,0,G14/(1-INDEX($B$5:$B$9,MATCH(H14,$A$5:$A$9,0)))) -> 25252525 | J14: =IF(G14=0,0,I14*INDEX($C$5:$C$9,MATCH(H14,$A$5:$A$9,0))/10000) -> 30303.03 | K14: =G14*$C$5/10000 -> 112500
A15: Kestrel Macro Fund | B15: Y | C15: Y | D15: N | E15: N | F15: N | G15: =IF('Margin calls'!Q7="Counterparty calls us",'Margin calls'!R7,0) -> 0 | H15: =IF(G15=0,"-",INDEX($A$5:$A$9,MATCH(MIN(IF(B15="Y",$D$5,1000000000),IF(C15="Y",$D$6,1000000000),IF(D15="Y",$D$7,1000000000),IF(E15="Y",$D$8,1000000000),IF(F15="Y",$D$9,1000000000)),CHOOSE({1,2,3,4,5},IF(B15="Y",$D$5,1000000000),IF(C15="Y",$D$6,1000000000),IF(D15="Y",$D$7,1000000000),IF(E15="Y",$D$8,1000000000),IF(F15="Y",$D$9,1000000000)),0))) -> - | I15: =IF(G15=0,0,G15/(1-INDEX($B$5:$B$9,MATCH(H15,$A$5:$A$9,0)))) -> 0 | J15: =IF(G15=0,0,I15*INDEX($C$5:$C$9,MATCH(H15,$A$5:$A$9,0))/10000) -> 0 | K15: =G15*$C$5/10000 -> 0
A16: Harbour Insurance | B16: Y | C16: Y | D16: Y | E16: Y | F16: N | G16: =IF('Margin calls'!Q8="Counterparty calls us",'Margin calls'!R8,0) -> 0 | H16: =IF(G16=0,"-",INDEX($A$5:$A$9,MATCH(MIN(IF(B16="Y",$D$5,1000000000),IF(C16="Y",$D$6,1000000000),IF(D16="Y",$D$7,1000000000),IF(E16="Y",$D$8,1000000000),IF(F16="Y",$D$9,1000000000)),CHOOSE({1,2,3,4,5},IF(B16="Y",$D$5,1000000000),IF(C16="Y",$D$6,1000000000),IF(D16="Y",$D$7,1000000000),IF(E16="Y",$D$8,1000000000),IF(F16="Y",$D$9,1000000000)),0))) -> - | I16: =IF(G16=0,0,G16/(1-INDEX($B$5:$B$9,MATCH(H16,$A$5:$A$9,0)))) -> 0 | J16: =IF(G16=0,0,I16*INDEX($C$5:$C$9,MATCH(H16,$A$5:$A$9,0))/10000) -> 0 | K16: =G16*$C$5/10000 -> 0
A17: Solent Asset Management | B17: Y | C17: Y | D17: Y | E17: Y | F17: Y | G17: =IF('Margin calls'!Q9="Counterparty calls us",'Margin calls'!R9,0) -> 0 | H17: =IF(G17=0,"-",INDEX($A$5:$A$9,MATCH(MIN(IF(B17="Y",$D$5,1000000000),IF(C17="Y",$D$6,1000000000),IF(D17="Y",$D$7,1000000000),IF(E17="Y",$D$8,1000000000),IF(F17="Y",$D$9,1000000000)),CHOOSE({1,2,3,4,5},IF(B17="Y",$D$5,1000000000),IF(C17="Y",$D$6,1000000000),IF(D17="Y",$D$7,1000000000),IF(E17="Y",$D$8,1000000000),IF(F17="Y",$D$9,1000000000)),0))) -> - | I17: =IF(G17=0,0,G17/(1-INDEX($B$5:$B$9,MATCH(H17,$A$5:$A$9,0)))) -> 0 | J17: =IF(G17=0,0,I17*INDEX($C$5:$C$9,MATCH(H17,$A$5:$A$9,0))/10000) -> 0 | K17: =G17*$C$5/10000 -> 0
A18: Meridian Bank | B18: Y | C18: Y | D18: Y | E18: N | F18: N | G18: =IF('Margin calls'!Q10="Counterparty calls us",'Margin calls'!R10,0) -> 0 | H18: =IF(G18=0,"-",INDEX($A$5:$A$9,MATCH(MIN(IF(B18="Y",$D$5,1000000000),IF(C18="Y",$D$6,1000000000),IF(D18="Y",$D$7,1000000000),IF(E18="Y",$D$8,1000000000),IF(F18="Y",$D$9,1000000000)),CHOOSE({1,2,3,4,5},IF(B18="Y",$D$5,1000000000),IF(C18="Y",$D$6,1000000000),IF(D18="Y",$D$7,1000000000),IF(E18="Y",$D$8,1000000000),IF(F18="Y",$D$9,1000000000)),0))) -> - | I18: =IF(G18=0,0,G18/(1-INDEX($B$5:$B$9,MATCH(H18,$A$5:$A$9,0)))) -> 0 | J18: =IF(G18=0,0,I18*INDEX($C$5:$C$9,MATCH(H18,$A$5:$A$9,0))/10000) -> 0 | K18: =G18*$C$5/10000 -> 0
A19: Tarn Energy Trading | B19: Y | C19: Y | D19: N | E19: N | F19: N | G19: =IF('Margin calls'!Q11="Counterparty calls us",'Margin calls'!R11,0) -> 0 | H19: =IF(G19=0,"-",INDEX($A$5:$A$9,MATCH(MIN(IF(B19="Y",$D$5,1000000000),IF(C19="Y",$D$6,1000000000),IF(D19="Y",$D$7,1000000000),IF(E19="Y",$D$8,1000000000),IF(F19="Y",$D$9,1000000000)),CHOOSE({1,2,3,4,5},IF(B19="Y",$D$5,1000000000),IF(C19="Y",$D$6,1000000000),IF(D19="Y",$D$7,1000000000),IF(E19="Y",$D$8,1000000000),IF(F19="Y",$D$9,1000000000)),0))) -> - | I19: =IF(G19=0,0,G19/(1-INDEX($B$5:$B$9,MATCH(H19,$A$5:$A$9,0)))) -> 0 | J19: =IF(G19=0,0,I19*INDEX($C$5:$C$9,MATCH(H19,$A$5:$A$9,0))/10000) -> 0 | K19: =G19*$C$5/10000 -> 0
A20: Vale Corporate Treasury | B20: Y | C20: N | D20: N | E20: N | F20: N | G20: =IF('Margin calls'!Q12="Counterparty calls us",'Margin calls'!R12,0) -> 12000000 | H20: =IF(G20=0,"-",INDEX($A$5:$A$9,MATCH(MIN(IF(B20="Y",$D$5,1000000000),IF(C20="Y",$D$6,1000000000),IF(D20="Y",$D$7,1000000000),IF(E20="Y",$D$8,1000000000),IF(F20="Y",$D$9,1000000000)),CHOOSE({1,2,3,4,5},IF(B20="Y",$D$5,1000000000),IF(C20="Y",$D$6,1000000000),IF(D20="Y",$D$7,1000000000),IF(E20="Y",$D$8,1000000000),IF(F20="Y",$D$9,1000000000)),0))) -> Cash (USD) | I20: =IF(G20=0,0,G20/(1-INDEX($B$5:$B$9,MATCH(H20,$A$5:$A$9,0)))) -> 12000000 | J20: =IF(G20=0,0,I20*INDEX($C$5:$C$9,MATCH(H20,$A$5:$A$9,0))/10000) -> 54000 | K20: =G20*$C$5/10000 -> 54000
A22: Totals | G22: =SUM(G13:G20) -> 37000000 | I22: =SUM(I13:I20) -> 37252525 | J22: =SUM(J13:J20) -> 84303.03 | K22: =SUM(K13:K20) -> 166500
A23: Annual saving vs posting cash ($) | B23: =K22-J22 -> 82196.97
