Workbook

Sheet Client Details
A1: CLIENT DETAILS
A3: CLIENT RISK PROFILE: DEVEN | D3: Parameter (Q Responses) | E3: Response | G3: RATIONALE FOR (A=1)
A4: Age | B4: 24 | D4: Q1 Self-Placement on Risk Scale | E4: Seeker | G4: Deven (A=1): Derived from 6 Risk Seeker answers out of 7 questions. Deven self-identifies as a risk seeker (Q1), prioritizes capital growth (Q2), has high risk capacity (Q3), focuses on gains over losses (Q4), has a long cash horizon (Q5), and holds/buys during market drops (Q6).
A5: Investment Objective | B5: Long Term Wealth Creation | D5: Q2 Investment Objectives | E5: Seeker
A6: Primary Financial Goal | B6: Starting a Cafe | D6: Q3 Risk Capacity | E6: Seeker
A7: Goal Target Amount (Rs) | B7: 6000000 | D7: Q4 Loss vs Gain Focus | E7: Seeker
A8: Years to Goal | B8: 15 | D8: Q5 Cash Need Horizon | E8: Seeker
A9: Monthly SIP Capacity (Rs) | B9: 10000 | D9: Q6 Portfolio Drop Reaction | E9: Seeker
A10: Required Annual Return (goal-implied) | B10: 0.1482 | D10: Q7 Risk Taking Ability | E10: Averse
A11: Investment Horizon (yrs) | B11: 35 | D11: Risk Aversion Count | E11: 1
A12: Liquidity Requirement | B12: Low | D12: Risk Seeker Count | E12: 6
A13: Max Acceptable 1-yr Loss | B13: 0.2 | D13: Derived A Score | E13: 1
A14: Risk Aversion Coefficient (A) | B14: 1 (Check Right Table)
A15: Risk Profile Band | B15: Aggressive
A17: CLIENT RISK PROFILE: JAI KUMAR AGARWAL | D17: Parameter (Q Responses) | E17: Response | G17: RATIONALE FOR (A=1)
A18: Age | B18: 23 | D18: Q1 Self-Placement on Risk Scale | E18: Seeker | G18: Jai (A=1): Derived from 6 Risk Seeker answers. Identifies as a seeker across all objectives, capacity, and loss-reaction parameters, showing maximum willingness to absorb short-term volatility for long-term compounding.
A19: Investment Objective | B19: Wealth Creation | D19: Q2 Investment Objectives | E19: Seeker
A20: Primary Financial Goal | B20: Retirement | D20: Q3 Risk Capacity | E20: Averse
A21: Goal Target Amount (Rs) | B21: 120000000 | D21: Q4 Loss vs Gain Focus | E21: Seeker
A22: Years to Goal | B22: 30 | D22: Q5 Cash Need Horizon | E22: Seeker
A23: Monthly SIP Capacity (Rs) | B23: 20000 | D23: Q6 Portfolio Drop Reaction | E23: Seeker
A24: Required Annual Return (goal-implied) | B24: 0.1537 | D24: Q7 Risk Taking Ability | E24: Seeker
A25: Investment Horizon (yrs) | B25: 37 | D25: Risk Aversion Count | E25: 1
A26: Liquidity Requirement | B26: Medium | D26: Risk Seeker Count | E26: 6
A27: Max Acceptable 1-yr Loss | B27: 0.2 | D27: Derived A Score | E27: 1
A28: Risk Aversion Coefficient (A) | B28: 1 (Check Right Table)
A29: Risk Profile Band | B29: Aggressive
A31: CLIENT RISK PROFILE: MANIK RATTY | D31: Parameter (Q Responses) | E31: Response | G31: RATIONALE FOR (A=3)
A32: Age | B32: 24 | D32: Q1 Self-Placement on Risk Scale | E32: Seeker | G32: Manik (A=3): Derived from a balanced profile (4 Seeker vs. 3 Averse answers). Displays high return aspirations (Q1, Q2) but moderate loss sensitivity (Q4) and cash horizon constraints (Q5), placing him squarely in the Moderate risk band.
A33: Investment Objective | B33: Wealth Creation | D33: Q2 Investment Objectives | E33: Seeker
A34: Primary Financial Goal | B34: Retirement | D34: Q3 Risk Capacity | E34: Averse
A35: Goal Target Amount (Rs) | B35: 30000000 | D35: Q4 Loss vs Gain Focus | E35: Averse
A36: Years to Goal | B36: 20 | D36: Q5 Cash Need Horizon | E36: Averse
A37: Monthly SIP Capacity (Rs) | B37: 10000 | D37: Q6 Portfolio Drop Reaction | E37: Seeker
A38: Required Annual Return (goal-implied) | B38: 0.2165 | D38: Q7 Risk Taking Ability | E38: Seeker
A39: Investment Horizon (yrs) | B39: 30 | D39: Risk Aversion Count | E39: 3
A40: Liquidity Requirement | B40: Low | D40: Risk Seeker Count | E40: 4
A41: Max Acceptable 1-yr Loss | B41: 0.3 | D41: Derived A Score | E41: 3
A42: Risk Aversion Coefficient (A) | B42: 3
A43: Risk Profile Band | B43: Moderate
A45: CLIENT RISK PROFILE: TARANA BANSAL | D45: Parameter (Q Responses) | E45: Response | G45: RATIONALE FOR (A=3)
A46: Age | B46: 22 | D46: Q1 Self-Placement on Risk Scale | E46: Seeker | G46: Tarana (A=3): Derived from 4 Seeker vs. 3 Averse answers. Desires capital growth (Q2) but exhibits aversion to sharp drawdowns (Q6) and medium-term liquidity needs (Q5)
A47: Investment Objective | B47: Wealth Creation and House Purchase | D47: Q2 Investment Objectives | E47: Seeker
A48: Primary Financial Goal | B48: Wealth / Money | D48: Q3 Risk Capacity | E48: Averse
A49: Goal Target Amount (Rs) | B49: 5000000 | D49: Q4 Loss vs Gain Focus | E49: Seeker
A50: Years to Goal | B50: 10 | D50: Q5 Cash Need Horizon | E50: Averse
A51: Monthly SIP Capacity (Rs) | B51: 25000 | D51: Q6 Portfolio Drop Reaction | E51: Averse
A52: Required Annual Return (goal-implied) | B52: 0.1001 | D52: Q7 Risk Taking Ability | E52: Seeker
A53: Investment Horizon (yrs) | B53: 40 | D53: Risk Aversion Count | E53: 3
A54: Liquidity Requirement | B54: Low | D54: Risk Seeker Count | E54: 4
A55: Max Acceptable 1-yr Loss | B55: 0.25 | D55: Derived A Score | E55: 3
A56: Risk Aversion Coefficient (A) | B56: 3
A57: Risk Profile Band | B57: Moderate
A59: CLIENT RISK PROFILE: PARTH GUPTA | D59: Parameter (Q Responses) | E59: Response | G59: RATIONALE FOR (A=4)
A60: Age | B60: 23 | D60: Q1 Self-Placement on Risk Scale | E60: Averse | G60: Parth (A=4): Derived from 4 Risk Averse answers. Self-identifies as risk-averse (Q1), prioritizes capital preservation (Q2), and prefers lower-volatility investments to avoid paper losses (Q6, Q7)
A61: Investment Objective | B61: Long-term Wealth Creation | D61: Q2 Investment Objectives | E61: Averse
A62: Primary Financial Goal | B62: Wealth Creation | D62: Q3 Risk Capacity | E62: Seeker
A63: Goal Target Amount (Rs) | B63: 50000000 | D63: Q4 Loss vs Gain Focus | E63: Seeker
A64: Years to Goal | B64: 30 | D64: Q5 Cash Need Horizon | E64: Seeker
A65: Monthly SIP Capacity (Rs) | B65: 5000 | D65: Q6 Portfolio Drop Reaction | E65: Averse
A66: Required Annual Return (goal-implied) | B66: 0.1788 | D66: Q7 Risk Taking Ability | E66: Averse
A67: Investment Horizon (yrs) | B67: 40 | D67: Risk Aversion Count | E67: 4
A68: Liquidity Requirement | B68: Low | D68: Risk Seeker Count | E68: 3
A69: Max Acceptable 1-yr Loss | B69: 0.2 | D69: Derived A Score | E69: 3
A70: Risk Aversion Coefficient (A) | B70: 4
A71: Risk Profile Band | B71: Moderate

Sheet 1. Investment Universe
A1: SHEET 1 - INVESTMENT ALTERNATIVES (14-asset marked)
A2: Expected Return / SD are the faculty-prescribed Table 2 values. Ranked by risk-adjusted return, Sharpe-style, rf=7.5%.
A4: Rank | B4: Asset Class | C4: Category | D4: Expected Return | E4: Standard Deviation | F4: Return/Risk Ratio | G4: Clients Aware (of 5) | H4: Suitability Note
A5: 1 | B5: Equity - Small Cap | C5: Equity | D5: 0.2 | E5: 0.25 | F5: =(D5-0.075)/E5 -> 0.5 | G5: 5 | H5: Moderate risk
A6: 2 | B6: Equity - Mid Cap | C6: Equity | D6: 0.18 | E6: 0.22 | F6: =(D6-0.075)/E6 -> 0.47727273 | G6: 5 | H6: Moderate risk
A7: 3 | B7: Long-Short AIF | C7: Alternatives | D7: 0.25 | E7: 0.4 | F7: =(D7-0.075)/E7 -> 0.4375 | G7: 3 | H7: High risk - Aggressive only
A8: 4 | B8: Mutual Fund - Large & Mid Cap | C8: Equity | D8: 0.14 | E8: 0.15 | F8: =(D8-0.075)/E8 -> 0.43333333 | G8: 5 | H8: Moderate risk
A9: 5 | B9: Multi-Asset Allocation Fund | C9: Multi-Asset | D9: 0.1278 | E9: 0.13 | F9: =(D9-0.075)/E9 -> 0.40615385 | G9: 4 | H9: Moderate risk
A10: 6 | B10: Gold Commodity | C10: Commodities | D10: 0.12 | E10: 0.12 | F10: =(D10-0.075)/E10 -> 0.375 | G10: 5 | H10: Moderate risk
A11: 7 | B11: Equity - Large Cap | C11: Equity | D11: 0.13 | E11: 0.17 | F11: =(D11-0.075)/E11 -> 0.32352941 | G11: 5 | H11: Moderate risk
A12: 8 | B12: ULIPs | C12: Retirement / Long-term | D12: 0.11 | E12: 0.11 | F12: =(D12-0.075)/E12 -> 0.31818182 | G12: 0 | H12: Moderate risk; Zero client awareness - advisor education needed if recommended
A13: 9 | B13: Child Education Plan | C13: Retirement / Long-term | D13: 0.11 | E13: 0.11 | F13: =(D13-0.075)/E13 -> 0.31818182 | G13: 0 | H13: Moderate risk; Zero client awareness - advisor education needed if recommended
A14: 10 | B14: Corporate Bonds | C14: Fixed Income | D14: 0.09 | E14: 0.05 | F14: =(D14-0.075)/E14 -> 0.3 | G14: 4 | H14: Low risk - all profiles
A15: 11 | B15: Embassy Office Parks REIT | C15: REITs | D15: 0.11 | E15: 0.16 | F15: =(D15-0.075)/E15 -> 0.21875 | G15: 3 | H15: Moderate risk
A16: 12 | B16: Hybrid Debt Fund | C16: Fixed Income | D16: 0.08 | E16: 0.05 | F16: =(D16-0.075)/E16 -> 0.1 | G16: 0 | H16: Low risk - all profiles; Zero client awareness - advisor education needed if recommended
... A18: 14 | B18: Government Bonds | C18: Fixed Income | D18: 0.075 | E18: 0.02 | F18: =(D18-0.075)/E18 -> 0 | G18: 5 | H18: Low risk - all profiles

Sheet 2. Correlation Matrix
A1: SHEET 2: CORRELATION & COVARIANCE MATRIX (10 correlation-linked assets)
A5: CORRELATION MATRIX | B5: Government Bonds | C5: Corporate Bonds | D5: Equity - Large Cap | E5: Mutual Fund - L&M Cap | F5: Embassy REIT | G5: Equity - Small Cap | H5: Equity - Mid Cap | I5: Gold Commodity | J5: Multi-Asset Allocation Fund | K5: Long-Short AIF
A6: Government Bonds | B6: 1 | C6: 0.9194 | D6: 0.118 | E6: 0.0911 | F6: 0.2596 | G6: 0.0479 | H6: 0.0867 | I6: 0.2438 | J6: 0.2631 | K6: 0.05
A7: Corporate Bonds | B7: 0.9194 | C7: 1 | D7: 0.2314 | E7: 0.2078 | F7: 0.3349 | G7: 0.1681 | H7: 0.2116 | I7: 0.1886 | J7: 0.3618 | K7: 0.1
A8: Equity - Large Cap | B8: 0.118 | C8: 0.2314 | D8: 1 | E8: 0.927 | F8: 0.5041 | G8: 0.8236 | H8: 0.9038 | I8: -0.1105 | J8: 0.9447 | K8: 0.45
A9: Mutual Fund - L&M Cap | B9: 0.0911 | C9: 0.2078 | D9: 0.927 | E9: 1 | F9: 0.5062 | G9: 0.8461 | H9: 0.8955 | I9: -0.1592 | J9: 0.858 | K9: 0.45
A10: Embassy REIT | B10: 0.2596 | C10: 0.3349 | D10: 0.5041 | E10: 0.5062 | F10: 1 | G10: 0.4982 | H10: 0.474 | I10: 0.0303 | J10: 0.5204 | K10: 0.3
A11: Equity - Small Cap | B11: 0.0479 | C11: 0.1681 | D11: 0.8236 | E11: 0.8461 | F11: 0.4982 | G11: 1 | H11: 0.9537 | I11: -0.1919 | J11: 0.7457 | K11: 0.4
A12: Equity - Mid Cap | B12: 0.0867 | C12: 0.2116 | D12: 0.9038 | E12: 0.8955 | F12: 0.474 | G12: 0.9537 | H12: 1 | I12: -0.2289 | J12: 0.815 | K12: 0.45
A13: Gold Commodity | B13: 0.2438 | C13: 0.1886 | D13: -0.1105 | E13: -0.1592 | F13: 0.0303 | G13: -0.1919 | H13: -0.2289 | I13: 1 | J13: 0.212 | K13: 0.05
A14: Multi-Asset Allocation Fund | B14: 0.2631 | C14: 0.3618 | D14: 0.9447 | E14: 0.858 | F14: 0.5204 | G14: 0.7457 | H14: 0.815 | I14: 0.212 | J14: 1 | K14: 0.45
A15: Long-Short AIF | B15: 0.05 | C15: 0.1 | D15: 0.45 | E15: 0.45 | F15: 0.3 | G15: 0.4 | H15: 0.45 | I15: 0.05 | J15: 0.45 | K15: 1
A18: EXPECTED RETURN / STANDARD DEVIATION (used for portfolio math on this sheet's assets)
A19: Asset | B19: Expected Return | C19: Standard Deviation
A20: Government Bonds | B20: 0.075 | C20: 0.02
A21: Corporate Bonds | B21: 0.09 | C21: 0.05
A22: Equity - Large Cap | B22: 0.13 | C22: 0.17
A23: Mutual Fund - L&M Cap | B23: 0.14 | C23: 0.15
A24: Embassy REIT | B24: 0.11 | C24: 0.16
A25: Equity - Small Cap | B25: 0.2 | C25: 0.25
A26: Equity - Mid Cap | B26: 0.18 | C26: 0.22
A27: Gold Commodity | B27: 0.12 | C27: 0.12
A28: Multi-Asset Allocation Fund | B28: 0.1278 | C28: 0.13
A29: Long-Short AIF | B29: 0.25 | C29: 0.4
A33: COVARIANCE MATRIX (= Correlation x SD_i x SD_j, formula-linked to tables above) | B33: Government Bonds | C33: Corporate Bonds | D33: Equity - Large Cap | E33: Mutual Fund - L&M Cap | F33: Embassy REIT | G33: Equity - Small Cap | H33: Equity - Mid Cap | I33: Gold Commodity | J33: Multi-Asset Allocation Fund | K33: Long-Short AIF
A34: Government Bonds | B34: =B6*C20*C20 -> 0.0004 | C34: =C6*C20*C21 -> 0.0009194 | D34: =D6*C20*C22 -> 0.0004012 | E34: =E6*C20*C23 -> 0.0002733 | F34: =F6*C20*C24 -> 0.00083072 | G34: =G6*C20*C25 -> 0.0002395 | H34: =H6*C20*C26 -> 0.00038148 | I34: =I6*C20*C27 -> 0.00058512 | J34: =J6*C20*C28 -> 0.00068406 | K34: =K6*C20*C29 -> 0.0004
A35: Corporate Bonds | B35: =B7*C21*C20 -> 0.0009194 | C35: =C7*C21*C21 -> 0.0025 | D35: =D7*C21*C22 -> 0.0019669 | E35: =E7*C21*C23 -> 0.0015585 | F35: =F7*C21*C24 -> 0.0026792 | G35: =G7*C21*C25 -> 0.00210125 | H35: =H7*C21*C26 -> 0.0023276 | I35: =I7*C21*C27 -> 0.0011316 | J35: =J7*C21*C28 -> 0.0023517 | K35: =K7*C21*C29 -> 0.002
A36: Equity - Large Cap | B36: =B8*C22*C20 -> 0.0004012 | C36: =C8*C22*C21 -> 0.0019669 | D36: =D8*C22*C22 -> 0.0289 | E36: =E8*C22*C23 -> 0.0236385 | F36: =F8*C22*C24 -> 0.01371152 | G36: =G8*C22*C25 -> 0.035003 | H36: =H8*C22*C26 -> 0.03380212 | I36: =I8*C22*C27 -> -0.0022542 | J36: =J8*C22*C28 -> 0.02087787 | K36: =K8*C22*C29 -> 0.0306
A37: Mutual Fund - L&M Cap | B37: =B9*C23*C20 -> 0.0002733 | C37: =C9*C23*C21 -> 0.0015585 | D37: =D9*C23*C22 -> 0.0236385 | E37: =E9*C23*C23 -> 0.0225 | F37: =F9*C23*C24 -> 0.0121488 | G37: =G9*C23*C25 -> 0.03172875 | H37: =H9*C23*C26 -> 0.0295515 | I37: =I9*C23*C27 -> -0.0028656 | J37: =J9*C23*C28 -> 0.016731 | K37: =K9*C23*C29 -> 0.027
A38: Embassy REIT | B38: =B10*C24*C20 -> 0.00083072 | C38: =C10*C24*C21 -> 0.0026792 | D38: =D10*C24*C22 -> 0.01371152 | E38: =E10*C24*C23 -> 0.0121488 | F38: =F10*C24*C24 -> 0.0256 | G38: =G10*C24*C25 -> 0.019928 | H38: =H10*C24*C26 -> 0.0166848 | I38: =I10*C24*C27 -> 0.00058176 | J38: =J10*C24*C28 -> 0.01082432 | K38: =K10*C24*C29 -> 0.0192
A39: Equity - Small Cap | B39: =B11*C25*C20 -> 0.0002395 | C39: =C11*C25*C21 -> 0.00210125 | D39: =D11*C25*C22 -> 0.035003 | E39: =E11*C25*C23 -> 0.03172875 | F39: =F11*C25*C24 -> 0.019928 | G39: =G11*C25*C25 -> 0.0625 | H39: =H11*C25*C26 -> 0.0524535 | I39: =I11*C25*C27 -> -0.005757 | J39: =J11*C25*C28 -> 0.02423525 | K39: =K11*C25*C29 -> 0.04
A40: Equity - Mid Cap | B40: =B12*C26*C20 -> 0.00038148 | C40: =C12*C26*C21 -> 0.0023276 | D40: =D12*C26*C22 -> 0.03380212 | E40: =E12*C26*C23 -> 0.0295515 | F40: =F12*C26*C24 -> 0.0166848 | G40: =G12*C26*C25 -> 0.0524535 | H40: =H12*C26*C26 -> 0.0484 | I40: =I12*C26*C27 -> -0.00604296 | J40: =J12*C26*C28 -> 0.023309 | K40: =K12*C26*C29 -> 0.0396
A41: Gold Commodity | B41: =B13*C27*C20 -> 0.00058512 | C41: =C13*C27*C21 -> 0.0011316 | D41: =D13*C27*C22 -> -0.0022542 | E41: =E13*C27*C23 -> -0.0028656 | F41: =F13*C27*C24 -> 0.00058176 | G41: =G13*C27*C25 -> -0.005757 | H41: =H13*C27*C26 -> -0.00604296 | I41: =I13*C27*C27 -> 0.0144 | J41: =J13*C27*C28 -> 0.0033072 | K41: =K13*C27*C29 -> 0.0024
A42: Multi-Asset Allocation Fund | B42: =B14*C28*C20 -> 0.00068406 | C42: =C14*C28*C21 -> 0.0023517 | D42: =D14*C28*C22 -> 0.02087787 | E42: =E14*C28*C23 -> 0.016731 | F42: =F14*C28*C24 -> 0.01082432 | G42: =G14*C28*C25 -> 0.02423525 | H42: =H14*C28*C26 -> 0.023309 | I42: =I14*C28*C27 -> 0.0033072 | J42: =J14*C28*C28 -> 0.0169 | K42: =K14*C28*C29 -> 0.0234
A43: Long-Short AIF | B43: =B15*C29*C20 -> 0.0004 | C43: =C15*C29*C21 -> 0.002 | D43: =D15*C29*C22 -> 0.0306 | E43: =E15*C29*C23 -> 0.027 | F43: =F15*C29*C24 -> 0.0192 | G43: =G15*C29*C25 -> 0.04 | H43: =H15*C29*C26 -> 0.0396 | I43: =I15*C29*C27 -> 0.0024 | J43: =J15*C29*C28 -> 0.0234 | K43: =K15*C29*C29 -> 0.16

Sheet 3. Market Utility
A1: SHEET 3 - MARKET UTILITY & INDIFFERENCE CURVES
A2: Formula: U = E(R) - 0.5 x A x SD^2
A4: Asset Class | B4: Expected Return | C4: Standard Deviation | D4: A=1 | E4: A=2 | F4: A=3 | G4: A=4 | H4: A=5 | I4: A=6
A5: Government Bonds | B5: 0.075 | C5: 0.02 | D5: =$B5-0.5*1*$C5^2 -> 0.0748 | E5: =$B5-0.5*2*$C5^2 -> 0.0746 | F5: =$B5-0.5*3*$C5^2 -> 0.0744 | G5: =$B5-0.5*4*$C5^2 -> 0.0742 | H5: =$B5-0.5*5*$C5^2 -> 0.074 | I5: =$B5-0.5*6*$C5^2 -> 0.0738
A6: Hybrid Debt Fund | B6: 0.08 | C6: 0.05 | D6: =$B6-0.5*1*$C6^2 -> 0.07875 | E6: =$B6-0.5*2*$C6^2 -> 0.0775 | F6: =$B6-0.5*3*$C6^2 -> 0.07625 | G6: =$B6-0.5*4*$C6^2 -> 0.075 | H6: =$B6-0.5*5*$C6^2 -> 0.07375 | I6: =$B6-0.5*6*$C6^2 -> 0.0725
A7: Pension Plan | B7: 0.08 | C7: 0.05 | D7: =$B7-0.5*1*$C7^2 -> 0.07875 | E7: =$B7-0.5*2*$C7^2 -> 0.0775 | F7: =$B7-0.5*3*$C7^2 -> 0.07625 | G7: =$B7-0.5*4*$C7^2 -> 0.075 | H7: =$B7-0.5*5*$C7^2 -> 0.07375 | I7: =$B7-0.5*6*$C7^2 -> 0.0725
A8: Corporate Bonds | B8: 0.09 | C8: 0.05 | D8: =$B8-0.5*1*$C8^2 -> 0.08875 | E8: =$B8-0.5*2*$C8^2 -> 0.0875 | F8: =$B8-0.5*3*$C8^2 -> 0.08625 | G8: =$B8-0.5*4*$C8^2 -> 0.085 | H8: =$B8-0.5*5*$C8^2 -> 0.08375 | I8: =$B8-0.5*6*$C8^2 -> 0.0825
A9: Embassy Office Parks REIT | B9: 0.11 | C9: 0.16 | D9: =$B9-0.5*1*$C9^2 -> 0.0972 | E9: =$B9-0.5*2*$C9^2 -> 0.0844 | F9: =$B9-0.5*3*$C9^2 -> 0.0716 | G9: =$B9-0.5*4*$C9^2 -> 0.0588 | H9: =$B9-0.5*5*$C9^2 -> 0.046 | I9: =$B9-0.5*6*$C9^2 -> 0.0332
A10: ULIPs | B10: 0.11 | C10: 0.11 | D10: =$B10-0.5*1*$C10^2 -> 0.10395 | E10: =$B10-0.5*2*$C10^2 -> 0.0979 | F10: =$B10-0.5*3*$C10^2 -> 0.09185 | G10: =$B10-0.5*4*$C10^2 -> 0.0858 | H10: =$B10-0.5*5*$C10^2 -> 0.07975 | I10: =$B10-0.5*6*$C10^2 -> 0.0737
A11: Child Education Plan | B11: 0.11 | C11: 0.11 | D11: =$B11-0.5*1*$C11^2 -> 0.10395 | E11: =$B11-0.5*2*$C11^2 -> 0.0979 | F11: =$B11-0.5*3*$C11^2 -> 0.09185 | G11: =$B11-0.5*4*$C11^2 -> 0.0858 | H11: =$B11-0.5*5*$C11^2 -> 0.07975 | I11: =$B11-0.5*6*$C11^2 -> 0.0737
A12: Gold Commodity | B12: 0.12 | C12: 0.12 | D12: =$B12-0.5*1*$C12^2 -> 0.1128 | E12: =$B12-0.5*2*$C12^2 -> 0.1056 | F12: =$B12-0.5*3*$C12^2 -> 0.0984 | G12: =$B12-0.5*4*$C12^2 -> 0.0912 | H12: =$B12-0.5*5*$C12^2 -> 0.084 | I12: =$B12-0.5*6*$C12^2 -> 0.0768
A13: Multi-Asset Allocation Fund | B13: 0.1278 | C13: 0.13 | D13: =$B13-0.5*1*$C13^2 -> 0.11935 | E13: =$B13-0.5*2*$C13^2 -> 0.1109 | F13: =$B13-0.5*3*$C13^2 -> 0.10245 | G13: =$B13-0.5*4*$C13^2 -> 0.094 | H13: =$B13-0.5*5*$C13^2 -> 0.08555 | I13: =$B13-0.5*6*$C13^2 -> 0.0771
A14: Equity - Large Cap | B14: 0.13 | C14: 0.17 | D14: =$B14-0.5*1*$C14^2 -> 0.11555 | E14: =$B14-0.5*2*$C14^2 -> 0.1011 | F14: =$B14-0.5*3*$C14^2 -> 0.08665 | G14: =$B14-0.5*4*$C14^2 -> 0.0722 | H14: =$B14-0.5*5*$C14^2 -> 0.05775 | I14: =$B14-0.5*6*$C14^2 -> 0.0433
A15: Mutual Fund - Large & Mid Cap | B15: 0.14 | C15: 0.15 | D15: =$B15-0.5*1*$C15^2 -> 0.12875 | E15: =$B15-0.5*2*$C15^2 -> 0.1175 | F15: =$B15-0.5*3*$C15^2 -> 0.10625 | G15: =$B15-0.5*4*$C15^2 -> 0.095 | H15: =$B15-0.5*5*$C15^2 -> 0.08375 | I15: =$B15-0.5*6*$C15^2 -> 0.0725
A16: Equity - Mid Cap | B16: 0.18 | C16: 0.22 | D16: =$B16-0.5*1*$C16^2 -> 0.1558 | E16: =$B16-0.5*2*$C16^2 -> 0.1316 | F16: =$B16-0.5*3*$C16^2 -> 0.1074 | G16: =$B16-0.5*4*$C16^2 -> 0.0832 | H16: =$B16-0.5*5*$C16^2 -> 0.059 | I16: =$B16-0.5*6*$C16^2 -> 0.0348
... A18: Long-Short AIF | B18: 0.25 | C18: 0.4 | D18: =$B18-0.5*1*$C18^2 -> 0.17 | E18: =$B18-0.5*2*$C18^2 -> 0.09 | F18: =$B18-0.5*3*$C18^2 -> 0.01 | G18: =$B18-0.5*4*$C18^2 -> -0.07 | H18: =$B18-0.5*5*$C18^2 -> -0.15 | I18: =$B18-0.5*6*$C18^2 -> -0.23

Sheet 4. Efficient Frontier
A1: SHEET 4 - PORTFOLIO OPTIMIZATION: MINIMUM VARIANCE, EFFICIENT FRONTIER, TANGENCY PORTFOLIO & CAL
A4: MINIMUM VARIANCE PORTFOLIO (MVP) and TANGENCY / MAX-SHARPE PORTFOLIO
A5: Asset | B5: Expected Return | C5: Standard Deviation | D5: MVP Weight | E5: Tangency Weight
A6: Government Bonds | B6: 0.075 | C6: 0.02 | D6: 0.4 | E6: 0
A7: Corporate Bonds | B7: 0.09 | C7: 0.05 | D7: 0.4 | E7: 0.3197
A8: Equity - Large Cap | B8: 0.13 | C8: 0.17 | D8: 0 | E8: 0
A9: Mutual Fund - L&M Cap | B9: 0.14 | C9: 0.15 | D9: 0.0768 | E9: 0
A10: Embassy REIT | B10: 0.11 | C10: 0.16 | D10: 0 | E10: 0
A11: Equity - Small Cap | B11: 0.2 | C11: 0.25 | D11: 0 | E11: 0.2183
A12: Equity - Mid Cap | B12: 0.18 | C12: 0.22 | D12: 0 | E12: 0
A13: Gold Commodity | B13: 0.12 | C13: 0.12 | D13: 0.1232 | E13: 0.4
A14: Multi-Asset Allocation Fund | B14: 0.1278 | C14: 0.13 | D14: 0 | E14: 0
A15: Long-Short AIF | B15: 0.25 | C15: 0.4 | D15: 0 | E15: 0.0619
A16: TOTAL | D16: =SUM(D6:D15) -> 1 | E16: =SUM(E6:E15) -> 0.9999
A18: Portfolio Return (=SUMPRODUCT weights x returns) | D18: =SUMPRODUCT(D6:D15,B6:B15) -> 0.091536 | E18: =SUMPRODUCT(E6:E15,B6:B15) -> 0.135908
A19: Portfolio Variance (=SUM of helper grid below) | D19: =SUM(B25:K34) -> 0.0013370035 | E19: =SUM(B38:K47) -> 0.0070073459
A20: Portfolio Risk (SD) (=SQRT(Variance)) | D20: =SQRT(D19) -> 0.036565059 | E20: =SQRT(E19) -> 0.083709891
A21: Portfolio Sharpe Ratio (=(Return-Rf)/Risk) | D21: =(D18-0.075)/D20 -> 0.45223502 | E21: =(E18-0.075)/E20 -> 0.72760816
A24: HELPER GRID - MVP | B24: Government | C24: Corporate | D24: Equity - Long | E24: Mutual Fund | F24: Embassy REIT | G24: Equity - S | H24: Equity - M | I24: Gold Commodity | J24: Multi-Asset | K24: Long-Short
A25: Government | B25: =$D$6*$D$6*'2. Correlation Matrix'!B34 -> 6.4e-05 | C25: =$D$6*$D$7*'2. Correlation Matrix'!C34 -> 0.000147104 | D25: =$D$6*$D$8*'2. Correlation Matrix'!D34 -> 0 | E25: =$D$6*$D$9*'2. Correlation Matrix'!E34 -> 8.395776e-06 | F25: =$D$6*$D$10*'2. Correlation Matrix'!F34 -> 0 | G25: =$D$6*$D$11*'2. Correlation Matrix'!G34 -> 0 | H25: =$D$6*$D$12*'2. Correlation Matrix'!H34 -> 0 | I25: =$D$6*$D$13*'2. Correlation Matrix'!I34 -> 2.8834714e-05 | J25: =$D$6*$D$14*'2. Correlation Matrix'!J34 -> 0 | K25: =$D$6*$D$15*'2. Correlation Matrix'!K34 -> 0
A26: Corporate | B26: =$D$7*$D$6*'2. Correlation Matrix'!B35 -> 0.000147104 | C26: =$D$7*$D$7*'2. Correlation Matrix'!C35 -> 0.0004 | D26: =$D$7*$D$8*'2. Correlation Matrix'!D35 -> 0 | E26: =$D$7*$D$9*'2. Correlation Matrix'!E35 -> 4.787712e-05 | F26: =$D$7*$D$10*'2. Correlation Matrix'!F35 -> 0 | G26: =$D$7*$D$11*'2. Correlation Matrix'!G35 -> 0 | H26: =$D$7*$D$12*'2. Correlation Matrix'!H35 -> 0 | I26: =$D$7*$D$13*'2. Correlation Matrix'!I35 -> 5.5765248e-05 | J26: =$D$7*$D$14*'2. Correlation Matrix'!J35 -> 0 | K26: =$D$7*$D$15*'2. Correlation Matrix'!K35 -> 0
A27: Equity - L | B27: =$D$8*$D$6*'2. Correlation Matrix'!B36 -> 0 | C27: =$D$8*$D$7*'2. Correlation Matrix'!C36 -> 0 | D27: =$D$8*$D$8*'2. Correlation Matrix'!D36 -> 0 | E27: =$D$8*$D$9*'2. Correlation Matrix'!E36 -> 0 | F27: =$D$8*$D$10*'2. Correlation Matrix'!F36 -> 0 | G27: =$D$8*$D$11*'2. Correlation Matrix'!G36 -> 0 | H27: =$D$8*$D$12*'2. Correlation Matrix'!H36 -> 0 | I27: =$D$8*$D$13*'2. Correlation Matrix'!I36 -> 0 | J27: =$D$8*$D$14*'2. Correlation Matrix'!J36 -> 0 | K27: =$D$8*$D$15*'2. Correlation Matrix'!K36 -> 0
A28: Mutual Fun | B28: =$D$9*$D$6*'2. Correlation Matrix'!B37 -> 8.395776e-06 | C28: =$D$9*$D$7*'2. Correlation Matrix'!C37 -> 4.787712e-05 | D28: =$D$9*$D$8*'2. Correlation Matrix'!D37 -> 0 | E28: =$D$9*$D$9*'2. Correlation Matrix'!E37 -> 0.0001327104 | F28: =$D$9*$D$10*'2. Correlation Matrix'!F37 -> 0 | G28: =$D$9*$D$11*'2. Correlation Matrix'!G37 -> 0 | H28: =$D$9*$D$12*'2. Correlation Matrix'!H37 -> 0 | I28: =$D$9*$D$13*'2. Correlation Matrix'!I37 -> -2.7113619e-05 | J28: =$D$9*$D$14*'2. Correlation Matrix'!J37 -> 0 | K28: =$D$9*$D$15*'2. Correlation Matrix'!K37 -> 0
A29: Embassy RE | B29: =$D$10*$D$6*'2. Correlation Matrix'!B38 -> 0 | C29: =$D$10*$D$7*'2. Correlation Matrix'!C38 -> 0 | D29: =$D$10*$D$8*'2. Correlation Matrix'!D38 -> 0 | E29: =$D$10*$D$9*'2. Correlation Matrix'!E38 -> 0 | F29: =$D$10*$D$10*'2. Correlation Matrix'!F38 -> 0 | G29: =$D$10*$D$11*'2. Correlation Matrix'!G38 -> 0 | H29: =$D$10*$D$12*'2. Correlation Matrix'!H38 -> 0 | I29: =$D$10*$D$13*'2. Correlation Matrix'!I38 -> 0 | J29: =$D$10*$D$14*'2. Correlation Matrix'!J38 -> 0 | K29: =$D$10*$D$15*'2. Correlation Matrix'!K38 -> 0
A30: Equity - S | B30: =$D$11*$D$6*'2. Correlation Matrix'!B39 -> 0 | C30: =$D$11*$D$7*'2. Correlation Matrix'!C39 -> 0 | D30: =$D$11*$D$8*'2. Correlation Matrix'!D39 -> 0 | E30: =$D$11*$D$9*'2. Correlation Matrix'!E39 -> 0 | F30: =$D$11*$D$10*'2. Correlation Matrix'!F39 -> 0 | G30: =$D$11*$D$11*'2. Correlation Matrix'!G39 -> 0 | H30: =$D$11*$D$12*'2. Correlation Matrix'!H39 -> 0 | I30: =$D$11*$D$13*'2. Correlation Matrix'!I39 -> 0 | J30: =$D$11*$D$14*'2. Correlation Matrix'!J39 -> 0 | K30: =$D$11*$D$15*'2. Correlation Matrix'!K39 -> 0
A31: Equity - M | B31: =$D$12*$D$6*'2. Correlation Matrix'!B40 -> 0 | C31: =$D$12*$D$7*'2. Correlation Matrix'!C40 -> 0 | D31: =$D$12*$D$8*'2. Correlation Matrix'!D40 -> 0 | E31: =$D$12*$D$9*'2. Correlation Matrix'!E40 -> 0 | F31: =$D$12*$D$10*'2. Correlation Matrix'!F40 -> 0 | G31: =$D$12*$D$11*'2. Correlation Matrix'!G40 -> 0 | H31: =$D$12*$D$12*'2. Correlation Matrix'!H40 -> 0 | I31: =$D$12*$D$13*'2. Correlation Matrix'!I40 -> 0 | J31: =$D$12*$D$14*'2. Correlation Matrix'!J40 -> 0 | K31: =$D$12*$D$15*'2. Correlation Matrix'!K40 -> 0
A32: Gold Commo | B32: =$D$13*$D$6*'2. Correlation Matrix'!B41 -> 2.8834714e-05 | C32: =$D$13*$D$7*'2. Correlation Matrix'!C41 -> 5.5765248e-05 | D32: =$D$13*$D$8*'2. Correlation Matrix'!D41 -> 0 | E32: =$D$13*$D$9*'2. Correlation Matrix'!E41 -> -2.7113619e-05 | F32: =$D$13*$D$10*'2. Correlation Matrix'!F41 -> 0 | G32: =$D$13*$D$11*'2. Correlation Matrix'!G41 -> 0 | H32: =$D$13*$D$12*'2. Correlation Matrix'!H41 -> 0 | I32: =$D$13*$D$13*'2. Correlation Matrix'!I41 -> 0.00021856666 | J32: =$D$13*$D$14*'2. Correlation Matrix'!J41 -> 0 | K32: =$D$13*$D$15*'2. Correlation Matrix'!K41 -> 0
A33: Multi-Asse | B33: =$D$14*$D$6*'2. Correlation Matrix'!B42 -> 0 | C33: =$D$14*$D$7*'2. Correlation Matrix'!C42 -> 0 | D33: =$D$14*$D$8*'2. Correlation Matrix'!D42 -> 0 | E33: =$D$14*$D$9*'2. Correlation Matrix'!E42 -> 0 | F33: =$D$14*$D$10*'2. Correlation Matrix'!F42 -> 0 | G33: =$D$14*$D$11*'2. Correlation Matrix'!G42 -> 0 | H33: =$D$14*$D$12*'2. Correlation Matrix'!H42 -> 0 | I33: =$D$14*$D$13*'2. Correlation Matrix'!I42 -> 0 | J33: =$D$14*$D$14*'2. Correlation Matrix'!J42 -> 0 | K33: =$D$14*$D$15*'2. Correlation Matrix'!K42 -> 0
A34: Long-Short | B34: =$D$15*$D$6*'2. Correlation Matrix'!B43 -> 0 | C34: =$D$15*$D$7*'2. Correlation Matrix'!C43 -> 0 | D34: =$D$15*$D$8*'2. Correlation Matrix'!D43 -> 0 | E34: =$D$15*$D$9*'2. Correlation Matrix'!E43 -> 0 | F34: =$D$15*$D$10*'2. Correlation Matrix'!F43 -> 0 | G34: =$D$15*$D$11*'2. Correlation Matrix'!G43 -> 0 | H34: =$D$15*$D$12*'2. Correlation Matrix'!H43 -> 0 | I34: =$D$15*$D$13*'2. Correlation Matrix'!I43 -> 0 | J34: =$D$15*$D$14*'2. Correlation Matrix'!J43 -> 0 | K34: =$D$15*$D$15*'2. Correlation Matrix'!K43 -> 0
A37: HELPER GRID - TANGENCY | B37: Government | C37: Corporate | D37: Equity - Long | E37: Mutual Fund | F37: Embassy REIT | G37: Equity - S | H37: Equity - M | I37: Gold Commodity | J37: Multi-Asset | K37: Long-Short
A38: Government | B38: =$E$6*$E$6*'2. Correlation Matrix'!B34 -> 0 | C38: =$E$6*$E$7*'2. Correlation Matrix'!C34 -> 0 | D38: =$E$6*$E$8*'2. Correlation Matrix'!D34 -> 0 | E38: =$E$6*$E$9*'2. Correlation Matrix'!E34 -> 0 | F38: =$E$6*$E$10*'2. Correlation Matrix'!F34 -> 0 | G38: =$E$6*$E$11*'2. Correlation Matrix'!G34 -> 0 | H38: =$E$6*$E$12*'2. Correlation Matrix'!H34 -> 0 | I38: =$E$6*$E$13*'2. Correlation Matrix'!I34 -> 0 | J38: =$E$6*$E$14*'2. Correlation Matrix'!J34 -> 0 | K38: =$E$6*$E$15*'2. Correlation Matrix'!K34 -> 0
A39: Corporate | B39: =$E$7*$E$6*'2. Correlation Matrix'!B35 -> 0 | C39: =$E$7*$E$7*'2. Correlation Matrix'!C35 -> 0.00025552023 | D39: =$E$7*$E$8*'2. Correlation Matrix'!D35 -> 0 | E39: =$E$7*$E$9*'2. Correlation Matrix'!E35 -> 0 | F39: =$E$7*$E$10*'2. Correlation Matrix'!F35 -> 0 | G39: =$E$7*$E$11*'2. Correlation Matrix'!G35 -> 0.00014664731 | H39: =$E$7*$E$12*'2. Correlation Matrix'!H35 -> 0 | I39: =$E$7*$E$13*'2. Correlation Matrix'!I35 -> 0.00014470901 | J39: =$E$7*$E$14*'2. Correlation Matrix'!J35 -> 0 | K39: =$E$7*$E$15*'2. Correlation Matrix'!K35 -> 3.957886e-05
A40: Equity - L | B40: =$E$8*$E$6*'2. Correlation Matrix'!B36 -> 0 | C40: =$E$8*$E$7*'2. Correlation Matrix'!C36 -> 0 | D40: =$E$8*$E$8*'2. Correlation Matrix'!D36 -> 0 | E40: =$E$8*$E$9*'2. Correlation Matrix'!E36 -> 0 | F40: =$E$8*$E$10*'2. Correlation Matrix'!F36 -> 0 | G40: =$E$8*$E$11*'2. Correlation Matrix'!G36 -> 0 | H40: =$E$8*$E$12*'2. Correlation Matrix'!H36 -> 0 | I40: =$E$8*$E$13*'2. Correlation Matrix'!I36 -> 0 | J40: =$E$8*$E$14*'2. Correlation Matrix'!J36 -> 0 | K40: =$E$8*$E$15*'2. Correlation Matrix'!K36 -> 0
A41: Mutual Fun | B41: =$E$9*$E$6*'2. Correlation Matrix'!B37 -> 0 | C41: =$E$9*$E$7*'2. Correlation Matrix'!C37 -> 0 | D41: =$E$9*$E$8*'2. Correlation Matrix'!D37 -> 0 | E41: =$E$9*$E$9*'2. Correlation Matrix'!E37 -> 0 | F41: =$E$9*$E$10*'2. Correlation Matrix'!F37 -> 0 | G41: =$E$9*$E$11*'2. Correlation Matrix'!G37 -> 0 | H41: =$E$9*$E$12*'2. Correlation Matrix'!H37 -> 0 | I41: =$E$9*$E$13*'2. Correlation Matrix'!I37 -> 0 | J41: =$E$9*$E$14*'2. Correlation Matrix'!J37 -> 0 | K41: =$E$9*$E$15*'2. Correlation Matrix'!K37 -> 0
A42: Embassy RE | B42: =$E$10*$E$6*'2. Correlation Matrix'!B38 -> 0 | C42: =$E$10*$E$7*'2. Correlation Matrix'!C38 -> 0 | D42: =$E$10*$E$8*'2. Correlation Matrix'!D38 -> 0 | E42: =$E$10*$E$9*'2. Correlation Matrix'!E38 -> 0 | F42: =$E$10*$E$10*'2. Correlation Matrix'!F38 -> 0 | G42: =$E$10*$E$11*'2. Correlation Matrix'!G38 -> 0 | H42: =$E$10*$E$12*'2. Correlation Matrix'!H38 -> 0 | I42: =$E$10*$E$13*'2. Correlation Matrix'!I38 -> 0 | J42: =$E$10*$E$14*'2. Correlation Matrix'!J38 -> 0 | K42: =$E$10*$E$15*'2. Correlation Matrix'!K38 -> 0
A43: Equity - S | B43: =$E$11*$E$6*'2. Correlation Matrix'!B39 -> 0 | C43: =$E$11*$E$7*'2. Correlation Matrix'!C39 -> 0.00014664731 | D43: =$E$11*$E$8*'2. Correlation Matrix'!D39 -> 0 | E43: =$E$11*$E$9*'2. Correlation Matrix'!E39 -> 0 | F43: =$E$11*$E$10*'2. Correlation Matrix'!F39 -> 0 | G43: =$E$11*$E$11*'2. Correlation Matrix'!G39 -> 0.0029784306 | H43: =$E$11*$E$12*'2. Correlation Matrix'!H39 -> 0 | I43: =$E$11*$E$13*'2. Correlation Matrix'!I39 -> -0.00050270124 | J43: =$E$11*$E$14*'2. Correlation Matrix'!J39 -> 0 | K43: =$E$11*$E$15*'2. Correlation Matrix'!K39 -> 0.0005405108
A44: Equity - M | B44: =$E$12*$E$6*'2. Correlation Matrix'!B40 -> 0 | C44: =$E$12*$E$7*'2. Correlation Matrix'!C40 -> 0 | D44: =$E$12*$E$8*'2. Correlation Matrix'!D40 -> 0 | E44: =$E$12*$E$9*'2. Correlation Matrix'!E40 -> 0 | F44: =$E$12*$E$10*'2. Correlation Matrix'!F40 -> 0 | G44: =$E$12*$E$11*'2. Correlation Matrix'!G40 -> 0 | H44: =$E$12*$E$12*'2. Correlation Matrix'!H40 -> 0 | I44: =$E$12*$E$13*'2. Correlation Matrix'!I40 -> 0 | J44: =$E$12*$E$14*'2. Correlation Matrix'!J40 -> 0 | K44: =$E$12*$E$15*'2. Correlation Matrix'!K40 -> 0
A45: Gold Commo | B45: =$E$13*$E$6*'2. Correlation Matrix'!B41 -> 0 | C45: =$E$13*$E$7*'2. Correlation Matrix'!C41 -> 0.00014470901 | D45: =$E$13*$E$8*'2. Correlation Matrix'!D41 -> 0 | E45: =$E$13*$E$9*'2. Correlation Matrix'!E41 -> 0 | F45: =$E$13*$E$10*'2. Correlation Matrix'!F41 -> 0 | G45: =$E$13*$E$11*'2. Correlation Matrix'!G41 -> -0.00050270124 | H45: =$E$13*$E$12*'2. Correlation Matrix'!H41 -> 0 | I45: =$E$13*$E$13*'2. Correlation Matrix'!I41 -> 0.002304 | J45: =$E$13*$E$14*'2. Correlation Matrix'!J41 -> 0 | K45: =$E$13*$E$15*'2. Correlation Matrix'!K41 -> 5.9424e-05
A46: Multi-Asse | B46: =$E$14*$E$6*'2. Correlation Matrix'!B42 -> 0 | C46: =$E$14*$E$7*'2. Correlation Matrix'!C42 -> 0 | D46: =$E$14*$E$8*'2. Correlation Matrix'!D42 -> 0 | E46: =$E$14*$E$9*'2. Correlation Matrix'!E42 -> 0 | F46: =$E$14*$E$10*'2. Correlation Matrix'!F42 -> 0 | G46: =$E$14*$E$11*'2. Correlation Matrix'!G42 -> 0 | H46: =$E$14*$E$12*'2. Correlation Matrix'!H42 -> 0 | I46: =$E$14*$E$13*'2. Correlation Matrix'!I42 -> 0 | J46: =$E$14*$E$14*'2. Correlation Matrix'!J42 -> 0 | K46: =$E$14*$E$15*'2. Correlation Matrix'!K42 -> 0
A47: Long-Short | B47: =$E$15*$E$6*'2. Correlation Matrix'!B43 -> 0 | C47: =$E$15*$E$7*'2. Correlation Matrix'!C43 -> 3.957886e-05 | D47: =$E$15*$E$8*'2. Correlation Matrix'!D43 -> 0 | E47: =$E$15*$E$9*'2. Correlation Matrix'!E43 -> 0 | F47: =$E$15*$E$10*'2. Correlation Matrix'!F43 -> 0 | G47: =$E$15*$E$11*'2. Correlation Matrix'!G43 -> 0.0005405108 | H47: =$E$15*$E$12*'2. Correlation Matrix'!H43 -> 0 | I47: =$E$15*$E$13*'2. Correlation Matrix'!I43 -> 5.9424e-05 | J47: =$E$15*$E$14*'2. Correlation Matrix'!J43 -> 0 | K47: =$E$15*$E$15*'2. Correlation Matrix'!K43 -> 0.0006130576
A49: EFFICIENT FRONTIER POINTS (computed - see Assumptions tab note on Solver)
A50: Point | B50: Risk (SD) | C50: Return
A51: 1 | B51: 0.036590312 | C51: 0.091535942
A52: 2 | B52: 0.043831342 | C52: 0.10249766
A53: 3 | B53: 0.055912866 | C53: 0.11345938
A54: 4 | B54: 0.069353947 | C54: 0.1244211
A55: 5 | B55: 0.082981734 | C55: 0.13538282
A56: 6 | B56: 0.099120389 | C56: 0.14634453
A57: 7 | B57: 0.11699333 | C57: 0.15730625
A58: 8 | B58: 0.13592015 | C58: 0.16826797
A59: 9 | B59: 0.15656483 | C59: 0.17922969
A60: 10 | B60: 0.18325182 | C60: 0.19019141
A61: 11 | B61: 0.21213127 | C61: 0.20115313
A62: 12 | B62: 0.24295274 | C62: 0.21211484
A64: INDIVIDUAL ASSETS (for chart)
A65: Asset | B65: Risk | C65: Return
A66: Government Bonds | B66: 0.02 | C66: 0.075
A67: Corporate Bonds | B67: 0.05 | C67: 0.09
A68: Equity - Large Cap | B68: 0.17 | C68: 0.13
A69: Mutual Fund - L&M Cap | B69: 0.15 | C69: 0.14
A70: Embassy REIT | B70: 0.16 | C70: 0.11
A71: Equity - Small Cap | B71: 0.25 | C71: 0.2
A72: Equity - Mid Cap | B72: 0.22 | C72: 0.18
A73: Gold Commodity | B73: 0.12 | C73: 0.12
A74: Multi-Asset Allocation Fund | B74: 0.13 | C74: 0.1278
A75: Long-Short AIF | B75: 0.4 | C75: 0.25
A77: CAL LINE POINTS (for chart)
A78: Point | B78: Risk | C78: Return | D78: Utility (A=1) | E78: Utility (A=3) | F78: Utility (A=4)
A79: Risk-free | B79: 0 | C79: 0.075 | D79: =$C79-((1/2)*1*$B79^2) -> 0.075 | E79: =$C79-((1/2)*1*$B79^2) -> 0.075 | F79: =$C79-((1/2)*1*$B79^2) -> 0.075
A80: Tangency | B80: =E20 -> 0.083709891 | C80: =E18 -> 0.135908 | D80: =$C80-((1/2)*1*$B80^2) -> 0.13240433 | E80: =$C80-((1/2)*1*$B80^2) -> 0.13240433 | F80: =$C80-((1/2)*1*$B80^2) -> 0.13240433
A81: CAL extended | B81: 0.14233792 | C81: 0.17857871 | D81: =$C81-((1/2)*1*$B81^2) -> 0.16844866 | E81: =$C81-((1/2)*1*$B81^2) -> 0.16844866 | F81: =$C81-((1/2)*1*$B81^2) -> 0.16844866
A83: MVP: Return=9.15% Risk=3.66%
A84: Tangency: Return=13.59% Risk=8.37% Sharpe=0.73
A85: Risk-free rate: 7.50%

Sheet 5. Random Scenario Search
A1: SHEET 5 - PORTFOLIO OPTIMIZATION: RANDOM SCENARIO SEARCH (5,000 scenarios)
A2: Each row = one randomly generated weight combination (equivalent to RANDBETWEEN(1,100) per asset, normalized to sum 100%). Return/Risk computed from the 10-asset E(R) and covariance matrix.
A4: Scenario | B4: Government Bond | C4: Corporate Bond | D4: Equity - Large | E4: Mutual Fund - | F4: Embassy REIT | G4: Equity - Small | H4: Equity - Mid C | I4: Gold Commodity | J4: Multi-Asset Al | K4: Long-Short AIF | L4: Sum of Weights | M4: Return | N4: Risk | O4: Sharpe | P4: Utility A=1 | Q4: Utility A=3 | R4: Utility A=4
A5: 439 | B5: 0.1313 | C5: 0.1957 | D5: 0.0621 | E5: 0.0143 | F5: 0.0095 | G5: 0.0692 | H5: 0.1408 | I5: 0.2339 | J5: 0.0406 | K5: 0.1026 | L5: =SUM(B5:K5) -> 1 | M5: 0.13668 | N5: {=SQRT(MMULT(MMULT(B5:K5, '2. Correlation Matrix'!$B$34:$K$43), TRANSPOSE(B5:K5)))} -> 0.096287017 | O5: =(M5-0.075)/N5 -> 0.6405848 | P5: =M5-((1/2)*1*N5^2) -> 0.13204441 | Q5: =$M$5-((1/2)*3*$N$5^2) -> 0.12277322 | R5: =$M$5-((1/2)*4*$N$5^2) -> 0.11813762
A6: 778 | B6: 0.0693 | C6: 0.2 | D6: 0.0053 | E6: 0.0373 | F6: 0.08 | G6: 0.1307 | H6: 0.032 | I6: 0.24 | J6: 0.1173 | K6: 0.088 | L6: =SUM(B6:K6) -> 0.9999 | M6: 0.13561 | N6: {=SQRT(MMULT(MMULT(B6:K6, '2. Correlation Matrix'!$B$34:$K$43), TRANSPOSE(B6:K6)))} -> 0.094896392 | O6: =(M6-0.075)/N6 -> 0.63869657 | P6: =M6-((1/2)*1*N6^2) -> 0.13110734 | Q6: =$M$5-((1/2)*3*$N$5^2) -> 0.12277322 | R6: =$M$5-((1/2)*4*$N$5^2) -> 0.11813762
A7: 3539 | B7: 0.1076 | C7: 0.22 | D7: 0.0122 | E7: 0.0807 | F7: 0.0122 | G7: 0.088 | H7: 0.1883 | I7: 0.198 | J7: 0.0318 | K7: 0.0611 | L7: =SUM(B7:K7) -> 0.9999 | M7: 0.1367 | N7: {=SQRT(MMULT(MMULT(B7:K7, '2. Correlation Matrix'!$B$34:$K$43), TRANSPOSE(B7:K7)))} -> 0.097282611 | O7: =(M7-0.075)/N7 -> 0.63423462 | P7: =M7-((1/2)*1*N7^2) -> 0.13196805 | Q7: =$M$5-((1/2)*3*$N$5^2) -> 0.12277322 | R7: =$M$5-((1/2)*4*$N$5^2) -> 0.11813762
A8: 4838 | B8: 0.2198 | C8: 0.1374 | D8: 0.011 | E8: 0.022 | F8: 0.0989 | G8: 0.0275 | H8: 0.0824 | I8: 0.2747 | J8: 0.044 | K8: 0.0824 | L8: =SUM(B8:K8) -> 1.0001 | M8: 0.12375 | N8: {=SQRT(MMULT(MMULT(B8:K8, '2. Correlation Matrix'!$B$34:$K$43), TRANSPOSE(B8:K8)))} -> 0.076949363 | O8: =(M8-0.075)/N8 -> 0.63353351 | P8: =M8-((1/2)*1*N8^2) -> 0.1207894 | Q8: =$M$5-((1/2)*3*$N$5^2) -> 0.12277322 | R8: =$M$5-((1/2)*4*$N$5^2) -> 0.11813762
A9: 2733 | B9: 0.0948 | C9: 0.1945 | D9: 0.005 | E9: 0.0224 | F9: 0.0125 | G9: 0.2444 | H9: 0.0474 | I9: 0.1771 | J9: 0.0973 | K9: 0.1047 | L9: =SUM(B9:K9) -> 1.0001 | M9: 0.14704 | N9: {=SQRT(MMULT(MMULT(B9:K9, '2. Correlation Matrix'!$B$34:$K$43), TRANSPOSE(B9:K9)))} -> 0.11406075 | O9: =(M9-0.075)/N9 -> 0.63159326 | P9: =M9-((1/2)*1*N9^2) -> 0.14053507 | Q9: =$M$5-((1/2)*3*$N$5^2) -> 0.12277322 | R9: =$M$5-((1/2)*4*$N$5^2) -> 0.11813762
A10: 2469 | B10: 0.2217 | C10: 0.2358 | D10: 0.0354 | E10: 0.033 | F10: 0.0731 | G10: 0.0684 | H10: 0.0637 | I10: 0.2005 | J10: 0.0212 | K10: 0.0472 | L10: =SUM(B10:K10) -> 1 | M10: 0.11882 | N10: {=SQRT(MMULT(MMULT(B10:K10, '2. Correlation Matrix'!$B$34:$K$43), TRANSPOSE(B10:K10)))} -> 0.069615693 | O10: =(M10-0.075)/N10 -> 0.62945578 | P10: =M10-((1/2)*1*N10^2) -> 0.11639683 | Q10: =$M$5-((1/2)*3*$N$5^2) -> 0.12277322 | R10: =$M$5-((1/2)*4*$N$5^2) -> 0.11813762
A11: 2 | B11: 0.1964 | C11: 0.2232 | D11: 0.0536 | E11: 0.0067 | F11: 0.0491 | G11: 0.1183 | H11: 0.0045 | I11: 0.1964 | J11: 0.067 | K11: 0.0848 | L11: =SUM(B11:K11) -> 1 | M11: 0.12592 | N11: {=SQRT(MMULT(MMULT(B11:K11, '2. Correlation Matrix'!$B$34:$K$43), TRANSPOSE(B11:K11)))} -> 0.080991769 | O11: =(M11-0.075)/N11 -> 0.62870586 | P11: =M11-((1/2)*1*N11^2) -> 0.12264017 | Q11: =$M$5-((1/2)*3*$N$5^2) -> 0.12277322 | R11: =$M$5-((1/2)*4*$N$5^2) -> 0.11813762
A12: 1483 | B12: 0.1899 | C12: 0.2514 | D12: 0.0112 | E12: 0.0251 | F12: 0.0838 | G12: 0.1257 | H12: 0.0112 | I12: 0.1927 | J12: 0.0642 | K12: 0.0447 | L12: =SUM(B12:K12) -> 0.9999 | M12: 0.12072 | N12: {=SQRT(MMULT(MMULT(B12:K12, '2. Correlation Matrix'!$B$34:$K$43), TRANSPOSE(B12:K12)))} -> 0.072812063 | O12: =(M12-0.075)/N12 -> 0.62791793 | P12: =M12-((1/2)*1*N12^2) -> 0.1180692 | Q12: =$M$5-((1/2)*3*$N$5^2) -> 0.12277322 | R12: =$M$5-((1/2)*4*$N$5^2) -> 0.11813762
A13: 471 | B13: 0.1497 | C13: 0.2119 | D13: 0.0141 | E13: 0.0763 | F13: 0.0339 | G13: 0.048 | H13: 0.0169 | I13: 0.274 | J13: 0.0141 | K13: 0.161 | L13: =SUM(B13:K13) -> 0.9999 | M13: 0.13414 | N13: {=SQRT(MMULT(MMULT(B13:K13, '2. Correlation Matrix'!$B$34:$K$43), TRANSPOSE(B13:K13)))} -> 0.094292636 | O13: =(M13-0.075)/N13 -> 0.62719638 | P13: =M13-((1/2)*1*N13^2) -> 0.12969445 | Q13: =$M$5-((1/2)*3*$N$5^2) -> 0.12277322 | R13: =$M$5-((1/2)*4*$N$5^2) -> 0.11813762
A14: 188 | B14: 0.1383 | C14: 0.2021 | D14: 0.0186 | E14: 0.0771 | F14: 0.0293 | G14: 0.0878 | H14: 0.016 | I14: 0.2101 | J14: 0.0851 | K14: 0.1356 | L14: =SUM(B14:K14) -> 1 | M14: 0.13542 | N14: {=SQRT(MMULT(MMULT(B14:K14, '2. Correlation Matrix'!$B$34:$K$43), TRANSPOSE(B14:K14)))} -> 0.096537653 | O14: =(M14-0.075)/N14 -> 0.62586978 | P14: =M14-((1/2)*1*N14^2) -> 0.13076024 | Q14: =$M$5-((1/2)*3*$N$5^2) -> 0.12277322 | R14: =$M$5-((1/2)*4*$N$5^2) -> 0.11813762
A15: 2110 | B15: 0.0372 | C15: 0.2025 | D15: 0.0248 | E15: 0.0331 | F15: 0.0083 | G15: 0.1839 | H15: 0.0702 | I15: 0.1901 | J15: 0.095 | K15: 0.155 | L15: =SUM(B15:K15) -> 1.0001 | M15: 0.15289 | N15: {=SQRT(MMULT(MMULT(B15:K15, '2. Correlation Matrix'!$B$34:$K$43), TRANSPOSE(B15:K15)))} -> 0.12445836 | O15: =(M15-0.075)/N15 -> 0.62583181 | P15: =M15-((1/2)*1*N15^2) -> 0.14514506 | Q15: =$M$5-((1/2)*3*$N$5^2) -> 0.12277322 | R15: =$M$5-((1/2)*4*$N$5^2) -> 0.11813762
A16: 4859 | B16: 0.1378 | C16: 0.1454 | D16: 0.0251 | E16: 0.0702 | F16: 0.0351 | G16: 0.208 | H16: 0.0652 | I16: 0.1855 | J16: 0.0426 | K16: 0.0852 | L16: =SUM(B16:K16) -> 1.0001 | M16: 0.1427 | N16: {=SQRT(MMULT(MMULT(B16:K16, '2. Correlation Matrix'!$B$34:$K$43), TRANSPOSE(B16:K16)))} -> 0.10833441 | O16: =(M16-0.075)/N16 -> 0.62491689 | P16: =M16-((1/2)*1*N16^2) -> 0.13683183 | Q16: =$M$5-((1/2)*3*$N$5^2) -> 0.12277322 | R16: =$M$5-((1/2)*4*$N$5^2) -> 0.11813762
... A5004: 3177 | B5004: 0.1025 | C5004: 0.0859 | D5004: 0.1717 | E5004: 0.0499 | F5004: 0.2493 | G5004: 0.0166 | H5004: 0.0249 | I5004: 0.0305 | J5004: 0.2632 | K5004: 0.0055 | L5004: =SUM(B5004:K5004) -> 1 | M5004: 0.11863 | N5004: {=SQRT(MMULT(MMULT(B5004:K5004, '2. Correlation Matrix'!$B$34:$K$43), TRANSPOSE(B5004:K5004)))} -> 0.10768249 | O5004: =(M5004-0.075)/N5004 -> 0.40517263 | P5004: =M5004-((1/2)*1*N5004^2) -> 0.11283224 | Q5004: =$M$5-((1/2)*3*$N$5^2) -> 0.12277322 | R5004: =$M$5-((1/2)*4*$N$5^2) -> 0.11813762

Sheet Deven
A1: CLIENT: Deven Saboo (A = 1, Aggressive, self-identifies as Risk Seeker)
A3: SHEET 1 - CLIENT RISK PROFILE
A4: Age | B4: 24
A5: Investment Objective | B5: Long Term Wealth Creation
A6: Primary Financial Goal | B6: Starting a Cafe
A7: Goal Target Amount (Rs) | B7: 6000000
A8: Years to Goal | B8: 15
A9: Monthly SIP Capacity (Rs) | B9: 10000
A10: Required Annual Return (goal-implied) | B10: 0.1482
A11: Investment Horizon (yrs) | B11: 35
A12: Liquidity Requirement | B12: Low
A13: Max Acceptable 1-yr Loss | B13: 0.2
A14: Risk Aversion Coefficient (A) | B14: 1
A15: Risk Profile Band | B15: Aggressive
A17: SHEET 3 - UTILITY & INDIFFERENCE CURVES (client's own beliefs, own aware assets only)
A18: Product | B18: Client Exp. Return | C18: Client Exp. Risk | D18: Utility of an Investor | E18: Product Risk from Market | F18: Product Return from Market | G18: Market Utility A=1 | H18: Difference
A19: Government Bonds | B19: 0.07 | C19: 0 | D19: =B19-0.5*1*C19^2 -> 0.07 | E19: 0.02 | F19: 0.075 | G19: ='3. Market Utility'!D5 -> 0.0748 | H19: =D19-G19 -> -0.0048
A20: Corporate Bonds | B20: 0.1 | C20: 0.08 | D20: =B20-0.5*1*C20^2 -> 0.0968 | E20: 0.05 | F20: 0.09 | G20: ='3. Market Utility'!D8 -> 0.08875 | H20: =D20-G20 -> 0.00805
A21: Embassy Office Parks REIT | B21: 0.12 | C21: 0.15 | D21: =B21-0.5*1*C21^2 -> 0.10875 | E21: 0.16 | F21: 0.11 | G21: ='3. Market Utility'!D9 -> 0.0972 | H21: =D21-G21 -> 0.01155
A22: Gold Commodity | B22: 0.12 | C22: 0.15 | D22: =B22-0.5*1*C22^2 -> 0.10875 | E22: 0.12 | F22: 0.12 | G22: ='3. Market Utility'!D12 -> 0.1128 | H22: =D22-G22 -> -0.00405
A23: Multi-Asset Allocation Fund | B23: 0.09 | C23: 0.05 | D23: =B23-0.5*1*C23^2 -> 0.08875 | E23: 0.13 | F23: 0.1278 | G23: ='3. Market Utility'!D13 -> 0.11935 | H23: =D23-G23 -> -0.0306
A24: Equity - Large Cap | B24: 0.1 | C24: 0.07 | D24: =B24-0.5*1*C24^2 -> 0.09755 | E24: 0.17 | F24: 0.13 | G24: ='3. Market Utility'!D14 -> 0.11555 | H24: =D24-G24 -> -0.018
A25: Mutual Fund - Large & Mid Cap | B25: 0.12 | C25: 0.1 | D25: =B25-0.5*1*C25^2 -> 0.115 | E25: 0.15 | F25: 0.14 | G25: ='3. Market Utility'!D15 -> 0.12875 | H25: =D25-G25 -> -0.01375
A26: Equity - Mid Cap | B26: 0.15 | C26: 0.2 | D26: =B26-0.5*1*C26^2 -> 0.13 | E26: 0.22 | F26: 0.18 | G26: ='3. Market Utility'!D16 -> 0.1558 | H26: =D26-G26 -> -0.0258
A27: Equity - Small Cap | B27: 0.22 | C27: 0.25 | D27: =B27-0.5*1*C27^2 -> 0.18875 | E27: 0.25 | F27: 0.2 | G27: ='3. Market Utility'!D17 -> 0.16875 | H27: =D27-G27 -> 0.02
A29: Positive Difference = client OVER-estimates the asset's attractiveness vs the market view (Blue above Orange). Negative = client UNDER-estimates it / is more pessimistic than the market.
A31: MARKET UTILITY CURVE (all 14 assets, at A=1) vs CLIENT'S OWN UTILITY CURVE
A32: Asset (market, sorted by SD) | B32: Market SD | C32: Market Product Utility | E32: Asset (client belief, sorted by SD) | F32: Client SD | G32: Client Product Utility | H32: Market Product Utility | J32: CAL Utility | K32: Risk | L32: Return | M32: Utility
A33: Government Bonds | B33: 0.02 | C33: ='3. Market Utility'!D5 -> 0.0748 | E33: Government Bonds | F33: 0 | G33: =0.07-0.5*1*F33^2 -> 0.07 | H33: =VLOOKUP(E33,A32:C46,3,FALSE) -> 0.0748 | J33: Risk-free | K33: ='4. Efficient Frontier'!B79 -> 0 | L33: ='4. Efficient Frontier'!C79 -> 0.075 | M33: ='4. Efficient Frontier'!D79 -> 0.075
A34: Hybrid Debt Fund | B34: 0.05 | C34: ='3. Market Utility'!D6 -> 0.07875 | E34: Multi-Asset Allocation Fund | F34: 0.05 | G34: =0.09-0.5*1*F34^2 -> 0.08875 | H34: =VLOOKUP(E34,A33:C47,3,FALSE) -> 0.11935 | J34: Tangency | K34: ='4. Efficient Frontier'!B80 -> 0.083709891 | L34: ='4. Efficient Frontier'!C80 -> 0.135908 | M34: ='4. Efficient Frontier'!D80 -> 0.13240433
A35: Pension Plan | B35: 0.05 | C35: ='3. Market Utility'!D7 -> 0.07875 | E35: Equity - Large Cap | F35: 0.07 | G35: =0.1-0.5*1*F35^2 -> 0.09755 | H35: =VLOOKUP(E35,A34:C48,3,FALSE) -> 0.11555 | J35: CAL extended | K35: ='4. Efficient Frontier'!B81 -> 0.14233792 | L35: ='4. Efficient Frontier'!C81 -> 0.17857871 | M35: ='4. Efficient Frontier'!D81 -> 0.16844866
A36: Corporate Bonds | B36: 0.05 | C36: ='3. Market Utility'!D8 -> 0.08875 | E36: Corporate Bonds | F36: 0.08 | G36: =0.1-0.5*1*F36^2 -> 0.0968 | H36: =VLOOKUP(E36,A35:C49,3,FALSE) -> 0.08875
A37: ULIPs | B37: 0.11 | C37: ='3. Market Utility'!D10 -> 0.10395 | E37: Mutual Fund - Large & Mid Cap | F37: 0.1 | G37: =0.12-0.5*1*F37^2 -> 0.115 | H37: =VLOOKUP(E37,A36:C50,3,FALSE) -> 0.12875
A38: Child Education Plan | B38: 0.11 | C38: ='3. Market Utility'!D11 -> 0.10395 | E38: Embassy Office Parks REIT | F38: 0.15 | G38: =0.12-0.5*1*F38^2 -> 0.10875 | H38: =VLOOKUP(E38,A37:C51,3,FALSE) -> 0.0972
A39: Gold Commodity | B39: 0.12 | C39: ='3. Market Utility'!D12 -> 0.1128 | E39: Gold Commodity | F39: 0.15 | G39: =0.12-0.5*1*F39^2 -> 0.10875 | H39: =VLOOKUP(E39,A38:C52,3,FALSE) -> 0.1128
A40: Multi-Asset Allocation Fund | B40: 0.13 | C40: ='3. Market Utility'!D13 -> 0.11935 | E40: Equity - Mid Cap | F40: 0.2 | G40: =0.15-0.5*1*F40^2 -> 0.13 | H40: =VLOOKUP(E40,A39:C53,3,FALSE) -> 0.1558
A41: Mutual Fund - Large & Mid Cap | B41: 0.15 | C41: ='3. Market Utility'!D15 -> 0.12875 | E41: Equity - Small Cap | F41: 0.25 | G41: =0.22-0.5*1*F41^2 -> 0.18875 | H41: =VLOOKUP(E41,A40:C54,3,FALSE) -> 0.16875
A42: Embassy Office Parks REIT | B42: 0.16 | C42: ='3. Market Utility'!D9 -> 0.0972
A43: Equity - Large Cap | B43: 0.17 | C43: ='3. Market Utility'!D14 -> 0.11555
A44: Equity - Mid Cap | B44: 0.22 | C44: ='3. Market Utility'!D16 -> 0.1558
A45: Equity - Small Cap | B45: 0.25 | C45: ='3. Market Utility'!D17 -> 0.16875
A46: Long-Short AIF | B46: 0.4 | C46: ='3. Market Utility'!D18 -> 0.17
A47: SHEET 4 - STRATEGIC ASSET ALLOCATION
A48: Asset Category | B48: Target Allocation
A49: Equity | B49: 55%
A50: Alternatives (Long-Short AIF) | B50: 15%
A51: Commodities (Gold) | B51: 10%
A52: REITs | B52: 10%
A53: Fixed Income | B53: 10%
A55: Rationale: High A(risk aversion)=1, long horizon (35+ yrs), low liquidity need -> tilts heavily to equity + alternatives for growth.
A57: SHEET 5 - PORTFOLIO OPTIMIZATION (best of 5,000 random scenarios, by utility at this client's A)
A58: Maximum Utility Achieved (across 5,000 scenarios) | B58: =B59-0.5*B14*B60^2 -> 0.13204441
A59: Winning Scenario Return | B59: ='5. Random Scenario Search'!M5 -> 0.13668
A60: Winning Scenario Risk | B60: ='5. Random Scenario Search'!N5 -> 0.096287017
A61: Winning Scenario Sharpe | B61: ='5. Random Scenario Search'!O5 -> 0.6405848
A63: Winning Portfolio Weights:
A64: Government Bonds | B64: 0.1313
A65: Corporate Bonds | B65: 0.1957
A66: Equity - Large Cap | B66: 0.0621
A67: Mutual Fund - L&M Cap | B67: 0.0143
A68: Embassy REIT | B68: 0.0095
A69: Equity - Small Cap | B69: 0.0692
A70: Equity - Mid Cap | B70: 0.1408
A71: Gold Commodity | B71: 0.2339
A72: Multi-Asset Allocation Fund | B72: 0.0406
A73: Long-Short AIF | B73: 0.1026
A75: SHEET 3 (cont'd) - INDIFFERENCE CURVE: Expected Return vs Risk/SD (guideline-required axes), all 14 market assets shown
A76: Curve equation: Return = U0 + 0.5 x A x Risk^2, where U0 = this client's own Maximum Utility Achieved (Sheet 5 above) and A=1. Points on the curve give equal utility to the client; points above/left of the curve are preferred to it, points below/right are inferior.
A77: Risk (SD) | B77: Return | C77: Utility
A78: =SQRT((B78-C78)/(0.5*$B$14)) -> 0.096287017 | B78: =B59 -> 0.13668 | C78: =B58 -> 0.13204441
A79: =SQRT((B79-C79)/(0.5*$B$14)) -> 0.11520065 | B79: =B78+0.2% -> 0.13868 | C79: =C78 -> 0.13204441
A80: =SQRT((B80-C80)/(0.5*$B$14)) -> 0.1314199 | B80: =B79+0.2% -> 0.14068 | C80: =C79 -> 0.13204441
A81: =SQRT((B81-C81)/(0.5*$B$14)) -> 0.14584646 | B81: =B80+0.2% -> 0.14268 | C81: =C80 -> 0.13204441
A82: =SQRT((B82-C82)/(0.5*$B$14)) -> 0.15896915 | B82: =B81+0.2% -> 0.14468 | C82: =C81 -> 0.13204441
A83: =SQRT((B83-C83)/(0.5*$B$14)) -> 0.17108825 | B83: =B82+0.2% -> 0.14668 | C83: =C82 -> 0.13204441
A84: =SQRT((B84-C84)/(0.5*$B$14)) -> 0.29878285 | B84: =B83+3% -> 0.17668 | C84: =C83 -> 0.13204441
A85: =SQRT((B85-C85)/(0.5*$B$14)) -> 0.3863563 | B85: =B84+3% -> 0.20668 | C85: =C84 -> 0.13204441
A86: =SQRT((B86-C86)/(0.5*$B$14)) -> 0.45746168 | B86: =B85+3% -> 0.23668 | C86: =C85 -> 0.13204441
A87: =SQRT((B87-C87)/(0.5*$B$14)) -> 0.51891347 | B87: =B86+3% -> 0.26668 | C87: =C86 -> 0.13204441
A88: =SQRT((B88-C88)/(0.5*$B$14)) -> 0.57382157 | B88: =B87+3% -> 0.29668 | C88: =C87 -> 0.13204441
A89: =SQRT((B89-C89)/(0.5*$B$14)) -> 0.62391601 | B89: =B88+3% -> 0.32668 | C89: =C88 -> 0.13204441
A91: All 14 Market Assets (for chart) - the 4 marked * are excluded from portfolio optimization (no correlation data) but shown here for reference
A92: Asset | B92: Risk (SD) | C92: Expected Return
A93: Government Bonds | B93: 0.02 | C93: 0.075
A94: Hybrid Debt Fund * | B94: 0.05 | C94: 0.08
A95: Pension Plan * | B95: 0.05 | C95: 0.08
A96: Corporate Bonds | B96: 0.05 | C96: 0.09
A97: Embassy Office Parks REIT | B97: 0.16 | C97: 0.11
A98: ULIPs * | B98: 0.11 | C98: 0.11
A99: Child Education Plan * | B99: 0.11 | C99: 0.11
A100: Gold Commodity | B100: 0.12 | C100: 0.12
A101: Multi-Asset Allocation Fund | B101: 0.13 | C101: 0.1278
A102: Equity - Large Cap | B102: 0.17 | C102: 0.13
A103: Mutual Fund - Large & Mid Cap | B103: 0.15 | C103: 0.14
A104: Equity - Mid Cap | B104: 0.22 | C104: 0.18
... A106: Long-Short AIF | B106: 0.4 | C106: 0.25
A121: CLIENT THOUGHT ON WINNING PORTFOLIO
A122: Expanding my product awareness across new and non-traditional asset classes has fundamentally reshaped my investment strategy. Given my 35-year investment horizon and aggressive risk profile ($A=1$), moving away from traditional single-asset stock picking toward an optimized, multi-asset portfolio allowed me to unlock significant diversification benefits
A128: ADVISOR NOTE - PRODUCT AWARENESS GAPS
A129: Deven’s current investment awareness is restricted to a subset of traditional asset classes, including Government Bonds, Corporate Bonds, Embassy Office Parks REIT, Gold Commodity, Multi-Asset Allocation Funds, Large-Cap Equity, Large & Mid-Cap Mutual Funds, Mid-Cap Equity, and Small-Cap Equity. Consequently, introducing him to broader asset categories and modern portfolio diversification strategies represents a primary value-add for the advisor.
...

Sheet Jai
A1: CLIENT: Jai Kumar Agarwal (A = 1, Aggressive, self-identifies as Risk Seeker)
A3: SHEET 1 - CLIENT RISK PROFILE
A4: Age | B4: 23
A5: Investment Objective | B5: Wealth Creation
A6: Primary Financial Goal | B6: Retirement
A7: Goal Target Amount (Rs) | B7: 120000000
A8: Years to Goal | B8: 30
A9: Monthly SIP Capacity (Rs) | B9: 20000
A10: Required Annual Return (goal-implied) | B10: 0.1537
A11: Investment Horizon (yrs) | B11: 37
A12: Liquidity Requirement | B12: Medium
A13: Max Acceptable 1-yr Loss | B13: 0.2
A14: Risk Aversion Coefficient (A) | B14: 1
A15: Risk Profile Band | B15: Aggressive
A17: SHEET 3 - UTILITY & INDIFFERENCE CURVES (client's own beliefs, own aware assets only)
A18: Product | B18: Client Exp. Return | C18: Client Exp. Risk | D18: Utility of an Investor | E18: Product Risk from Market | F18: Product Return from Market | G18: Market Utility A=1 | H18: Difference
A19: Government Bonds | B19: 0.07 | C19: 0.03 | D19: =B19-0.5*1*C19^2 -> 0.06955 | E19: 0.02 | F19: 0.075 | G19: ='3. Market Utility'!D5 -> 0.0748 | H19: =D19-G19 -> -0.00525
A20: Corporate Bonds | B20: 0.1 | C20: 0.07 | D20: =B20-0.5*1*C20^2 -> 0.09755 | E20: 0.05 | F20: 0.09 | G20: ='3. Market Utility'!D8 -> 0.08875 | H20: =D20-G20 -> 0.0088
A21: Embassy Office Parks REIT | B21: 0.11 | C21: 0.13 | D21: =B21-0.5*1*C21^2 -> 0.10155 | E21: 0.16 | F21: 0.11 | G21: ='3. Market Utility'!D9 -> 0.0972 | H21: =D21-G21 -> 0.00435
A22: Gold Commodity | B22: 0.11 | C22: 0.13 | D22: =B22-0.5*1*C22^2 -> 0.10155 | E22: 0.12 | F22: 0.12 | G22: ='3. Market Utility'!D12 -> 0.1128 | H22: =D22-G22 -> -0.01125
A23: Multi-Asset Allocation Fund | B23: 0.1 | C23: 0.12 | D23: =B23-0.5*1*C23^2 -> 0.0928 | E23: 0.13 | F23: 0.1278 | G23: ='3. Market Utility'!D13 -> 0.11935 | H23: =D23-G23 -> -0.02655
A24: Equity - Large Cap | B24: 0.11 | C24: 0.08 | D24: =B24-0.5*1*C24^2 -> 0.1068 | E24: 0.17 | F24: 0.13 | G24: ='3. Market Utility'!D14 -> 0.11555 | H24: =D24-G24 -> -0.00875
A25: Mutual Fund - Large & Mid Cap | B25: 0.11 | C25: 0.08 | D25: =B25-0.5*1*C25^2 -> 0.1068 | E25: 0.15 | F25: 0.14 | G25: ='3. Market Utility'!D15 -> 0.12875 | H25: =D25-G25 -> -0.02195
A26: Equity - Mid Cap | B26: 0.14 | C26: 0.18 | D26: =B26-0.5*1*C26^2 -> 0.1238 | E26: 0.22 | F26: 0.18 | G26: ='3. Market Utility'!D16 -> 0.1558 | H26: =D26-G26 -> -0.032
A27: Equity - Small Cap | B27: 0.2 | C27: 0.23 | D27: =B27-0.5*1*C27^2 -> 0.17355 | E27: 0.25 | F27: 0.2 | G27: ='3. Market Utility'!D17 -> 0.16875 | H27: =D27-G27 -> 0.0048
A28: Long-Short AIF | B28: 0.12 | C28: 0.15 | D28: =B28-0.5*1*C28^2 -> 0.10875 | E28: 0.4 | F28: 0.25 | G28: ='3. Market Utility'!D18 -> 0.17 | H28: =D28-G28 -> -0.06125
A30: Positive Difference = client OVER-estimates the asset's attractiveness vs the market view (Blue above Orange). Negative = client UNDER-estimates it / is more pessimistic than the market.
A32: MARKET UTILITY CURVE (all 14 assets, at A=1) vs CLIENT'S OWN UTILITY CURVE
A33: Asset (market, sorted by SD) | B33: Market SD | C33: Market Utility | E33: Asset (client belief, sorted by SD) | F33: Client SD | G33: Client Product Utility | H33: Market Product Utility | J33: CAL Utility | K33: Risk | L33: Return | M33: Utility (A=1)
A34: Government Bonds | B34: 0.02 | C34: ='3. Market Utility'!D5 -> 0.0748 | E34: Government Bonds | F34: 0.03 | G34: =0.07-0.5*1*F34^2 -> 0.06955 | H34: =VLOOKUP(E34,A34:C47,3,FALSE) -> 0.0748 | J34: Risk-free | K34: ='4. Efficient Frontier'!B79 -> 0 | L34: ='4. Efficient Frontier'!C79 -> 0.075 | M34: ='4. Efficient Frontier'!D79 -> 0.075
A35: Hybrid Debt Fund | B35: 0.05 | C35: ='3. Market Utility'!D6 -> 0.07875 | E35: Corporate Bonds | F35: 0.07 | G35: =0.1-0.5*1*F35^2 -> 0.09755 | H35: =VLOOKUP(E35,A35:C48,3,FALSE) -> 0.08875 | J35: Tangency | K35: ='4. Efficient Frontier'!B80 -> 0.083709891 | L35: ='4. Efficient Frontier'!C80 -> 0.135908 | M35: ='4. Efficient Frontier'!D80 -> 0.13240433
A36: Pension Plan | B36: 0.05 | C36: ='3. Market Utility'!D7 -> 0.07875 | E36: Equity - Large Cap | F36: 0.08 | G36: =0.11-0.5*1*F36^2 -> 0.1068 | H36: =VLOOKUP(E36,A36:C49,3,FALSE) -> 0.11555 | J36: CAL extended | K36: ='4. Efficient Frontier'!B81 -> 0.14233792 | L36: ='4. Efficient Frontier'!C81 -> 0.17857871 | M36: ='4. Efficient Frontier'!D81 -> 0.16844866
A37: Corporate Bonds | B37: 0.05 | C37: ='3. Market Utility'!D8 -> 0.08875 | E37: Mutual Fund - Large & Mid Cap | F37: 0.08 | G37: =0.11-0.5*1*F37^2 -> 0.1068 | H37: =VLOOKUP(E37,A37:C50,3,FALSE) -> 0.12875
A38: ULIPs | B38: 0.11 | C38: ='3. Market Utility'!D10 -> 0.10395 | E38: Multi-Asset Allocation Fund | F38: 0.12 | G38: =0.1-0.5*1*F38^2 -> 0.0928 | H38: =VLOOKUP(E38,A38:C51,3,FALSE) -> 0.11935
A39: Child Education Plan | B39: 0.11 | C39: ='3. Market Utility'!D11 -> 0.10395 | E39: Embassy Office Parks REIT | F39: 0.13 | G39: =0.11-0.5*1*F39^2 -> 0.10155 | H39: =VLOOKUP(E39,A39:C52,3,FALSE) -> 0.0972
A40: Gold Commodity | B40: 0.12 | C40: ='3. Market Utility'!D12 -> 0.1128 | E40: Gold Commodity | F40: 0.13 | G40: =0.11-0.5*1*F40^2 -> 0.10155 | H40: =VLOOKUP(E40,A40:C53,3,FALSE) -> 0.1128
A41: Multi-Asset Allocation Fund | B41: 0.13 | C41: ='3. Market Utility'!D13 -> 0.11935 | E41: Long-Short AIF | F41: 0.15 | G41: =0.12-0.5*1*F41^2 -> 0.10875 | H41: =VLOOKUP(E41,A41:C54,3,FALSE) -> 0.17
A42: Mutual Fund - Large & Mid Cap | B42: 0.15 | C42: ='3. Market Utility'!D15 -> 0.12875 | E42: Equity - Mid Cap | F42: 0.18 | G42: =0.14-0.5*1*F42^2 -> 0.1238 | H42: =VLOOKUP(E42,A42:C55,3,FALSE) -> 0.1558
A43: Embassy Office Parks REIT | B43: 0.16 | C43: ='3. Market Utility'!D9 -> 0.0972 | E43: Equity - Small Cap | F43: 0.23 | G43: =0.2-0.5*1*F43^2 -> 0.17355 | H43: =VLOOKUP(E43,A43:C56,3,FALSE) -> 0.16875
A44: Equity - Large Cap | B44: 0.17 | C44: ='3. Market Utility'!D14 -> 0.11555
A45: Equity - Mid Cap | B45: 0.22 | C45: ='3. Market Utility'!D16 -> 0.1558
A46: Equity - Small Cap | B46: 0.25 | C46: ='3. Market Utility'!D17 -> 0.16875
A47: Long-Short AIF | B47: 0.4 | C47: ='3. Market Utility'!D18 -> 0.17
A48: SHEET 4 - STRATEGIC ASSET ALLOCATION
A49: Asset Category | B49: Target Allocation
A50: Equity | B50: 55%
A51: Alternatives (Long-Short AIF) | B51: 15%
A52: Commodities (Gold) | B52: 10%
A53: REITs | B53: 10%
A54: Fixed Income | B54: 10%
A56: Rationale: High A(risk aversion)=1, long horizon (37+ yrs), low liquidity need -> tilts heavily to equity + alternatives for growth.
A58: SHEET 5 - PORTFOLIO OPTIMIZATION (best of 5,000 random scenarios, by utility at this client's A)
A59: Maximum Utility Achieved (across 5,000 scenarios) | B59: =B60-0.5*B14*B61^2 -> 0.13110734
A60: Winning Scenario Return | B60: ='5. Random Scenario Search'!M6 -> 0.13561
A61: Winning Scenario Risk | B61: ='5. Random Scenario Search'!N6 -> 0.094896392
A62: Winning Scenario Sharpe | B62: ='5. Random Scenario Search'!O6 -> 0.63869657
A64: Winning Portfolio Weights:
A65: Government Bonds | B65: 0.1313
A66: Corporate Bonds | B66: 0.1957
A67: Equity - Large Cap | B67: 0.0621
A68: Mutual Fund - L&M Cap | B68: 0.0143
A69: Embassy REIT | B69: 0.0095
A70: Equity - Small Cap | B70: 0.0692
A71: Equity - Mid Cap | B71: 0.1408
A72: Gold Commodity | B72: 0.2339
A73: Multi-Asset Allocation Fund | B73: 0.0406
A74: Long-Short AIF | B74: 0.1026
A76: SHEET 3 (cont'd) - INDIFFERENCE CURVE: Expected Return vs Risk/SD (guideline-required axes), all 14 market assets shown
A77: Curve equation: Return = U0 + 0.5 x A x Risk^2, where U0 = this client's own Maximum Utility Achieved (Sheet 5 above) and A=1. Points on the curve give equal utility to the client; points above/left of the curve are preferred to it, points below/right are inferior.
A78: Risk (SD) | B78: Indifference Curve Return | C78: Utility
A79: =SQRT((B79-C79)/(0.5*$B$14)) -> 0.094896392 | B79: =B60 -> 0.13561 | C79: =B59 -> 0.13110734
A80: =SQRT((B80-C80)/(0.5*$B$14)) -> 0.11404089 | B80: =B79+0.2% -> 0.13761 | C80: =C79 -> 0.13110734
A81: =SQRT((B81-C81)/(0.5*$B$14)) -> 0.13040447 | B81: =B80+0.2% -> 0.13961 | C81: =C80 -> 0.13110734
A82: =SQRT((B82-C82)/(0.5*$B$14)) -> 0.14493214 | B82: =B81+0.2% -> 0.14161 | C82: =C81 -> 0.13110734
A83: =SQRT((B83-C83)/(0.5*$B$14)) -> 0.15813072 | B83: =B82+0.2% -> 0.14361 | C83: =C82 -> 0.13110734
A84: =SQRT((B84-C84)/(0.5*$B$14)) -> 0.1703095 | B84: =B83+0.2% -> 0.14561 | C84: =C83 -> 0.13110734
A85: =SQRT((B85-C85)/(0.5*$B$14)) -> 0.2983376 | B85: =B84+3% -> 0.17561 | C85: =C84 -> 0.13110734
A86: =SQRT((B86-C86)/(0.5*$B$14)) -> 0.38601208 | B86: =B85+3% -> 0.20561 | C86: =C85 -> 0.13110734
A87: =SQRT((B87-C87)/(0.5*$B$14)) -> 0.457171 | B87: =B86+3% -> 0.23561 | C87: =C86 -> 0.13110734
A88: =SQRT((B88-C88)/(0.5*$B$14)) -> 0.51865723 | B88: =B87+3% -> 0.26561 | C88: =C87 -> 0.13110734
A89: =SQRT((B89-C89)/(0.5*$B$14)) -> 0.57358986 | B89: =B88+3% -> 0.29561 | C89: =C88 -> 0.13110734
A90: =SQRT((B90-C90)/(0.5*$B$14)) -> 0.62370291 | B90: =B89+3% -> 0.32561 | C90: =C89 -> 0.13110734
A92: All 14 Market Assets (for chart) - the 4 marked * are excluded from portfolio optimization (no correlation data) but shown here for reference
A93: Asset | B93: Risk (SD) | C93: Expected Return
A94: Government Bonds | B94: 0.02 | C94: 0.075
A95: Hybrid Debt Fund * | B95: 0.05 | C95: 0.08
A96: Pension Plan * | B96: 0.05 | C96: 0.08
A97: Corporate Bonds | B97: 0.05 | C97: 0.09
A98: Embassy Office Parks REIT | B98: 0.16 | C98: 0.11
A99: ULIPs * | B99: 0.11 | C99: 0.11
A100: Child Education Plan * | B100: 0.11 | C100: 0.11
A101: Gold Commodity | B101: 0.12 | C101: 0.12
A102: Multi-Asset Allocation Fund | B102: 0.13 | C102: 0.1278
A103: Equity - Large Cap | B103: 0.17 | C103: 0.13
A104: Mutual Fund - Large & Mid Cap | B104: 0.15 | C104: 0.14
A105: Equity - Mid Cap | B105: 0.22 | C105: 0.18
... A107: Long-Short AIF | B107: 0.4 | C107: 0.25
A125: CLIENT THOUGHT ON WINNING PORTFOLIO
A126: Expanding my product awareness across new and non-traditional asset classes has fundamentally reshaped my investment strategy. Given my 35-year investment horizon and aggressive risk profile (A=1), moving away from traditional single-asset stock picking toward an optimized, multi-asset portfolio allowed me to unlock significant diversification benefits
A132: ADVISOR NOTE - PRODUCT AWARENESS GAPS
...

Sheet Manik
A1: CLIENT: Manik Ratty (A = 3, Moderate, self-identifies as Risk Seeker)
A3: SHEET 1 - CLIENT RISK PROFILE
A4: Age | B4: 24
A5: Investment Objective | B5: Wealth Creation
A6: Primary Financial Goal | B6: Retirement
A7: Goal Target Amount (Rs) | B7: 30000000
A8: Years to Goal | B8: 20
A9: Monthly SIP Capacity (Rs) | B9: 10000
A10: Required Annual Return (goal-implied) | B10: 0.2165
A11: Investment Horizon (yrs) | B11: 30
A12: Liquidity Requirement | B12: Low
A13: Max Acceptable 1-yr Loss | B13: 0.3
A14: Risk Aversion Coefficient (A) | B14: 3
A15: Risk Profile Band | B15: Moderate
A17: SHEET 3 - UTILITY & INDIFFERENCE CURVES (client's own beliefs, own aware assets only)
A18: Product | B18: Client Exp. Return | C18: Client Exp. Risk | D18: Utility of an Investor | E18: Product Risk from Market | F18: Product Return from Market | G18: Market Utility A=3 | H18: Difference
A19: Government Bonds | B19: 0.07 | C19: 0.03 | D19: =B19-0.5*3*C19^2 -> 0.06865 | E19: 0.02 | F19: 0.075 | G19: ='3. Market Utility'!F5 -> 0.0744 | H19: =D19-G19 -> -0.00575
A20: Corporate Bonds | B20: 0.09 | C20: 0.06 | D20: =B20-0.5*3*C20^2 -> 0.0846 | E20: 0.05 | F20: 0.09 | G20: ='3. Market Utility'!F8 -> 0.08625 | H20: =D20-G20 -> -0.00165
A21: Embassy Office Parks REIT | B21: 0.11 | C21: 0.12 | D21: =B21-0.5*3*C21^2 -> 0.0884 | E21: 0.16 | F21: 0.11 | G21: ='3. Market Utility'!F9 -> 0.0716 | H21: =D21-G21 -> 0.0168
A22: Gold Commodity | B22: 0.1 | C22: 0.12 | D22: =B22-0.5*3*C22^2 -> 0.0784 | E22: 0.12 | F22: 0.12 | G22: ='3. Market Utility'!F12 -> 0.0984 | H22: =D22-G22 -> -0.02
A23: Multi-Asset Allocation Fund | B23: 0.11 | C23: 0.1 | D23: =B23-0.5*3*C23^2 -> 0.095 | E23: 0.13 | F23: 0.1278 | G23: ='3. Market Utility'!F13 -> 0.10245 | H23: =D23-G23 -> -0.00745
A24: Equity - Large Cap | B24: 0.13 | C24: 0.15 | D24: =B24-0.5*3*C24^2 -> 0.09625 | E24: 0.17 | F24: 0.13 | G24: ='3. Market Utility'!F14 -> 0.08665 | H24: =D24-G24 -> 0.0096
A25: Mutual Fund - Large & Mid Cap | B25: 0.14 | C25: 0.17 | D25: =B25-0.5*3*C25^2 -> 0.09665 | E25: 0.15 | F25: 0.14 | G25: ='3. Market Utility'!F15 -> 0.10625 | H25: =D25-G25 -> -0.0096
A26: Equity - Mid Cap | B26: 0.16 | C26: 0.22 | D26: =B26-0.5*3*C26^2 -> 0.0874 | E26: 0.22 | F26: 0.18 | G26: ='3. Market Utility'!F16 -> 0.1074 | H26: =D26-G26 -> -0.02
A27: Equity - Small Cap | B27: 0.2 | C27: 0.28 | D27: =B27-0.5*3*C27^2 -> 0.0824 | E27: 0.25 | F27: 0.2 | G27: ='3. Market Utility'!F17 -> 0.10625 | H27: =D27-G27 -> -0.02385
A28: Long-Short AIF | B28: 0.15 | C28: 0.18 | D28: =B28-0.5*3*C28^2 -> 0.1014 | E28: 0.4 | F28: 0.25 | G28: ='3. Market Utility'!F18 -> 0.01 | H28: =D28-G28 -> 0.0914
A30: Positive Difference = client OVER-estimates the asset's attractiveness vs the market view (Blue above Orange). Negative = client UNDER-estimates it / is more pessimistic than the market.
A32: MARKET UTILITY CURVE (all 14 assets, at A=3) vs CLIENT'S OWN UTILITY CURVE
A33: Asset (market, sorted by SD) | B33: Market SD | C33: Market Utility | E33: Asset (client belief, sorted by SD) | F33: Client SD | G33: Client Utility | H33: Market Utility
A34: Government Bonds | B34: 0.02 | C34: ='3. Market Utility'!F5 -> 0.0744 | E34: Government Bonds | F34: 0.03 | G34: =0.07-0.5*3*F34^2 -> 0.06865 | H34: =VLOOKUP(E34,A33:C47,3,FALSE) -> 0.0744 | J34: CAL Utility | K34: Risk | L34: Return | M34: Utility (A=1)
A35: Hybrid Debt Fund | B35: 0.05 | C35: ='3. Market Utility'!F6 -> 0.07625 | E35: Corporate Bonds | F35: 0.06 | G35: =0.09-0.5*3*F35^2 -> 0.0846 | H35: =VLOOKUP(E35,A34:C48,3,FALSE) -> 0.08625 | J35: Risk-free | K35: ='4. Efficient Frontier'!B79 -> 0 | L35: ='4. Efficient Frontier'!C79 -> 0.075 | M35: ='4. Efficient Frontier'!E79 -> 0.075
A36: Pension Plan | B36: 0.05 | C36: ='3. Market Utility'!F7 -> 0.07625 | E36: Multi-Asset Allocation Fund | F36: 0.1 | G36: =0.11-0.5*3*F36^2 -> 0.095 | H36: =VLOOKUP(E36,A35:C49,3,FALSE) -> 0.10245 | J36: Tangency | K36: ='4. Efficient Frontier'!B80 -> 0.083709891 | L36: ='4. Efficient Frontier'!C80 -> 0.135908 | M36: ='4. Efficient Frontier'!E80 -> 0.13240433
A37: Corporate Bonds | B37: 0.05 | C37: ='3. Market Utility'!F8 -> 0.08625 | E37: Embassy Office Parks REIT | F37: 0.12 | G37: =0.11-0.5*3*F37^2 -> 0.0884 | H37: =VLOOKUP(E37,A36:C50,3,FALSE) -> 0.0716 | J37: CAL extended | K37: ='4. Efficient Frontier'!B81 -> 0.14233792 | L37: ='4. Efficient Frontier'!C81 -> 0.17857871 | M37: ='4. Efficient Frontier'!E81 -> 0.16844866
A38: ULIPs | B38: 0.11 | C38: ='3. Market Utility'!F10 -> 0.09185 | E38: Gold Commodity | F38: 0.12 | G38: =0.1-0.5*3*F38^2 -> 0.0784 | H38: =VLOOKUP(E38,A37:C51,3,FALSE) -> 0.0984
A39: Child Education Plan | B39: 0.11 | C39: ='3. Market Utility'!F11 -> 0.09185 | E39: Equity - Large Cap | F39: 0.15 | G39: =0.13-0.5*3*F39^2 -> 0.09625 | H39: =VLOOKUP(E39,A38:C52,3,FALSE) -> 0.08665
A40: Gold Commodity | B40: 0.12 | C40: ='3. Market Utility'!F12 -> 0.0984 | E40: Mutual Fund - Large & Mid Cap | F40: 0.17 | G40: =0.14-0.5*3*F40^2 -> 0.09665 | H40: =VLOOKUP(E40,A39:C53,3,FALSE) -> 0.10625
A41: Multi-Asset Allocation Fund | B41: 0.13 | C41: ='3. Market Utility'!F13 -> 0.10245 | E41: Long-Short AIF | F41: 0.18 | G41: =0.15-0.5*3*F41^2 -> 0.1014 | H41: =VLOOKUP(E41,A40:C54,3,FALSE) -> 0.01
A42: Mutual Fund - Large & Mid Cap | B42: 0.15 | C42: ='3. Market Utility'!F15 -> 0.10625 | E42: Equity - Mid Cap | F42: 0.22 | G42: =0.16-0.5*3*F42^2 -> 0.0874 | H42: =VLOOKUP(E42,A41:C55,3,FALSE) -> 0.1074
A43: Embassy Office Parks REIT | B43: 0.16 | C43: ='3. Market Utility'!F9 -> 0.0716 | E43: Equity - Small Cap | F43: 0.28 | G43: =0.2-0.5*3*F43^2 -> 0.0824 | H43: =VLOOKUP(E43,A42:C56,3,FALSE) -> 0.10625
A44: Equity - Large Cap | B44: 0.17 | C44: ='3. Market Utility'!F14 -> 0.08665
A45: Equity - Mid Cap | B45: 0.22 | C45: ='3. Market Utility'!F16 -> 0.1074
A46: Equity - Small Cap | B46: 0.25 | C46: ='3. Market Utility'!F17 -> 0.10625
A47: Long-Short AIF | B47: 0.4 | C47: ='3. Market Utility'!F18 -> 0.01
A48: SHEET 4 - STRATEGIC ASSET ALLOCATION
A49: Asset Category | B49: Target Allocation
A50: Equity | B50: 35%
A51: Fixed Income | B51: 30%
A52: Commodities (Gold) | B52: 15%
A53: Multi-Asset | B53: 10%
A54: REITs | B54: 10%
A56: Rationale: Moderate A=3, Low liquidity need, 30% max loss tolerance -> balanced equity/fixed-income mix with gold as a stabilizer.
A58: SHEET 5 - PORTFOLIO OPTIMIZATION (best of 5,000 random scenarios, by utility at this client's A)
A59: Maximum Utility Achieved (across 5,000 scenarios) | B59: =B60-0.5*B14*B61^2 -> 0.12210201
A60: Winning Scenario Return | B60: ='5. Random Scenario Search'!M6 -> 0.13561
A61: Winning Scenario Risk | B61: ='5. Random Scenario Search'!N6 -> 0.094896392
A62: Winning Scenario Sharpe | B62: ='5. Random Scenario Search'!O6 -> 0.63869657
A64: Winning Portfolio Weights:
A65: Government Bonds | B65: 0.1313
A66: Corporate Bonds | B66: 0.1957
A67: Equity - Large Cap | B67: 0.0621
A68: Mutual Fund - L&M Cap | B68: 0.0143
A69: Embassy REIT | B69: 0.0095
A70: Equity - Small Cap | B70: 0.0692
A71: Equity - Mid Cap | B71: 0.1408
A72: Gold Commodity | B72: 0.2339
A73: Multi-Asset Allocation Fund | B73: 0.0406
A74: Long-Short AIF | B74: 0.1026
A76: SHEET 3 (cont'd) - INDIFFERENCE CURVE: Expected Return vs Risk/SD (guideline-required axes), all 14 market assets shown
A77: Curve equation: Return = U0 + 0.5 x A x Risk^2, where U0 = this client's own Maximum Utility Achieved (Sheet 5 above) and A=1. Points on the curve give equal utility to the client; points above/left of the curve are preferred to it, points below/right are inferior.
A78: Risk (SD) | B78: Indifference Curve Return | C78: Utility
A79: =SQRT((B79-C79)/(0.5*$B$14)) -> 0.094896392 | B79: =B60 -> 0.13561 | C79: =B59 -> 0.12210201
A80: =SQRT((B80-C80)/(0.5*$B$14)) -> 0.10167919 | B80: =B79+0.2% -> 0.13761 | C80: =C79 -> 0.12210201
A81: =SQRT((B81-C81)/(0.5*$B$14)) -> 0.10803699 | B81: =B80+0.2% -> 0.13961 | C81: =C80 -> 0.12210201
A82: =SQRT((B82-C82)/(0.5*$B$14)) -> 0.11404089 | B82: =B81+0.2% -> 0.14161 | C82: =C81 -> 0.12210201
A83: =SQRT((B83-C83)/(0.5*$B$14)) -> 0.11974414 | B83: =B82+0.2% -> 0.14361 | C83: =C82 -> 0.12210201
A84: =SQRT((B84-C84)/(0.5*$B$14)) -> 0.12518783 | B84: =B83+0.2% -> 0.14561 | C84: =C83 -> 0.12210201
A85: =SQRT((B85-C85)/(0.5*$B$14)) -> 0.1888703 | B85: =B84+3% -> 0.17561 | C85: =C84 -> 0.12210201
A86: =SQRT((B86-C86)/(0.5*$B$14)) -> 0.23594913 | B86: =B85+3% -> 0.20561 | C86: =C85 -> 0.12210201
A87: =SQRT((B87-C87)/(0.5*$B$14)) -> 0.27508543 | B87: =B86+3% -> 0.23561 | C87: =C86 -> 0.12210201
A88: =SQRT((B88-C88)/(0.5*$B$14)) -> 0.30930889 | B88: =B87+3% -> 0.26561 | C88: =C87 -> 0.12210201
A89: =SQRT((B89-C89)/(0.5*$B$14)) -> 0.34010585 | B89: =B88+3% -> 0.29561 | C89: =C88 -> 0.12210201
A90: =SQRT((B90-C90)/(0.5*$B$14)) -> 0.36833679 | B90: =B89+3% -> 0.32561 | C90: =C89 -> 0.12210201
A92: All 14 Market Assets (for chart) - the 4 marked * are excluded from portfolio optimization (no correlation data) but shown here for reference
A93: Asset | B93: Risk (SD) | C93: Expected Return
A94: Government Bonds | B94: 0.02 | C94: 0.075
A95: Hybrid Debt Fund * | B95: 0.05 | C95: 0.08
A96: Pension Plan * | B96: 0.05 | C96: 0.08
A97: Corporate Bonds | B97: 0.05 | C97: 0.09
A98: Embassy Office Parks REIT | B98: 0.16 | C98: 0.11
A99: ULIPs * | B99: 0.11 | C99: 0.11
A100: Child Education Plan * | B100: 0.11 | C100: 0.11
A101: Gold Commodity | B101: 0.12 | C101: 0.12
A102: Multi-Asset Allocation Fund | B102: 0.13 | C102: 0.1278
A103: Equity - Large Cap | B103: 0.17 | C103: 0.13
A104: Mutual Fund - Large & Mid Cap | B104: 0.15 | C104: 0.14
A105: Equity - Mid Cap | B105: 0.22 | C105: 0.18
... A107: Long-Short AIF | B107: 0.4 | C107: 0.25
A125: CLIENT THOUGHT ON WINNING PORTFOLIO
A126: Expanding my product awareness across new and non-traditional asset classes has fundamentally reshaped my investment strategy. Given my 30-year investment horizon and moderate risk profile (A=3), moving away from traditional single-asset stock picking toward an optimized, multi-asset portfolio allowed me to unlock significant diversification benefits.
A131: ADVISOR NOTE - PRODUCT AWARENESS GAPS
...

Sheet Tarana
A1: CLIENT: Tarana Bansal (A = 3, Moderate, self-identifies as Risk Seeker)
A3: SHEET 1 - CLIENT RISK PROFILE
A4: Age | B4: 22
A5: Investment Objective | B5: Wealth Creation and House Purchase
A6: Primary Financial Goal | B6: Wealth / Money
A7: Goal Target Amount (Rs) | B7: 5000000
A8: Years to Goal | B8: 10
A9: Monthly SIP Capacity (Rs) | B9: 25000
A10: Required Annual Return (goal-implied) | B10: 0.1001
A11: Investment Horizon (yrs) | B11: 40
A12: Liquidity Requirement | B12: Low
A13: Max Acceptable 1-yr Loss | B13: 0.25
A14: Risk Aversion Coefficient (A) | B14: 3
A15: Risk Profile Band | B15: Moderate
A17: SHEET 3 - UTILITY & INDIFFERENCE CURVES (client's own beliefs, own aware assets only)
A18: Product | B18: Client Exp. Return | C18: Client Exp. Risk | D18: Utility of an Investor | E18: Product Risk from Market | F18: Product Return from Market | G18: Market Utility A=3 | H18: Difference
A19: Government Bonds | B19: 0.05 | C19: 0 | D19: =B19-0.5*3*C19^2 -> 0.05 | E19: 0.02 | F19: 0.075 | G19: ='3. Market Utility'!F5 -> 0.0744 | H19: =D19-G19 -> -0.0244
A20: Corporate Bonds | B20: 0.08 | C20: 0.07 | D20: =B20-0.5*3*C20^2 -> 0.07265 | E20: 0.05 | F20: 0.09 | G20: ='3. Market Utility'!F8 -> 0.08625 | H20: =D20-G20 -> -0.0136
A21: Gold Commodity | B21: 0.1 | C21: 0.1 | D21: =B21-0.5*3*C21^2 -> 0.085 | E21: 0.12 | F21: 0.12 | G21: ='3. Market Utility'!F12 -> 0.0984 | H21: =D21-G21 -> -0.0134
A22: Multi-Asset Allocation Fund | B22: 0.085 | C22: 0.04 | D22: =B22-0.5*3*C22^2 -> 0.0826 | E22: 0.13 | F22: 0.1278 | G22: ='3. Market Utility'!F13 -> 0.10245 | H22: =D22-G22 -> -0.01985
A23: Equity - Large Cap | B23: 0.1 | C23: 0.07 | D23: =B23-0.5*3*C23^2 -> 0.09265 | E23: 0.17 | F23: 0.13 | G23: ='3. Market Utility'!F14 -> 0.08665 | H23: =D23-G23 -> 0.006
A24: Mutual Fund - Large & Mid Cap | B24: 0.11 | C24: 0.08 | D24: =B24-0.5*3*C24^2 -> 0.1004 | E24: 0.15 | F24: 0.14 | G24: ='3. Market Utility'!F15 -> 0.10625 | H24: =D24-G24 -> -0.00585
A25: Equity - Mid Cap | B25: 0.12 | C25: 0.15 | D25: =B25-0.5*3*C25^2 -> 0.08625 | E25: 0.22 | F25: 0.18 | G25: ='3. Market Utility'!F16 -> 0.1074 | H25: =D25-G25 -> -0.02115
A26: Equity - Small Cap | B26: 0.15 | C26: 0.2 | D26: =B26-0.5*3*C26^2 -> 0.09 | E26: 0.25 | F26: 0.2 | G26: ='3. Market Utility'!F17 -> 0.10625 | H26: =D26-G26 -> -0.01625
A28: Positive Difference = client OVER-estimates the asset's attractiveness vs the market view (Blue above Orange). Negative = client UNDER-estimates it / is more pessimistic than the market.
A30: MARKET UTILITY CURVE (all 14 assets, at A=3) vs CLIENT'S OWN UTILITY CURVE
A31: Asset (market, sorted by SD) | B31: Market SD | C31: Market Utility | E31: Asset (client belief, sorted by SD) | F31: Client SD | G31: Client Utility | H31: Market Utility | J31: CAL Utility | K31: Risk | L31: Return | M31: Utility (A=1)
A32: Government Bonds | B32: 0.02 | C32: ='3. Market Utility'!F5 -> 0.0744 | E32: Government Bonds | F32: 0 | G32: =0.05-0.5*3*F32^2 -> 0.05 | H32: =VLOOKUP(E32,A31:C45,3,FALSE) -> 0.0744 | J32: Risk-free | K32: ='4. Efficient Frontier'!B79 -> 0 | L32: ='4. Efficient Frontier'!C79 -> 0.075 | M32: ='4. Efficient Frontier'!E79 -> 0.075
A33: Hybrid Debt Fund | B33: 0.05 | C33: ='3. Market Utility'!F6 -> 0.07625 | E33: Multi-Asset Allocation Fund | F33: 0.04 | G33: =0.085-0.5*3*F33^2 -> 0.0826 | H33: =VLOOKUP(E33,A32:C46,3,FALSE) -> 0.10245 | J33: Tangency | K33: ='4. Efficient Frontier'!B80 -> 0.083709891 | L33: ='4. Efficient Frontier'!C80 -> 0.135908 | M33: ='4. Efficient Frontier'!E80 -> 0.13240433
A34: Pension Plan | B34: 0.05 | C34: ='3. Market Utility'!F7 -> 0.07625 | E34: Corporate Bonds | F34: 0.07 | G34: =0.08-0.5*3*F34^2 -> 0.07265 | H34: =VLOOKUP(E34,A33:C47,3,FALSE) -> 0.08625 | J34: CAL extended | K34: ='4. Efficient Frontier'!B81 -> 0.14233792 | L34: ='4. Efficient Frontier'!C81 -> 0.17857871 | M34: ='4. Efficient Frontier'!E81 -> 0.16844866
A35: Corporate Bonds | B35: 0.05 | C35: ='3. Market Utility'!F8 -> 0.08625 | E35: Equity - Large Cap | F35: 0.07 | G35: =0.1-0.5*3*F35^2 -> 0.09265 | H35: =VLOOKUP(E35,A34:C48,3,FALSE) -> 0.08665
A36: ULIPs | B36: 0.11 | C36: ='3. Market Utility'!F10 -> 0.09185 | E36: Mutual Fund - Large & Mid Cap | F36: 0.08 | G36: =0.11-0.5*3*F36^2 -> 0.1004 | H36: =VLOOKUP(E36,A35:C49,3,FALSE) -> 0.10625
A37: Child Education Plan | B37: 0.11 | C37: ='3. Market Utility'!F11 -> 0.09185 | E37: Gold Commodity | F37: 0.1 | G37: =0.1-0.5*3*F37^2 -> 0.085 | H37: =VLOOKUP(E37,A36:C50,3,FALSE) -> 0.0984
A38: Gold Commodity | B38: 0.12 | C38: ='3. Market Utility'!F12 -> 0.0984 | E38: Equity - Mid Cap | F38: 0.15 | G38: =0.12-0.5*3*F38^2 -> 0.08625 | H38: =VLOOKUP(E38,A37:C51,3,FALSE) -> 0.1074
A39: Multi-Asset Allocation Fund | B39: 0.13 | C39: ='3. Market Utility'!F13 -> 0.10245 | E39: Equity - Small Cap | F39: 0.2 | G39: =0.15-0.5*3*F39^2 -> 0.09 | H39: =VLOOKUP(E39,A38:C52,3,FALSE) -> 0.10625
A40: Mutual Fund - Large & Mid Cap | B40: 0.15 | C40: ='3. Market Utility'!F15 -> 0.10625
A41: Embassy Office Parks REIT | B41: 0.16 | C41: ='3. Market Utility'!F9 -> 0.0716
A42: Equity - Large Cap | B42: 0.17 | C42: ='3. Market Utility'!F14 -> 0.08665
A43: Equity - Mid Cap | B43: 0.22 | C43: ='3. Market Utility'!F16 -> 0.1074
A44: Equity - Small Cap | B44: 0.25 | C44: ='3. Market Utility'!F17 -> 0.10625
A45: Long-Short AIF | B45: 0.4 | C45: ='3. Market Utility'!F18 -> 0.01
A46: SHEET 4 - STRATEGIC ASSET ALLOCATION
A47: Asset Category | B47: Target Allocation
A48: Equity | B48: 35%
A49: Fixed Income | B49: 30%
A50: Commodities (Gold) | B50: 15%
A51: Multi-Asset | B51: 10%
A52: REITs | B52: 10%
A54: Rationale: Moderate A=3, Low liquidity need, 25% max loss tolerance -> balanced equity/fixed-income mix with gold as a stabilizer.
A56: SHEET 5 - PORTFOLIO OPTIMIZATION (best of 5,000 random scenarios, by utility at this client's A)
A57: Maximum Utility Achieved (across 5,000 scenarios) | B57: =B58-0.5*B14*B59^2 -> 0.12210201
A58: Winning Scenario Return | B58: ='5. Random Scenario Search'!M6 -> 0.13561
A59: Winning Scenario Risk | B59: ='5. Random Scenario Search'!N6 -> 0.094896392
A60: Winning Scenario Sharpe | B60: ='5. Random Scenario Search'!O6 -> 0.63869657
A62: Winning Portfolio Weights:
A63: Government Bonds | B63: 0.1313
A64: Corporate Bonds | B64: 0.1957
A65: Equity - Large Cap | B65: 0.0621
A66: Mutual Fund - L&M Cap | B66: 0.0143
A67: Embassy REIT | B67: 0.0095
A68: Equity - Small Cap | B68: 0.0692
A69: Equity - Mid Cap | B69: 0.1408
A70: Gold Commodity | B70: 0.2339
A71: Multi-Asset Allocation Fund | B71: 0.0406
A72: Long-Short AIF | B72: 0.1026
A74: SHEET 3 (cont'd) - INDIFFERENCE CURVE: Expected Return vs Risk/SD (guideline-required axes), all 14 market assets shown
A75: Curve equation: Return = U0 + 0.5 x A x Risk^2, where U0 = this client's own Maximum Utility Achieved (Sheet 5 above) and A=1. Points on the curve give equal utility to the client; points above/left of the curve are preferred to it, points below/right are inferior.
A76: Risk (SD) | B76: Indifference Curve Return | C76: Utility
A77: =SQRT((B77-C77)/(0.5*$B$14)) -> 0.094896392 | B77: =B58 -> 0.13561 | C77: =B57 -> 0.12210201
A78: =SQRT((B78-C78)/(0.5*$B$14)) -> 0.10167919 | B78: =B77+0.2% -> 0.13761 | C78: =C77 -> 0.12210201
A79: =SQRT((B79-C79)/(0.5*$B$14)) -> 0.10803699 | B79: =B78+0.2% -> 0.13961 | C79: =C78 -> 0.12210201
A80: =SQRT((B80-C80)/(0.5*$B$14)) -> 0.11404089 | B80: =B79+0.2% -> 0.14161 | C80: =C79 -> 0.12210201
A81: =SQRT((B81-C81)/(0.5*$B$14)) -> 0.11974414 | B81: =B80+0.2% -> 0.14361 | C81: =C80 -> 0.12210201
A82: =SQRT((B82-C82)/(0.5*$B$14)) -> 0.12518783 | B82: =B81+0.2% -> 0.14561 | C82: =C81 -> 0.12210201
A83: =SQRT((B83-C83)/(0.5*$B$14)) -> 0.1888703 | B83: =B82+3% -> 0.17561 | C83: =C82 -> 0.12210201
A84: =SQRT((B84-C84)/(0.5*$B$14)) -> 0.23594913 | B84: =B83+3% -> 0.20561 | C84: =C83 -> 0.12210201
A85: =SQRT((B85-C85)/(0.5*$B$14)) -> 0.27508543 | B85: =B84+3% -> 0.23561 | C85: =C84 -> 0.12210201
A86: =SQRT((B86-C86)/(0.5*$B$14)) -> 0.30930889 | B86: =B85+3% -> 0.26561 | C86: =C85 -> 0.12210201
A87: =SQRT((B87-C87)/(0.5*$B$14)) -> 0.34010585 | B87: =B86+3% -> 0.29561 | C87: =C86 -> 0.12210201
A88: =SQRT((B88-C88)/(0.5*$B$14)) -> 0.36833679 | B88: =B87+3% -> 0.32561 | C88: =C87 -> 0.12210201
A90: All 14 Market Assets (for chart) - the 4 marked * are excluded from portfolio optimization (no correlation data) but shown here for reference
A91: Asset | B91: Risk (SD) | C91: Expected Return
A92: Government Bonds | B92: 0.02 | C92: 0.075
A93: Hybrid Debt Fund * | B93: 0.05 | C93: 0.08
A94: Pension Plan * | B94: 0.05 | C94: 0.08
A95: Corporate Bonds | B95: 0.05 | C95: 0.09
A96: Embassy Office Parks REIT | B96: 0.16 | C96: 0.11
A97: ULIPs * | B97: 0.11 | C97: 0.11
A98: Child Education Plan * | B98: 0.11 | C98: 0.11
A99: Gold Commodity | B99: 0.12 | C99: 0.12
A100: Multi-Asset Allocation Fund | B100: 0.13 | C100: 0.1278
A101: Equity - Large Cap | B101: 0.17 | C101: 0.13
A102: Mutual Fund - Large & Mid Cap | B102: 0.15 | C102: 0.14
A103: Equity - Mid Cap | B103: 0.22 | C103: 0.18
... A105: Long-Short AIF | B105: 0.4 | C105: 0.25
A122: CLIENT THOUGHT ON WINNING PORTFOLIO
A123: Expanding my product awareness across new and non-traditional asset classes has fundamentally reshaped my investment strategy. Given my 30-year investment horizon and moderate risk profile (A=3), moving away from traditional single-asset stock picking toward an optimized, multi-asset portfolio allowed me to unlock significant diversification benefits.
A129: ADVISOR NOTE - PRODUCT AWARENESS GAPS
A130: Tarana’s current investment awareness is restricted to a subset of traditional asset classes, including Government Bonds, Corporate Bonds, Gold Commodity, Multi-Asset Allocation Funds, Large-Cap Equity, Large & Mid-Cap Mutual Funds, Mid-Cap Equity, and Small-Cap Equity. Consequently, introducing her to broader asset categories and modern portfolio diversification strategies represents a primary value-add for the advisor.
A131: Educating Tarana on objective market statistics—specifically expected returns and product utility—will align her subjective expectations with market realities, thereby narrowing the gap between her perceived client utility and actual product utility.
...

Sheet Parth
A1: CLIENT: Parth Gupta (A = 4, Moderate, self-identifies as Risk Averse)
A3: SHEET 1 - CLIENT RISK PROFILE
A4: Age | B4: 23
A5: Investment Objective | B5: Long-term Wealth Creation
A6: Primary Financial Goal | B6: Wealth Creation
A7: Goal Target Amount (Rs) | B7: 50000000
A8: Years to Goal | B8: 30
A9: Monthly SIP Capacity (Rs) | B9: 5000
A10: Required Annual Return (goal-implied) | B10: 0.1788
A11: Investment Horizon (yrs) | B11: 40
A12: Liquidity Requirement | B12: Low
A13: Max Acceptable 1-yr Loss | B13: 0.2
A14: Risk Aversion Coefficient (A) | B14: 4
A15: Risk Profile Band | B15: Moderate
A17: SHEET 3 - UTILITY & INDIFFERENCE CURVES (client's own beliefs, own aware assets only)
A18: Product | B18: Client Exp. Return | C18: Client Exp. Risk | D18: Utility of an Investor | E18: Product Risk from Market | F18: Product Return from Market | G18: Market Utility A=4 | H18: Difference
A19: Government Bonds | B19: 0.065 | C19: 0.015 | D19: =B19-0.5*4*C19^2 -> 0.06455 | E19: 0.02 | F19: 0.075 | G19: ='3. Market Utility'!G5 -> 0.0742 | H19: =D19-G19 -> -0.00965
A20: Gold Commodity | B20: 0.09 | C20: 0.09 | D20: =B20-0.5*4*C20^2 -> 0.0738 | E20: 0.12 | F20: 0.12 | G20: ='3. Market Utility'!G12 -> 0.0912 | H20: =D20-G20 -> -0.0174
A21: Equity - Large Cap | B21: 0.105 | C21: 0.07 | D21: =B21-0.5*4*C21^2 -> 0.0952 | E21: 0.17 | F21: 0.13 | G21: ='3. Market Utility'!G14 -> 0.0722 | H21: =D21-G21 -> 0.023
A22: Mutual Fund - Large & Mid Cap | B22: 0.115 | C22: 0.07 | D22: =B22-0.5*4*C22^2 -> 0.1052 | E22: 0.15 | F22: 0.14 | G22: ='3. Market Utility'!G15 -> 0.095 | H22: =D22-G22 -> 0.0102
A23: Equity - Mid Cap | B23: 0.15 | C23: 0.165 | D23: =B23-0.5*4*C23^2 -> 0.09555 | E23: 0.22 | F23: 0.18 | G23: ='3. Market Utility'!G16 -> 0.0832 | H23: =D23-G23 -> 0.01235
A24: Equity - Small Cap | B24: 0.15 | C24: 0.165 | D24: =B24-0.5*4*C24^2 -> 0.09555 | E24: 0.25 | F24: 0.2 | G24: ='3. Market Utility'!G17 -> 0.075 | H24: =D24-G24 -> 0.02055
A25: Long-Short AIF | B25: 0.09 | C25: 0.07 | D25: =B25-0.5*4*C25^2 -> 0.0802 | E25: 0.4 | F25: 0.25 | G25: ='3. Market Utility'!G18 -> -0.07 | H25: =D25-G25 -> 0.1502
A27: Positive Difference = client OVER-estimates the asset's attractiveness vs the market view (Blue above Orange). Negative = client UNDER-estimates it / is more pessimistic than the market.
A29: MARKET UTILITY CURVE (all 14 assets, at A=4) vs CLIENT'S OWN UTILITY CURVE
A30: Asset (market, sorted by SD) | B30: Market SD | C30: Market Utility | E30: Asset (client belief, sorted by SD) | F30: Client SD | G30: Client Utility | H30: Market Utility | J30: CAL Utility | K30: Risk | L30: Return | M30: Utility (A=1)
A31: Government Bonds | B31: 0.02 | C31: ='3. Market Utility'!G5 -> 0.0742 | E31: Government Bonds | F31: 0.015 | G31: =0.065-0.5*4*F31^2 -> 0.06455 | H31: =VLOOKUP(E31,A30:C44,3,FALSE) -> 0.0742 | J31: Risk-free | K31: ='4. Efficient Frontier'!B79 -> 0 | L31: ='4. Efficient Frontier'!C79 -> 0.075 | M31: ='4. Efficient Frontier'!F79 -> 0.075
A32: Hybrid Debt Fund | B32: 0.05 | C32: ='3. Market Utility'!G6 -> 0.075 | E32: Equity - Large Cap | F32: 0.07 | G32: =0.105-0.5*4*F32^2 -> 0.0952 | H32: =VLOOKUP(E32,A31:C45,3,FALSE) -> 0.0722 | J32: Tangency | K32: ='4. Efficient Frontier'!B80 -> 0.083709891 | L32: ='4. Efficient Frontier'!C80 -> 0.135908 | M32: ='4. Efficient Frontier'!F80 -> 0.13240433
A33: Pension Plan | B33: 0.05 | C33: ='3. Market Utility'!G7 -> 0.075 | E33: Mutual Fund - Large & Mid Cap | F33: 0.07 | G33: =0.115-0.5*4*F33^2 -> 0.1052 | H33: =VLOOKUP(E33,A32:C46,3,FALSE) -> 0.095 | J33: CAL extended | K33: ='4. Efficient Frontier'!B81 -> 0.14233792 | L33: ='4. Efficient Frontier'!C81 -> 0.17857871 | M33: ='4. Efficient Frontier'!F81 -> 0.16844866
A34: Corporate Bonds | B34: 0.05 | C34: ='3. Market Utility'!G8 -> 0.085 | E34: Long-Short AIF | F34: 0.07 | G34: =0.09-0.5*4*F34^2 -> 0.0802 | H34: =VLOOKUP(E34,A33:C47,3,FALSE) -> -0.07
A35: ULIPs | B35: 0.11 | C35: ='3. Market Utility'!G10 -> 0.0858 | E35: Gold Commodity | F35: 0.09 | G35: =0.09-0.5*4*F35^2 -> 0.0738 | H35: =VLOOKUP(E35,A34:C48,3,FALSE) -> 0.0912
A36: Child Education Plan | B36: 0.11 | C36: ='3. Market Utility'!G11 -> 0.0858 | E36: Equity - Mid Cap | F36: 0.165 | G36: =0.15-0.5*4*F36^2 -> 0.09555 | H36: =VLOOKUP(E36,A35:C49,3,FALSE) -> 0.0832
A37: Gold Commodity | B37: 0.12 | C37: ='3. Market Utility'!G12 -> 0.0912 | E37: Equity - Small Cap | F37: 0.165 | G37: =0.15-0.5*4*F37^2 -> 0.09555 | H37: =VLOOKUP(E37,A36:C50,3,FALSE) -> 0.075
A38: Multi-Asset Allocation Fund | B38: 0.13 | C38: ='3. Market Utility'!G13 -> 0.094
A39: Mutual Fund - Large & Mid Cap | B39: 0.15 | C39: ='3. Market Utility'!G15 -> 0.095
A40: Embassy Office Parks REIT | B40: 0.16 | C40: ='3. Market Utility'!G9 -> 0.0588
A41: Equity - Large Cap | B41: 0.17 | C41: ='3. Market Utility'!G14 -> 0.0722
A42: Equity - Mid Cap | B42: 0.22 | C42: ='3. Market Utility'!G16 -> 0.0832
A43: Equity - Small Cap | B43: 0.25 | C43: ='3. Market Utility'!G17 -> 0.075
A44: Long-Short AIF | B44: 0.4 | C44: ='3. Market Utility'!G18 -> -0.07
A45: SHEET 4 - STRATEGIC ASSET ALLOCATION
A46: Asset Category | B46: Target Allocation
A47: Equity | B47: 35%
A48: Fixed Income | B48: 30%
A49: Commodities (Gold) | B49: 15%
A50: Multi-Asset | B50: 10%
A51: REITs | B51: 10%
A53: Rationale: Moderate A=4, Low liquidity need, 20% max loss tolerance -> balanced equity/fixed-income mix with gold as a stabilizer.
A55: SHEET 5 - PORTFOLIO OPTIMIZATION (best of 5,000 random scenarios, by utility at this client's A)
A56: Maximum Utility Achieved (across 5,000 scenarios) | B56: =B57-0.5*B14*B58^2 -> 0.11813762
A57: Winning Scenario Return | B57: ='5. Random Scenario Search'!M5 -> 0.13668
A58: Winning Scenario Risk | B58: ='5. Random Scenario Search'!N5 -> 0.096287017
A59: Winning Scenario Sharpe | B59: ='5. Random Scenario Search'!O5 -> 0.6405848
A61: Winning Portfolio Weights:
A62: Government Bonds | B62: 0.1313
A63: Corporate Bonds | B63: 0.1957
A64: Equity - Large Cap | B64: 0.0621
A65: Mutual Fund - L&M Cap | B65: 0.0143
A66: Embassy REIT | B66: 0.0095
A67: Equity - Small Cap | B67: 0.0692
A68: Equity - Mid Cap | B68: 0.1408
A69: Gold Commodity | B69: 0.2339
A70: Multi-Asset Allocation Fund | B70: 0.0406
A71: Long-Short AIF | B71: 0.1026
A73: SHEET 3 (cont'd) - INDIFFERENCE CURVE: Expected Return vs Risk/SD (guideline-required axes), all 14 market assets shown
A74: Curve equation: Return = U0 + 0.5 x A x Risk^2, where U0 = this client's own Maximum Utility Achieved (Sheet 5 above) and A=1. Points on the curve give equal utility to the client; points above/left of the curve are preferred to it, points below/right are inferior.
A75: Risk (SD) | B75: Indifference Curve Return | C75: Utility
A76: =SQRT((B76-C76)/(0.5*$B$14)) -> 0.096287017 | B76: =B57 -> 0.13668 | C76: =B56 -> 0.11813762
A77: =SQRT((B77-C77)/(0.5*$B$14)) -> 0.10134688 | B77: =B76+0.2% -> 0.13868 | C77: =C76 -> 0.11813762
A78: =SQRT((B78-C78)/(0.5*$B$14)) -> 0.10616586 | B78: =B77+0.2% -> 0.14068 | C78: =C77 -> 0.11813762
A79: =SQRT((B79-C79)/(0.5*$B$14)) -> 0.1107754 | B79: =B78+0.2% -> 0.14268 | C79: =C78 -> 0.11813762
A80: =SQRT((B80-C80)/(0.5*$B$14)) -> 0.11520065 | B80: =B79+0.2% -> 0.14468 | C80: =C79 -> 0.11813762
A81: =SQRT((B81-C81)/(0.5*$B$14)) -> 0.11946208 | B81: =B80+0.2% -> 0.14668 | C81: =C80 -> 0.11813762
A82: =SQRT((B82-C82)/(0.5*$B$14)) -> 0.17108825 | B82: =B81+3% -> 0.17668 | C82: =C81 -> 0.11813762
A83: =SQRT((B83-C83)/(0.5*$B$14)) -> 0.2104072 | B83: =B82+3% -> 0.20668 | C83: =C82 -> 0.11813762
A84: =SQRT((B84-C84)/(0.5*$B$14)) -> 0.24345675 | B84: =B83+3% -> 0.23668 | C84: =C83 -> 0.11813762
A85: =SQRT((B85-C85)/(0.5*$B$14)) -> 0.27252741 | B85: =B84+3% -> 0.26668 | C85: =C84 -> 0.11813762
A86: =SQRT((B86-C86)/(0.5*$B$14)) -> 0.29878285 | B86: =B85+3% -> 0.29668 | C86: =C85 -> 0.11813762
A87: =SQRT((B87-C87)/(0.5*$B$14)) -> 0.3229105 | B87: =B86+3% -> 0.32668 | C87: =C86 -> 0.11813762
A89: All 14 Market Assets (for chart) - the 4 marked * are excluded from portfolio optimization (no correlation data) but shown here for reference
A90: Asset | B90: Risk (SD) | C90: Expected Return
A91: Government Bonds | B91: 0.02 | C91: 0.075
A92: Hybrid Debt Fund * | B92: 0.05 | C92: 0.08
A93: Pension Plan * | B93: 0.05 | C93: 0.08
A94: Corporate Bonds | B94: 0.05 | C94: 0.09
A95: Embassy Office Parks REIT | B95: 0.16 | C95: 0.11
A96: ULIPs * | B96: 0.11 | C96: 0.11
A97: Child Education Plan * | B97: 0.11 | C97: 0.11
A98: Gold Commodity | B98: 0.12 | C98: 0.12
A99: Multi-Asset Allocation Fund | B99: 0.13 | C99: 0.1278
A100: Equity - Large Cap | B100: 0.17 | C100: 0.13
A101: Mutual Fund - Large & Mid Cap | B101: 0.15 | C101: 0.14
A102: Equity - Mid Cap | B102: 0.22 | C102: 0.18
... A104: Long-Short AIF | B104: 0.4 | C104: 0.25
A121: CLIENT THOUGHT ON WINNING PORTFOLIO
A122: Expanding my product awareness across new and non-traditional asset classes has fundamentally reshaped my investment strategy. Given my 40-year investment horizon and moderate risk profile (A=4), moving away from traditional single-asset stock picking toward an optimized, multi-asset portfolio allowed me to unlock significant diversification benefits.
A128: ADVISOR NOTE - PRODUCT AWARENESS GAPS
A129: Parth’s current investment awareness is restricted to a subset of traditional asset classes, including Government Bonds, Gold Commodity, Large-Cap Equity, Large & Mid-Cap Mutual Funds, Mid-Cap Equity, Small-Cap Equity, and Long-Short AIF. Consequently, introducing him to broader asset categories and modern portfolio diversification strategies represents a primary value-add for the advisor.
A130: ducating Parth on objective market statistics—specifically expected returns and product utility—will align his subjective expectations with market realities, thereby narrowing the gap between his perceived client utility and actual product utility.
A132: SHEET 6 - FINAL RECOMMENDATION & MONITORING
...
