Workbook

Sheet Inputs
A1: Project Finance Model: 100 MW Solar Plant
A2: Illustrative assumptions for learning; ₹ crore unless stated. Blue cells are inputs.
A4: Capacity (MW) | B4: 100
A5: Capacity utilisation factor | B5: 0.24 | C5: Share of the year the plant produces at full output
A6: Annual degradation | B6: 0.005 | C6: Panel output decline per year
A7: Tariff (₹ per kWh, fixed for 25 years) | B7: 2.6 | C7: Long-term power purchase agreement
A8: Capex (₹ crore per MW) | B8: 4
A9: O&M year 1 (₹ crore per MW) | B9: 0.06
A10: O&M escalation | B10: 0.035
A11: Debt share of capex | B11: 0.75 | C11: Gearing
A12: Interest rate | B12: 0.09
A13: Loan tenor (years) | B13: 18 | C13: Annuity repayment
A14: Target minimum DSCR | B14: 1.25 | C14: Lenders' covenant
A15: Tax rate | B15: 0.2517
A16: Tax depreciation life (years) | B16: 25 | C16: Straight line
A17: Project life (years) | B17: 25
A18: Derived
A19: Total capex | B19: =B4*B8 -> 400
A20: Debt | B20: =B19*B11 -> 300
A21: Equity | B21: =B19-B20 -> 100
A22: Annual debt service (annuity) | B22: =PMT(B12,B13,-B20) -> 34.263687
A23: Annual tax depreciation | B23: =B19/B16 -> 16

Sheet Returns
A1: Returns and lender metrics
A3: Minimum DSCR (loan life) | B3: =MIN('Cash flows'!C17:T17) -> 0.99943284
A4: Average DSCR (loan life) | B4: =AVERAGE('Cash flows'!C17:T17) -> 1.2128377
A5: Meets target DSCR? | B5: =IF(B3>=Inputs!B14,"Yes","No: resize debt") -> No: resize debt
A6: Loan life coverage ratio (LLCR) | B6: =NPV(Inputs!B12,'Cash flows'!C15:T15)/Inputs!B20 -> 1.2608529
A7: Debt capacity at target DSCR (₹ crore) | B7: =NPV(Inputs!B12,'Cash flows'!C15:T15)/Inputs!B14 -> 302.6047
A8: Implied maximum gearing | B8: =B7/Inputs!B19 -> 0.75651174
A9: Equity IRR | B9: =IRR('Cash flows'!B18:AA18) -> 0.10272215
A10: Project IRR (unlevered, post-tax) | B10: =IRR('Cash flows'!B19:AA19) -> 0.079033025
A11: Year-1 revenue (₹ crore) | B11: ='Cash flows'!C5 -> 54.6624
A12: Year-1 EBITDA margin | B12: ='Cash flows'!C7/'Cash flows'!C5 -> 0.89023534
A14: Debt capacity sizes the loan so that CFADS covers debt service at the target DSCR over the loan life (sculpted-repayment logic).
A15: Simplifications: no construction period, no reserve accounts, tax losses not carried forward. For learning, not investment advice.

Sheet Cash flows
A1: Annual cash flows and debt service (₹ crore)
A3: Year | B3: 0 | C3: 1 | D3: 2 | E3: 3 | F3: 4 | G3: 5 | H3: 6 | I3: 7 | J3: 8 | K3: 9 | L3: 10 | M3: 11 | N3: 12 | O3: 13 | P3: 14 | Q3: 15 | R3: 16 | S3: 17 | T3: 18 | U3: 19 | V3: 20 | W3: 21 | X3: 22 | Y3: 23 | Z3: 24 | AA3: 25
A4: Generation (million kWh) | B4: 0 | C4: =Inputs!$B$4*8760*Inputs!$B$5*(1-Inputs!$B$6)^(C$3-1)/1000 -> 210.24 | D4: =Inputs!$B$4*8760*Inputs!$B$5*(1-Inputs!$B$6)^(D$3-1)/1000 -> 209.1888 | E4: =Inputs!$B$4*8760*Inputs!$B$5*(1-Inputs!$B$6)^(E$3-1)/1000 -> 208.14286 | F4: =Inputs!$B$4*8760*Inputs!$B$5*(1-Inputs!$B$6)^(F$3-1)/1000 -> 207.10214 | G4: =Inputs!$B$4*8760*Inputs!$B$5*(1-Inputs!$B$6)^(G$3-1)/1000 -> 206.06663 | H4: =Inputs!$B$4*8760*Inputs!$B$5*(1-Inputs!$B$6)^(H$3-1)/1000 -> 205.0363 | I4: =Inputs!$B$4*8760*Inputs!$B$5*(1-Inputs!$B$6)^(I$3-1)/1000 -> 204.01112 | J4: =Inputs!$B$4*8760*Inputs!$B$5*(1-Inputs!$B$6)^(J$3-1)/1000 -> 202.99106 | ... AA4: =Inputs!$B$4*8760*Inputs!$B$5*(1-Inputs!$B$6)^(AA$3-1)/1000 -> 186.41003
A5: Revenue | B5: 0 | C5: =C4*Inputs!$B$7/10 -> 54.6624 | D5: =D4*Inputs!$B$7/10 -> 54.389088 | E5: =E4*Inputs!$B$7/10 -> 54.117143 | F5: =F4*Inputs!$B$7/10 -> 53.846557 | G5: =G4*Inputs!$B$7/10 -> 53.577324 | H5: =H4*Inputs!$B$7/10 -> 53.309437 | I5: =I4*Inputs!$B$7/10 -> 53.04289 | J5: =J4*Inputs!$B$7/10 -> 52.777676 | ... AA5: =AA4*Inputs!$B$7/10 -> 48.466609
A6: O&M cost | B6: 0 | C6: =Inputs!$B$4*Inputs!$B$9*(1+Inputs!$B$10)^(C$3-1) -> 6 | D6: =Inputs!$B$4*Inputs!$B$9*(1+Inputs!$B$10)^(D$3-1) -> 6.21 | E6: =Inputs!$B$4*Inputs!$B$9*(1+Inputs!$B$10)^(E$3-1) -> 6.42735 | F6: =Inputs!$B$4*Inputs!$B$9*(1+Inputs!$B$10)^(F$3-1) -> 6.6523072 | G6: =Inputs!$B$4*Inputs!$B$9*(1+Inputs!$B$10)^(G$3-1) -> 6.885138 | H6: =Inputs!$B$4*Inputs!$B$9*(1+Inputs!$B$10)^(H$3-1) -> 7.1261178 | I6: =Inputs!$B$4*Inputs!$B$9*(1+Inputs!$B$10)^(I$3-1) -> 7.375532 | J6: =Inputs!$B$4*Inputs!$B$9*(1+Inputs!$B$10)^(J$3-1) -> 7.6336756 | ... AA6: =Inputs!$B$4*Inputs!$B$9*(1+Inputs!$B$10)^(AA$3-1) -> 13.699971
A7: EBITDA | B7: 0 | C7: =C5-C6 -> 48.6624 | D7: =D5-D6 -> 48.179088 | E7: =E5-E6 -> 47.689793 | F7: =F5-F6 -> 47.19425 | G7: =G5-G6 -> 46.692186 | H7: =H5-H6 -> 46.18332 | I7: =I5-I6 -> 45.667358 | J7: =J5-J6 -> 45.144 | ... AA7: =AA5-AA6 -> 34.766638
A8: Tax depreciation | B8: 0 | C8: =IF(C$3<=Inputs!$B$16,Inputs!$B$23,0) -> 16 | D8: =IF(D$3<=Inputs!$B$16,Inputs!$B$23,0) -> 16 | E8: =IF(E$3<=Inputs!$B$16,Inputs!$B$23,0) -> 16 | F8: =IF(F$3<=Inputs!$B$16,Inputs!$B$23,0) -> 16 | G8: =IF(G$3<=Inputs!$B$16,Inputs!$B$23,0) -> 16 | H8: =IF(H$3<=Inputs!$B$16,Inputs!$B$23,0) -> 16 | I8: =IF(I$3<=Inputs!$B$16,Inputs!$B$23,0) -> 16 | J8: =IF(J$3<=Inputs!$B$16,Inputs!$B$23,0) -> 16 | ... AA8: =IF(AA$3<=Inputs!$B$16,Inputs!$B$23,0) -> 16
A9: Opening debt | B9: 0 | C9: =B12 -> 300 | D9: =C12 -> 292.73631 | E9: =D12 -> 284.81889 | F9: =E12 -> 276.18891 | G9: =F12 -> 266.78222 | H9: =G12 -> 256.52893 | I9: =H12 -> 245.35285 | J9: =I12 -> 233.17092 | ... AA9: =Z12 -> -1.2434498e-13
A10: Interest | B10: 0 | C10: =C9*Inputs!$B$12 -> 27 | D10: =D9*Inputs!$B$12 -> 26.346268 | E10: =E9*Inputs!$B$12 -> 25.6337 | F10: =F9*Inputs!$B$12 -> 24.857002 | G10: =G9*Inputs!$B$12 -> 24.0104 | H10: =H9*Inputs!$B$12 -> 23.087604 | I10: =I9*Inputs!$B$12 -> 22.081757 | J10: =J9*Inputs!$B$12 -> 20.985383 | ... AA10: =AA9*Inputs!$B$12 -> -1.1191048e-14
A11: Principal repayment | B11: 0 | C11: =IF(C$3<=Inputs!$B$13,Inputs!$B$22-C10,0) -> 7.2636872 | D11: =IF(D$3<=Inputs!$B$13,Inputs!$B$22-D10,0) -> 7.917419 | E11: =IF(E$3<=Inputs!$B$13,Inputs!$B$22-E10,0) -> 8.6299868 | F11: =IF(F$3<=Inputs!$B$13,Inputs!$B$22-F10,0) -> 9.4066856 | G11: =IF(G$3<=Inputs!$B$13,Inputs!$B$22-G10,0) -> 10.253287 | H11: =IF(H$3<=Inputs!$B$13,Inputs!$B$22-H10,0) -> 11.176083 | I11: =IF(I$3<=Inputs!$B$13,Inputs!$B$22-I10,0) -> 12.181931 | J11: =IF(J$3<=Inputs!$B$13,Inputs!$B$22-J10,0) -> 13.278304 | ... AA11: =IF(AA$3<=Inputs!$B$13,Inputs!$B$22-AA10,0) -> 0
A12: Closing debt | B12: =Inputs!$B$20 -> 300 | C12: =C9-C11 -> 292.73631 | D12: =D9-D11 -> 284.81889 | E12: =E9-E11 -> 276.18891 | F12: =F9-F11 -> 266.78222 | G12: =G9-G11 -> 256.52893 | H12: =H9-H11 -> 245.35285 | I12: =I9-I11 -> 233.17092 | J12: =J9-J11 -> 219.89262 | ... AA12: =AA9-AA11 -> -1.2434498e-13
A13: Taxable income | B13: 0 | C13: =C7-C8-C10 -> 5.6624 | D13: =D7-D8-D10 -> 5.8328198 | E13: =E7-E8-E10 -> 6.0560921 | F13: =F7-F8-F10 -> 6.337248 | G13: =G7-G8-G10 -> 6.6817861 | H13: =H7-H8-H10 -> 7.0957155 | I13: =I7-I8-I10 -> 7.5856017 | J13: =J7-J8-J10 -> 8.1586174 | ... AA13: =AA7-AA8-AA10 -> 18.766638
A14: Tax | B14: 0 | C14: =MAX(0,C13)*Inputs!$B$15 -> 1.4252261 | D14: =MAX(0,D13)*Inputs!$B$15 -> 1.4681208 | E14: =MAX(0,E13)*Inputs!$B$15 -> 1.5243184 | F14: =MAX(0,F13)*Inputs!$B$15 -> 1.5950853 | G14: =MAX(0,G13)*Inputs!$B$15 -> 1.6818056 | H14: =MAX(0,H13)*Inputs!$B$15 -> 1.7859916 | I14: =MAX(0,I13)*Inputs!$B$15 -> 1.9092959 | J14: =MAX(0,J13)*Inputs!$B$15 -> 2.053524 | ... AA14: =MAX(0,AA13)*Inputs!$B$15 -> 4.7235628
A15: CFADS (cash available for debt service) | B15: 0 | C15: =C7-C14 -> 47.237174 | D15: =D7-D14 -> 46.710967 | E15: =E7-E14 -> 46.165474 | F15: =F7-F14 -> 45.599164 | G15: =G7-G14 -> 45.01038 | H15: =H7-H14 -> 44.397328 | I15: =I7-I14 -> 43.758062 | J15: =J7-J14 -> 43.090476 | ... AA15: =AA7-AA14 -> 30.043075
A16: Debt service | B16: 0 | C16: =C10+C11 -> 34.263687 | D16: =D10+D11 -> 34.263687 | E16: =E10+E11 -> 34.263687 | F16: =F10+F11 -> 34.263687 | G16: =G10+G11 -> 34.263687 | H16: =H10+H11 -> 34.263687 | I16: =I10+I11 -> 34.263687 | J16: =J10+J11 -> 34.263687 | ... AA16: =AA10+AA11 -> -1.1191048e-14
A17: DSCR | C17: =IF(C16>0,C15/C16,"") -> 1.3786366 | D17: =IF(D16>0,D15/D16,"") -> 1.3632791 | E17: =IF(E16>0,E15/E16,"") -> 1.3473586 | F17: =IF(F16>0,F15/F16,"") -> 1.3308306 | G17: =IF(G16>0,G15/G16,"") -> 1.3136467 | H17: =IF(H16>0,H15/H16,"") -> 1.2957545 | I17: =IF(I16>0,I15/I16,"") -> 1.2770973 | J17: =IF(J16>0,J15/J16,"") -> 1.2576135 | ... AA17: =IF(AA16>0,AA15/AA16,"")
A18: Equity cash flow | B18: =-Inputs!$B$21 -> -100 | C18: =C15-C16 -> 12.973487 | D18: =D15-D16 -> 12.44728 | E18: =E15-E16 -> 11.901787 | F18: =F15-F16 -> 11.335477 | G18: =G15-G16 -> 10.746693 | H18: =H15-H16 -> 10.133641 | I18: =I15-I16 -> 9.4943751 | J18: =J15-J16 -> 8.826789 | ... AA18: =AA15-AA16 -> 30.043075
A19: Project cash flow (unlevered, post-tax) | B19: =-Inputs!$B$19 -> -400 | C19: =C7-MAX(0,C7-C8)*Inputs!$B$15 -> 40.441274 | D19: =D7-MAX(0,D7-D8)*Inputs!$B$15 -> 40.079612 | E19: =E7-MAX(0,E7-E8)*Inputs!$B$15 -> 39.713472 | F19: =F7-MAX(0,F7-F8)*Inputs!$B$15 -> 39.342657 | G19: =G7-MAX(0,G7-G8)*Inputs!$B$15 -> 38.966963 | H19: =H7-MAX(0,H7-H8)*Inputs!$B$15 -> 38.586178 | I19: =I7-MAX(0,I7-I8)*Inputs!$B$15 -> 38.200084 | J19: =J7-MAX(0,J7-J8)*Inputs!$B$15 -> 37.808455 | ... AA19: =AA7-MAX(0,AA7-AA8)*Inputs!$B$15 -> 30.043075
