Workbook

Sheet Rules
A1: Trade Break Reconciliation
A2: Booking system against counterparty confirmations. Synthetic trades.
A4: Notional tolerance (bp of notional) | B4: 1
A5: Aged threshold (days) | B5: 3
A7: Break type | B7: Owner and action
A8: Unconfirmed | B8: Confirmations team: chase counterparty
A9: Unbooked | B9: Front office: book or reject
A10: Counterparty | B10: Static data: correct legal entity
A11: Notional | B11: Middle office: amend booking
A12: Rate or price | B12: Middle office: amend booking
A13: Value date | B13: Middle office: amend booking
A14: Matched | B14: None

Sheet Summary
A1: Reconciliation summary
A2: All figures are formulas over the Reconciliation sheet.
A4: Trades compared | B4: =COUNTA(Reconciliation!A2:A241) -> 240
A5: Matched | B5: =COUNTIF(Reconciliation!L2:L241,"Matched") -> 223
A6: Match rate | B6: =IF(B4=0,0,B5/B4) -> 0.92916667
A7: Open breaks | B7: =B4-B5 -> 17
A8: Aged breaks | B8: =COUNTIF(Reconciliation!N2:N241,TRUE()) -> 5
A9: Notional affected ($) | B9: =SUMIFS(Reconciliation!F2:F241,Reconciliation!L2:L241,"<>Matched")+SUMIFS(Reconciliation!G2:G241,Reconciliation!L2:L241,"Unbooked") -> 499000000
A11: Breaks by type
A12: Unconfirmed | B12: =COUNTIF(Reconciliation!L2:L241,A12) -> 5
A13: Unbooked | B13: =COUNTIF(Reconciliation!L2:L241,A13) -> 3
A14: Counterparty | B14: =COUNTIF(Reconciliation!L2:L241,A14) -> 2
A15: Notional | B15: =COUNTIF(Reconciliation!L2:L241,A15) -> 3
A16: Rate or price | B16: =COUNTIF(Reconciliation!L2:L241,A16) -> 3
A17: Value date | B17: =COUNTIF(Reconciliation!L2:L241,A17) -> 1

Sheet Booking
A1: Trade ID | B1: Product | C1: Counterparty | D1: Notional ($) | E1: Rate or price | F1: Value date (T+n) | G1: Age (days)
A2: TR-50100 | B2: FX forward | C2: Tarn Energy Trading | D2: 28000000 | E2: 5.1415 | F2: 1 | G2: 0
A3: TR-50101 | B3: FX swap | C3: Meridian Bank | D3: 19000000 | E3: 1.3863 | F3: 2 | G3: 1
A4: TR-50102 | B4: Equity option | C4: Tarn Energy Trading | D4: 25000000 | E4: 2.638 | F4: 2 | G4: 2
A5: TR-50103 | B5: CDS | C5: Solent Asset Management | D5: 14000000 | E5: 6.7727 | F5: 1 | G5: 3
A6: TR-50104 | B6: FX swap | C6: Northbay Pension Fund | D6: 35000000 | E6: 3.365 | F6: 3 | G6: 1
A7: TR-50105 | B7: Commodity swap | C7: Meridian Bank | D7: 38000000 | E7: 2.6629 | F7: 2 | G7: 3
A8: TR-50106 | B8: IRS | C8: Meridian Bank | D8: 50000000 | E8: 4.2661 | F8: 1 | G8: 5
A9: TR-50107 | B9: Commodity swap | C9: Kestrel Macro Fund | D9: 37000000 | E9: 4.6811 | F9: 3 | G9: 1
A10: TR-50108 | B10: FX forward | C10: Meridian Bank | D10: 19000000 | E10: 3.0089 | F10: 3 | G10: 0
A11: TR-50109 | B11: Repo | C11: Aldridge Capital | D11: 50000000 | E11: 5.9933 | F11: 1 | G11: 4
A12: TR-50110 | B12: IRS | C12: Aldridge Capital | D12: 21000000 | E12: 5.1547 | F12: 2 | G12: 3
A13: TR-50111 | B13: IRS | C13: Aldridge Capital | D13: 43000000 | E13: 3.1705 | F13: 3 | G13: 6
... A238: TR-50339 | B238: Equity option | C238: Tarn Energy Trading | D238: 34000000 | E238: 3.683 | F238: 3 | G238: 1

Sheet Confirmations
A1: Trade ID | B1: Product | C1: Counterparty | D1: Notional ($) | E1: Rate or price | F1: Value date (T+n) | G1: Age (days)
A2: TR-50100 | B2: FX forward | C2: Tarn Energy Trading | D2: 28000000 | E2: 5.1415 | F2: 1 | G2: 0
A3: TR-50101 | B3: FX swap | C3: Meridian Bank | D3: 19000000 | E3: 1.3863 | F3: 2 | G3: 1
A4: TR-50102 | B4: Equity option | C4: Tarn Energy Trading | D4: 25000000 | E4: 2.638 | F4: 2 | G4: 2
A5: TR-50103 | B5: CDS | C5: Solent Asset Management | D5: 14000000 | E5: 6.7727 | F5: 1 | G5: 3
A6: TR-50104 | B6: FX swap | C6: Northbay Pension Fund | D6: 35000000 | E6: 3.365 | F6: 3 | G6: 1
A7: TR-50105 | B7: Commodity swap | C7: Meridian Bank | D7: 38000000 | E7: 2.6629 | F7: 2 | G7: 3
A8: TR-50106 | B8: IRS | C8: Meridian Bank | D8: 50000000 | E8: 4.2661 | F8: 1 | G8: 5
A9: TR-50107 | B9: Commodity swap | C9: Kestrel Macro Fund | D9: 37000000 | E9: 4.6811 | F9: 3 | G9: 1
A10: TR-50108 | B10: FX forward | C10: Meridian Bank | D10: 18769137 | E10: 3.0089 | F10: 3 | G10: 0
A11: TR-50109 | B11: Repo | C11: Aldridge Capital | D11: 50000000 | E11: 5.9933 | F11: 1 | G11: 4
A12: TR-50110 | B12: IRS | C12: Aldridge Capital | D12: 21000000 | E12: 5.1547 | F12: 2 | G12: 3
A13: TR-50111 | B13: IRS | C13: Aldridge Capital | D13: 43000000 | E13: 3.1705 | F13: 3 | G13: 6
... A236: TR-50339 | B236: Equity option | C236: Tarn Energy Trading | D236: 34000000 | E236: 3.683 | F236: 3 | G236: 1

Sheet Reconciliation
A1: Trade ID | B1: In booking | C1: In confirmations | D1: Booked counterparty | E1: Confirmed counterparty | F1: Booked notional ($) | G1: Confirmed notional ($) | H1: Booked rate | I1: Confirmed rate | J1: Booked value date | K1: Confirmed value date | L1: Status | M1: Age (days) | N1: Aged | O1: Owner and action
A2: TR-50100 | B2: =ISNUMBER(MATCH(A2,Booking!$A:$A,0)) -> TRUE | C2: =ISNUMBER(MATCH(A2,Confirmations!$A:$A,0)) -> TRUE | D2: =IFERROR(INDEX(Booking!$C:$C,MATCH($A2,Booking!$A:$A,0)),"") -> Tarn Energy Trading | E2: =IFERROR(INDEX(Confirmations!$C:$C,MATCH($A2,Confirmations!$A:$A,0)),"") -> Tarn Energy Trading | F2: =IFERROR(INDEX(Booking!$D:$D,MATCH($A2,Booking!$A:$A,0)),"") -> 28000000 | G2: =IFERROR(INDEX(Confirmations!$D:$D,MATCH($A2,Confirmations!$A:$A,0)),"") -> 28000000 | H2: =IFERROR(INDEX(Booking!$E:$E,MATCH($A2,Booking!$A:$A,0)),"") -> 5.1415 | I2: =IFERROR(INDEX(Confirmations!$E:$E,MATCH($A2,Confirmations!$A:$A,0)),"") -> 5.1415 | J2: =IFERROR(INDEX(Booking!$F:$F,MATCH($A2,Booking!$A:$A,0)),"") -> 1 | K2: =IFERROR(INDEX(Confirmations!$F:$F,MATCH($A2,Confirmations!$A:$A,0)),"") -> 1 | L2: =IF(NOT(C2),"Unconfirmed",IF(NOT(B2),"Unbooked",IF(D2<>E2,"Counterparty",IF(ABS(F2-G2)>F2*Rules!$B$4/10000,"Notional",IF(H2<>I2,"Rate or price",IF(J2<>K2,"Value date","Matched")))))) -> Matched | M2: =IF(B2,INDEX(Booking!$G:$G,MATCH(A2,Booking!$A:$A,0)),INDEX(Confirmations!$G:$G,MATCH(A2,Confirmations!$A:$A,0))) -> 0 | N2: =AND(L2<>"Matched",M2>Rules!$B$5) -> FALSE | O2: =INDEX(Rules!$B$8:$B$14,MATCH(L2,Rules!$A$8:$A$14,0)) -> None
A3: TR-50101 | B3: =ISNUMBER(MATCH(A3,Booking!$A:$A,0)) -> TRUE | C3: =ISNUMBER(MATCH(A3,Confirmations!$A:$A,0)) -> TRUE | D3: =IFERROR(INDEX(Booking!$C:$C,MATCH($A3,Booking!$A:$A,0)),"") -> Meridian Bank | E3: =IFERROR(INDEX(Confirmations!$C:$C,MATCH($A3,Confirmations!$A:$A,0)),"") -> Meridian Bank | F3: =IFERROR(INDEX(Booking!$D:$D,MATCH($A3,Booking!$A:$A,0)),"") -> 19000000 | G3: =IFERROR(INDEX(Confirmations!$D:$D,MATCH($A3,Confirmations!$A:$A,0)),"") -> 19000000 | H3: =IFERROR(INDEX(Booking!$E:$E,MATCH($A3,Booking!$A:$A,0)),"") -> 1.3863 | I3: =IFERROR(INDEX(Confirmations!$E:$E,MATCH($A3,Confirmations!$A:$A,0)),"") -> 1.3863 | J3: =IFERROR(INDEX(Booking!$F:$F,MATCH($A3,Booking!$A:$A,0)),"") -> 2 | K3: =IFERROR(INDEX(Confirmations!$F:$F,MATCH($A3,Confirmations!$A:$A,0)),"") -> 2 | L3: =IF(NOT(C3),"Unconfirmed",IF(NOT(B3),"Unbooked",IF(D3<>E3,"Counterparty",IF(ABS(F3-G3)>F3*Rules!$B$4/10000,"Notional",IF(H3<>I3,"Rate or price",IF(J3<>K3,"Value date","Matched")))))) -> Matched | M3: =IF(B3,INDEX(Booking!$G:$G,MATCH(A3,Booking!$A:$A,0)),INDEX(Confirmations!$G:$G,MATCH(A3,Confirmations!$A:$A,0))) -> 1 | N3: =AND(L3<>"Matched",M3>Rules!$B$5) -> FALSE | O3: =INDEX(Rules!$B$8:$B$14,MATCH(L3,Rules!$A$8:$A$14,0)) -> None
A4: TR-50102 | B4: =ISNUMBER(MATCH(A4,Booking!$A:$A,0)) -> TRUE | C4: =ISNUMBER(MATCH(A4,Confirmations!$A:$A,0)) -> TRUE | D4: =IFERROR(INDEX(Booking!$C:$C,MATCH($A4,Booking!$A:$A,0)),"") -> Tarn Energy Trading | E4: =IFERROR(INDEX(Confirmations!$C:$C,MATCH($A4,Confirmations!$A:$A,0)),"") -> Tarn Energy Trading | F4: =IFERROR(INDEX(Booking!$D:$D,MATCH($A4,Booking!$A:$A,0)),"") -> 25000000 | G4: =IFERROR(INDEX(Confirmations!$D:$D,MATCH($A4,Confirmations!$A:$A,0)),"") -> 25000000 | H4: =IFERROR(INDEX(Booking!$E:$E,MATCH($A4,Booking!$A:$A,0)),"") -> 2.638 | I4: =IFERROR(INDEX(Confirmations!$E:$E,MATCH($A4,Confirmations!$A:$A,0)),"") -> 2.638 | J4: =IFERROR(INDEX(Booking!$F:$F,MATCH($A4,Booking!$A:$A,0)),"") -> 2 | K4: =IFERROR(INDEX(Confirmations!$F:$F,MATCH($A4,Confirmations!$A:$A,0)),"") -> 2 | L4: =IF(NOT(C4),"Unconfirmed",IF(NOT(B4),"Unbooked",IF(D4<>E4,"Counterparty",IF(ABS(F4-G4)>F4*Rules!$B$4/10000,"Notional",IF(H4<>I4,"Rate or price",IF(J4<>K4,"Value date","Matched")))))) -> Matched | M4: =IF(B4,INDEX(Booking!$G:$G,MATCH(A4,Booking!$A:$A,0)),INDEX(Confirmations!$G:$G,MATCH(A4,Confirmations!$A:$A,0))) -> 2 | N4: =AND(L4<>"Matched",M4>Rules!$B$5) -> FALSE | O4: =INDEX(Rules!$B$8:$B$14,MATCH(L4,Rules!$A$8:$A$14,0)) -> None
A5: TR-50103 | B5: =ISNUMBER(MATCH(A5,Booking!$A:$A,0)) -> TRUE | C5: =ISNUMBER(MATCH(A5,Confirmations!$A:$A,0)) -> TRUE | D5: =IFERROR(INDEX(Booking!$C:$C,MATCH($A5,Booking!$A:$A,0)),"") -> Solent Asset Management | E5: =IFERROR(INDEX(Confirmations!$C:$C,MATCH($A5,Confirmations!$A:$A,0)),"") -> Solent Asset Management | F5: =IFERROR(INDEX(Booking!$D:$D,MATCH($A5,Booking!$A:$A,0)),"") -> 14000000 | G5: =IFERROR(INDEX(Confirmations!$D:$D,MATCH($A5,Confirmations!$A:$A,0)),"") -> 14000000 | H5: =IFERROR(INDEX(Booking!$E:$E,MATCH($A5,Booking!$A:$A,0)),"") -> 6.7727 | I5: =IFERROR(INDEX(Confirmations!$E:$E,MATCH($A5,Confirmations!$A:$A,0)),"") -> 6.7727 | J5: =IFERROR(INDEX(Booking!$F:$F,MATCH($A5,Booking!$A:$A,0)),"") -> 1 | K5: =IFERROR(INDEX(Confirmations!$F:$F,MATCH($A5,Confirmations!$A:$A,0)),"") -> 1 | L5: =IF(NOT(C5),"Unconfirmed",IF(NOT(B5),"Unbooked",IF(D5<>E5,"Counterparty",IF(ABS(F5-G5)>F5*Rules!$B$4/10000,"Notional",IF(H5<>I5,"Rate or price",IF(J5<>K5,"Value date","Matched")))))) -> Matched | M5: =IF(B5,INDEX(Booking!$G:$G,MATCH(A5,Booking!$A:$A,0)),INDEX(Confirmations!$G:$G,MATCH(A5,Confirmations!$A:$A,0))) -> 3 | N5: =AND(L5<>"Matched",M5>Rules!$B$5) -> FALSE | O5: =INDEX(Rules!$B$8:$B$14,MATCH(L5,Rules!$A$8:$A$14,0)) -> None
A6: TR-50104 | B6: =ISNUMBER(MATCH(A6,Booking!$A:$A,0)) -> TRUE | C6: =ISNUMBER(MATCH(A6,Confirmations!$A:$A,0)) -> TRUE | D6: =IFERROR(INDEX(Booking!$C:$C,MATCH($A6,Booking!$A:$A,0)),"") -> Northbay Pension Fund | E6: =IFERROR(INDEX(Confirmations!$C:$C,MATCH($A6,Confirmations!$A:$A,0)),"") -> Northbay Pension Fund | F6: =IFERROR(INDEX(Booking!$D:$D,MATCH($A6,Booking!$A:$A,0)),"") -> 35000000 | G6: =IFERROR(INDEX(Confirmations!$D:$D,MATCH($A6,Confirmations!$A:$A,0)),"") -> 35000000 | H6: =IFERROR(INDEX(Booking!$E:$E,MATCH($A6,Booking!$A:$A,0)),"") -> 3.365 | I6: =IFERROR(INDEX(Confirmations!$E:$E,MATCH($A6,Confirmations!$A:$A,0)),"") -> 3.365 | J6: =IFERROR(INDEX(Booking!$F:$F,MATCH($A6,Booking!$A:$A,0)),"") -> 3 | K6: =IFERROR(INDEX(Confirmations!$F:$F,MATCH($A6,Confirmations!$A:$A,0)),"") -> 3 | L6: =IF(NOT(C6),"Unconfirmed",IF(NOT(B6),"Unbooked",IF(D6<>E6,"Counterparty",IF(ABS(F6-G6)>F6*Rules!$B$4/10000,"Notional",IF(H6<>I6,"Rate or price",IF(J6<>K6,"Value date","Matched")))))) -> Matched | M6: =IF(B6,INDEX(Booking!$G:$G,MATCH(A6,Booking!$A:$A,0)),INDEX(Confirmations!$G:$G,MATCH(A6,Confirmations!$A:$A,0))) -> 1 | N6: =AND(L6<>"Matched",M6>Rules!$B$5) -> FALSE | O6: =INDEX(Rules!$B$8:$B$14,MATCH(L6,Rules!$A$8:$A$14,0)) -> None
A7: TR-50105 | B7: =ISNUMBER(MATCH(A7,Booking!$A:$A,0)) -> TRUE | C7: =ISNUMBER(MATCH(A7,Confirmations!$A:$A,0)) -> TRUE | D7: =IFERROR(INDEX(Booking!$C:$C,MATCH($A7,Booking!$A:$A,0)),"") -> Meridian Bank | E7: =IFERROR(INDEX(Confirmations!$C:$C,MATCH($A7,Confirmations!$A:$A,0)),"") -> Meridian Bank | F7: =IFERROR(INDEX(Booking!$D:$D,MATCH($A7,Booking!$A:$A,0)),"") -> 38000000 | G7: =IFERROR(INDEX(Confirmations!$D:$D,MATCH($A7,Confirmations!$A:$A,0)),"") -> 38000000 | H7: =IFERROR(INDEX(Booking!$E:$E,MATCH($A7,Booking!$A:$A,0)),"") -> 2.6629 | I7: =IFERROR(INDEX(Confirmations!$E:$E,MATCH($A7,Confirmations!$A:$A,0)),"") -> 2.6629 | J7: =IFERROR(INDEX(Booking!$F:$F,MATCH($A7,Booking!$A:$A,0)),"") -> 2 | K7: =IFERROR(INDEX(Confirmations!$F:$F,MATCH($A7,Confirmations!$A:$A,0)),"") -> 2 | L7: =IF(NOT(C7),"Unconfirmed",IF(NOT(B7),"Unbooked",IF(D7<>E7,"Counterparty",IF(ABS(F7-G7)>F7*Rules!$B$4/10000,"Notional",IF(H7<>I7,"Rate or price",IF(J7<>K7,"Value date","Matched")))))) -> Matched | M7: =IF(B7,INDEX(Booking!$G:$G,MATCH(A7,Booking!$A:$A,0)),INDEX(Confirmations!$G:$G,MATCH(A7,Confirmations!$A:$A,0))) -> 3 | N7: =AND(L7<>"Matched",M7>Rules!$B$5) -> FALSE | O7: =INDEX(Rules!$B$8:$B$14,MATCH(L7,Rules!$A$8:$A$14,0)) -> None
A8: TR-50106 | B8: =ISNUMBER(MATCH(A8,Booking!$A:$A,0)) -> TRUE | C8: =ISNUMBER(MATCH(A8,Confirmations!$A:$A,0)) -> TRUE | D8: =IFERROR(INDEX(Booking!$C:$C,MATCH($A8,Booking!$A:$A,0)),"") -> Meridian Bank | E8: =IFERROR(INDEX(Confirmations!$C:$C,MATCH($A8,Confirmations!$A:$A,0)),"") -> Meridian Bank | F8: =IFERROR(INDEX(Booking!$D:$D,MATCH($A8,Booking!$A:$A,0)),"") -> 50000000 | G8: =IFERROR(INDEX(Confirmations!$D:$D,MATCH($A8,Confirmations!$A:$A,0)),"") -> 50000000 | H8: =IFERROR(INDEX(Booking!$E:$E,MATCH($A8,Booking!$A:$A,0)),"") -> 4.2661 | I8: =IFERROR(INDEX(Confirmations!$E:$E,MATCH($A8,Confirmations!$A:$A,0)),"") -> 4.2661 | J8: =IFERROR(INDEX(Booking!$F:$F,MATCH($A8,Booking!$A:$A,0)),"") -> 1 | K8: =IFERROR(INDEX(Confirmations!$F:$F,MATCH($A8,Confirmations!$A:$A,0)),"") -> 1 | L8: =IF(NOT(C8),"Unconfirmed",IF(NOT(B8),"Unbooked",IF(D8<>E8,"Counterparty",IF(ABS(F8-G8)>F8*Rules!$B$4/10000,"Notional",IF(H8<>I8,"Rate or price",IF(J8<>K8,"Value date","Matched")))))) -> Matched | M8: =IF(B8,INDEX(Booking!$G:$G,MATCH(A8,Booking!$A:$A,0)),INDEX(Confirmations!$G:$G,MATCH(A8,Confirmations!$A:$A,0))) -> 5 | N8: =AND(L8<>"Matched",M8>Rules!$B$5) -> FALSE | O8: =INDEX(Rules!$B$8:$B$14,MATCH(L8,Rules!$A$8:$A$14,0)) -> None
A9: TR-50107 | B9: =ISNUMBER(MATCH(A9,Booking!$A:$A,0)) -> TRUE | C9: =ISNUMBER(MATCH(A9,Confirmations!$A:$A,0)) -> TRUE | D9: =IFERROR(INDEX(Booking!$C:$C,MATCH($A9,Booking!$A:$A,0)),"") -> Kestrel Macro Fund | E9: =IFERROR(INDEX(Confirmations!$C:$C,MATCH($A9,Confirmations!$A:$A,0)),"") -> Kestrel Macro Fund | F9: =IFERROR(INDEX(Booking!$D:$D,MATCH($A9,Booking!$A:$A,0)),"") -> 37000000 | G9: =IFERROR(INDEX(Confirmations!$D:$D,MATCH($A9,Confirmations!$A:$A,0)),"") -> 37000000 | H9: =IFERROR(INDEX(Booking!$E:$E,MATCH($A9,Booking!$A:$A,0)),"") -> 4.6811 | I9: =IFERROR(INDEX(Confirmations!$E:$E,MATCH($A9,Confirmations!$A:$A,0)),"") -> 4.6811 | J9: =IFERROR(INDEX(Booking!$F:$F,MATCH($A9,Booking!$A:$A,0)),"") -> 3 | K9: =IFERROR(INDEX(Confirmations!$F:$F,MATCH($A9,Confirmations!$A:$A,0)),"") -> 3 | L9: =IF(NOT(C9),"Unconfirmed",IF(NOT(B9),"Unbooked",IF(D9<>E9,"Counterparty",IF(ABS(F9-G9)>F9*Rules!$B$4/10000,"Notional",IF(H9<>I9,"Rate or price",IF(J9<>K9,"Value date","Matched")))))) -> Matched | M9: =IF(B9,INDEX(Booking!$G:$G,MATCH(A9,Booking!$A:$A,0)),INDEX(Confirmations!$G:$G,MATCH(A9,Confirmations!$A:$A,0))) -> 1 | N9: =AND(L9<>"Matched",M9>Rules!$B$5) -> FALSE | O9: =INDEX(Rules!$B$8:$B$14,MATCH(L9,Rules!$A$8:$A$14,0)) -> None
A10: TR-50108 | B10: =ISNUMBER(MATCH(A10,Booking!$A:$A,0)) -> TRUE | C10: =ISNUMBER(MATCH(A10,Confirmations!$A:$A,0)) -> TRUE | D10: =IFERROR(INDEX(Booking!$C:$C,MATCH($A10,Booking!$A:$A,0)),"") -> Meridian Bank | E10: =IFERROR(INDEX(Confirmations!$C:$C,MATCH($A10,Confirmations!$A:$A,0)),"") -> Meridian Bank | F10: =IFERROR(INDEX(Booking!$D:$D,MATCH($A10,Booking!$A:$A,0)),"") -> 19000000 | G10: =IFERROR(INDEX(Confirmations!$D:$D,MATCH($A10,Confirmations!$A:$A,0)),"") -> 18769137 | H10: =IFERROR(INDEX(Booking!$E:$E,MATCH($A10,Booking!$A:$A,0)),"") -> 3.0089 | I10: =IFERROR(INDEX(Confirmations!$E:$E,MATCH($A10,Confirmations!$A:$A,0)),"") -> 3.0089 | J10: =IFERROR(INDEX(Booking!$F:$F,MATCH($A10,Booking!$A:$A,0)),"") -> 3 | K10: =IFERROR(INDEX(Confirmations!$F:$F,MATCH($A10,Confirmations!$A:$A,0)),"") -> 3 | L10: =IF(NOT(C10),"Unconfirmed",IF(NOT(B10),"Unbooked",IF(D10<>E10,"Counterparty",IF(ABS(F10-G10)>F10*Rules!$B$4/10000,"Notional",IF(H10<>I10,"Rate or price",IF(J10<>K10,"Value date","Matched")))))) -> Notional | M10: =IF(B10,INDEX(Booking!$G:$G,MATCH(A10,Booking!$A:$A,0)),INDEX(Confirmations!$G:$G,MATCH(A10,Confirmations!$A:$A,0))) -> 0 | N10: =AND(L10<>"Matched",M10>Rules!$B$5) -> FALSE | O10: =INDEX(Rules!$B$8:$B$14,MATCH(L10,Rules!$A$8:$A$14,0)) -> Middle office: amend booking
A11: TR-50109 | B11: =ISNUMBER(MATCH(A11,Booking!$A:$A,0)) -> TRUE | C11: =ISNUMBER(MATCH(A11,Confirmations!$A:$A,0)) -> TRUE | D11: =IFERROR(INDEX(Booking!$C:$C,MATCH($A11,Booking!$A:$A,0)),"") -> Aldridge Capital | E11: =IFERROR(INDEX(Confirmations!$C:$C,MATCH($A11,Confirmations!$A:$A,0)),"") -> Aldridge Capital | F11: =IFERROR(INDEX(Booking!$D:$D,MATCH($A11,Booking!$A:$A,0)),"") -> 50000000 | G11: =IFERROR(INDEX(Confirmations!$D:$D,MATCH($A11,Confirmations!$A:$A,0)),"") -> 50000000 | H11: =IFERROR(INDEX(Booking!$E:$E,MATCH($A11,Booking!$A:$A,0)),"") -> 5.9933 | I11: =IFERROR(INDEX(Confirmations!$E:$E,MATCH($A11,Confirmations!$A:$A,0)),"") -> 5.9933 | J11: =IFERROR(INDEX(Booking!$F:$F,MATCH($A11,Booking!$A:$A,0)),"") -> 1 | K11: =IFERROR(INDEX(Confirmations!$F:$F,MATCH($A11,Confirmations!$A:$A,0)),"") -> 1 | L11: =IF(NOT(C11),"Unconfirmed",IF(NOT(B11),"Unbooked",IF(D11<>E11,"Counterparty",IF(ABS(F11-G11)>F11*Rules!$B$4/10000,"Notional",IF(H11<>I11,"Rate or price",IF(J11<>K11,"Value date","Matched")))))) -> Matched | M11: =IF(B11,INDEX(Booking!$G:$G,MATCH(A11,Booking!$A:$A,0)),INDEX(Confirmations!$G:$G,MATCH(A11,Confirmations!$A:$A,0))) -> 4 | N11: =AND(L11<>"Matched",M11>Rules!$B$5) -> FALSE | O11: =INDEX(Rules!$B$8:$B$14,MATCH(L11,Rules!$A$8:$A$14,0)) -> None
A12: TR-50110 | B12: =ISNUMBER(MATCH(A12,Booking!$A:$A,0)) -> TRUE | C12: =ISNUMBER(MATCH(A12,Confirmations!$A:$A,0)) -> TRUE | D12: =IFERROR(INDEX(Booking!$C:$C,MATCH($A12,Booking!$A:$A,0)),"") -> Aldridge Capital | E12: =IFERROR(INDEX(Confirmations!$C:$C,MATCH($A12,Confirmations!$A:$A,0)),"") -> Aldridge Capital | F12: =IFERROR(INDEX(Booking!$D:$D,MATCH($A12,Booking!$A:$A,0)),"") -> 21000000 | G12: =IFERROR(INDEX(Confirmations!$D:$D,MATCH($A12,Confirmations!$A:$A,0)),"") -> 21000000 | H12: =IFERROR(INDEX(Booking!$E:$E,MATCH($A12,Booking!$A:$A,0)),"") -> 5.1547 | I12: =IFERROR(INDEX(Confirmations!$E:$E,MATCH($A12,Confirmations!$A:$A,0)),"") -> 5.1547 | J12: =IFERROR(INDEX(Booking!$F:$F,MATCH($A12,Booking!$A:$A,0)),"") -> 2 | K12: =IFERROR(INDEX(Confirmations!$F:$F,MATCH($A12,Confirmations!$A:$A,0)),"") -> 2 | L12: =IF(NOT(C12),"Unconfirmed",IF(NOT(B12),"Unbooked",IF(D12<>E12,"Counterparty",IF(ABS(F12-G12)>F12*Rules!$B$4/10000,"Notional",IF(H12<>I12,"Rate or price",IF(J12<>K12,"Value date","Matched")))))) -> Matched | M12: =IF(B12,INDEX(Booking!$G:$G,MATCH(A12,Booking!$A:$A,0)),INDEX(Confirmations!$G:$G,MATCH(A12,Confirmations!$A:$A,0))) -> 3 | N12: =AND(L12<>"Matched",M12>Rules!$B$5) -> FALSE | O12: =INDEX(Rules!$B$8:$B$14,MATCH(L12,Rules!$A$8:$A$14,0)) -> None
A13: TR-50111 | B13: =ISNUMBER(MATCH(A13,Booking!$A:$A,0)) -> TRUE | C13: =ISNUMBER(MATCH(A13,Confirmations!$A:$A,0)) -> TRUE | D13: =IFERROR(INDEX(Booking!$C:$C,MATCH($A13,Booking!$A:$A,0)),"") -> Aldridge Capital | E13: =IFERROR(INDEX(Confirmations!$C:$C,MATCH($A13,Confirmations!$A:$A,0)),"") -> Aldridge Capital | F13: =IFERROR(INDEX(Booking!$D:$D,MATCH($A13,Booking!$A:$A,0)),"") -> 43000000 | G13: =IFERROR(INDEX(Confirmations!$D:$D,MATCH($A13,Confirmations!$A:$A,0)),"") -> 43000000 | H13: =IFERROR(INDEX(Booking!$E:$E,MATCH($A13,Booking!$A:$A,0)),"") -> 3.1705 | I13: =IFERROR(INDEX(Confirmations!$E:$E,MATCH($A13,Confirmations!$A:$A,0)),"") -> 3.1705 | J13: =IFERROR(INDEX(Booking!$F:$F,MATCH($A13,Booking!$A:$A,0)),"") -> 3 | K13: =IFERROR(INDEX(Confirmations!$F:$F,MATCH($A13,Confirmations!$A:$A,0)),"") -> 3 | L13: =IF(NOT(C13),"Unconfirmed",IF(NOT(B13),"Unbooked",IF(D13<>E13,"Counterparty",IF(ABS(F13-G13)>F13*Rules!$B$4/10000,"Notional",IF(H13<>I13,"Rate or price",IF(J13<>K13,"Value date","Matched")))))) -> Matched | M13: =IF(B13,INDEX(Booking!$G:$G,MATCH(A13,Booking!$A:$A,0)),INDEX(Confirmations!$G:$G,MATCH(A13,Confirmations!$A:$A,0))) -> 6 | N13: =AND(L13<>"Matched",M13>Rules!$B$5) -> FALSE | O13: =INDEX(Rules!$B$8:$B$14,MATCH(L13,Rules!$A$8:$A$14,0)) -> None
... A241: TR-50339 | B241: =ISNUMBER(MATCH(A241,Booking!$A:$A,0)) -> TRUE | C241: =ISNUMBER(MATCH(A241,Confirmations!$A:$A,0)) -> TRUE | D241: =IFERROR(INDEX(Booking!$C:$C,MATCH($A241,Booking!$A:$A,0)),"") -> Tarn Energy Trading | E241: =IFERROR(INDEX(Confirmations!$C:$C,MATCH($A241,Confirmations!$A:$A,0)),"") -> Tarn Energy Trading | F241: =IFERROR(INDEX(Booking!$D:$D,MATCH($A241,Booking!$A:$A,0)),"") -> 34000000 | G241: =IFERROR(INDEX(Confirmations!$D:$D,MATCH($A241,Confirmations!$A:$A,0)),"") -> 34000000 | H241: =IFERROR(INDEX(Booking!$E:$E,MATCH($A241,Booking!$A:$A,0)),"") -> 3.683 | I241: =IFERROR(INDEX(Confirmations!$E:$E,MATCH($A241,Confirmations!$A:$A,0)),"") -> 3.683 | J241: =IFERROR(INDEX(Booking!$F:$F,MATCH($A241,Booking!$A:$A,0)),"") -> 3 | K241: =IFERROR(INDEX(Confirmations!$F:$F,MATCH($A241,Confirmations!$A:$A,0)),"") -> 3 | L241: =IF(NOT(C241),"Unconfirmed",IF(NOT(B241),"Unbooked",IF(D241<>E241,"Counterparty",IF(ABS(F241-G241)>F241*Rules!$B$4/10000,"Notional",IF(H241<>I241,"Rate or price",IF(J241<>K241,"Value date","Matched")))))) -> Matched | M241: =IF(B241,INDEX(Booking!$G:$G,MATCH(A241,Booking!$A:$A,0)),INDEX(Confirmations!$G:$G,MATCH(A241,Confirmations!$A:$A,0))) -> 1 | N241: =AND(L241<>"Matched",M241>Rules!$B$5) -> FALSE | O241: =INDEX(Rules!$B$8:$B$14,MATCH(L241,Rules!$A$8:$A$14,0)) -> None
